Workbook
Name Proteina: 'Base dados dieta'!$A$2:$F$198
Name Suplementação: #REF!

Sheet Base
C1: Nome: | G1: Suplementos Recomendados:
C2: Próxima atualização: | G2: Ver folha de suplementos
C3: Fim do Pack:
A5: DADOS PESSOAIS | D5: HOMEM | K5: METAS DIÁRIAS | O5: Calculo Macros
A6: Peso | D6: Taxa Metabólica Basal | E6: Peso(kg) | F6: Altura(cm) | G6: Idade | H6: Nivel Actividade Fisica | I6: Ajuste | K6: Kcal | L6: =D7+I7 -> 0 | O6: Kcal diárias
A7: Altura | D7: =(10*B6+6.25*B7-5*B8+5)*B9 -> 0 | E7: =B6 -> 0 | F7: =B7 -> 0 | G7: =B8 -> 0 | H7: =B9 -> 0 | K7: Proteina | L7: =(L21*B6) -> 0 | M7: =(L22*B6) -> 0 | P7: Proteina | Q7: Gordura | R7: Hidratos
A8: Idade | K8: Gordura | L8: =(K21*B6) -> 0 | M8: =(K22*B6) -> 0 | O8: Objectivo (g/kg) | P8: 2.3 | Q8: 0.8 | R8: 5
A9: Tipo actividade fisica | K9: Hidratos | L9: =(L6-((M7*4)+(M8*9)))/4 -> 0 | M9: =(L6-((L7*4)+(L8*9)))/4 -> 0 | O9: Total (gramas) | P9: =P8*E7 -> 0 | Q9: =Q8*E7 -> 0 | R9: =R8*E7 -> 0 | T9: =(P9*4)+(Q9*9)+(R9*4) -> 0
O10: Total (% Kcal) | P10: =(P9*4)/T9*100 -> #DIV/0! | Q10: =(Q9*9)/T9*100 -> #DIV/0! | R10: =(R9*4)/T9*100 -> #DIV/0!
A11: OBJETIVO | D11: MULHER | K11: METAS DIÁRIAS
A12: Ganhar massa muscular e melhorar mobilidade | D12: Taxa Metabólica Basal | E12: Peso(kg) | F12: Altura(cm) | G12: Idade | H12: Nivel Actividade Fisica | I12: Ajuste | K12: Kcal | L12: =D13+I13 -> 0 | O12: Objectivo (%) | P12: 25 | Q12: 20 | R12: 55
D13: =(10*B6+6.25*B7-5*B8-161)*B9 -> 0 | E13: =B6 -> 0 | F13: =B7 -> 0 | G13: =B8 -> 0 | H13: =B9 -> 0 | K13: Proteina | L13: =(L21*B6) -> 0 | M13: =(L22*B6) -> 0 | O13: Total (gramas) | P13: =(Q6*(P12/100)/4) -> 0 | Q13: =(Q6*(Q12/100)/9) -> 0 | R13: =(Q6*(R12/100)/4) -> 0 | T13: =(P13*4)+(Q13*9)+(R13*4) -> 0
A14: Limitações | K14: Gordura | L14: =(K21*B6) -> 0 | M14: =(K22*B6) -> 0 | O14: Total (g/kg) | P14: =P13/E7 -> #DIV/0! | Q14: =Q13/E7 -> #DIV/0! | R14: =R13/E7 -> #DIV/0!
A15: Trombo na perna que apanhou os dois pulmões | K15: Hidratos | L15: =(L12-((M13*4)+(M14*9)))/4 -> 0 | M15: =(L12-((L13*4)+(L14*9)))/4 -> 0
A16: Artrite | O16: Macros a utilizar
D17: Nivel Actividade Fisica
D18: 1. Sedentários = 1.2 (pouco ou nenhum exercício)
A19: Observações | D19: 2. Levemente ativo = 1.375 (exercício leve 1 a 3 dias por semana) | K19: Consumos
A20: Treino | D20: 3. Moderadamente ativo = 1.55 (exercício moderado, faz desporto 3 a 5 dias por semana) | K20: Gordura | L20: Proteina
A21: Frequência semanal | D21: 4. Altamente ativo = 1.725 (exercício pesado de 5 a 6 dias por semana) | K21: 0.5 | L21: 1.6
A22: Duração treino | D22: 5. Extremamente ativo = 1.9 (exercício pesado diariamente e até 2 vezes por dia) | K22: 1 | L22: 2.2
A23: Alimentação
A24: Rótulo | D24: CUPÃO DE DESCONTO NA PROZIS | I24: Ganhos de músculo
A25: Contou Kcal | I25: Mês | J25: homem | L25: mulher
A26: Balança cozinha | D26: http://prozis.com/nBW7 | I26: Iniciantes | J26: 1 | K26: 1.5 | L26: 0.5 | M26: 0.75
A27: Sono | I27: Intermediários | J27: 0.5 | K27: 1 | L27: 0.25 | M27: 0.5
A28: Hidratação | D28: Pontos Chave Alimentação | I28: Avançados | J28: 0.25 | K28: 0.5 | L28: 0.125 | M28: 0.25
A29: Compromisso | D29: 20-40g Proteina por refeição (ou 0,25-0,4g/kg) entre cada 3-4h | I29: gramas/semana | J29: homem | L29: mulher
A30: Perspectiva | D30: 3-6 refeições por dia | I30: Iniciantes | J30: =J26%*B6/4.2*1000 -> 0 | K30: =K26%*B6/4.2*1000 -> 0 | L30: =L26%*B6/4.2*1000 -> 0 | M30: =M26%*B6/4.2*1000 -> 0
D31: 40-50% dos hidratos diários consumidos nas refeições antes e depois do treino | I31: Intermediários | J31: =J27%*B6/4.2*1000 -> 0 | K31: =K27%*B6/4.2*1000 -> 0 | L31: =L27%*B6/4.2*1000 -> 0 | M31: =M27%*B6/4.2*1000 -> 0
D32: Consumir 10g de Fibra por cada 1000kcal | I32: Avançados | J32: =J28%*B6/4.2*1000 -> 0 | K32: =K28%*B6/4.2*1000 -> 0 | L32: =L28%*B6/4.2*1000 -> 0 | M32: =M28%*B6/4.2*1000 -> 0
D33: 2 Porções de fruta e 2 de Vegetais
I34: Perda peso
D35: Refeição até uma hora antes do treino | I35: Mês | J35: % peso a perder | L35: IMC
D36: Mais Hidratos | I36: Obeso | J36: 3 | K36: 4 | L36: =B6/(B7*B7*0.0001) -> #DIV/0!
D37: Menos Gordura | I37: Excesso peso | J37: 2 | K37: 3
D38: Menos Fibra | I38: Normal | J38: 1 | K38: 2
D39: Razoavel Proteina | I39: Atlético | J39: 0.5 | K39: 1
I40: Gramas perdidas por semana
I41: Obeso | J41: =J36%*B6*1000 -> 0 | K41: =K36%*B6*1000 -> 0
I42: Excesso peso | J42: =J37%*B6*1000 -> 0 | K42: =K37%*B6*1000 -> 0
I43: Normal | J43: =J38%*B6*1000 -> 0 | K43: =K38%*B6*1000 -> 0
I44: Atlético | J44: =J39%*B6*1000 -> 0 | K44: =K39%*B6*1000 -> 0

Sheet Controle de medidas
A1: Data | C1: Semana | D1: Fase | E1: diário | F1: média | G1: Dif | H1: % | I1: Passos | K1: Horas de sono | M1: Stress | N1: Energia | O1: Fome | P1: Meta | Q1: ingerido | R1: média | S1: diferença | T1: Hidratos (gr) | U1: Meta Hidratos | V1: Média semanal | W1: Proteína (gr) | X1: Meta Proteína | Y1: Média semanal | Z1: Gordura (gr) | AA1: Meta Gordura | AB1: Média semanal | AC1: Fibra
E2: Peso | I2: diário | J2: média | K2: diário | L2: média | M2: (1-5) | N2: (1-5) | O2: (1-5) | P2: Kcal | T2: Macros
A3: s | C3: 1 | F3: =AVERAGE(E3:E9) -> #DIV/0! | J3: =AVERAGE(I3:I9) -> #DIV/0! | L3: =AVERAGE(K3:K9) -> #DIV/0! | R3: =AVERAGE(Q3:Q9) -> #DIV/0! | S3: =R3-P3 -> #DIV/0! | U3: =(P3-(X3*4+AA3*9))/4 -> 0 | V3: =AVERAGE(T3:T9) -> #DIV/0! | Y3: =AVERAGE(W3:W9) -> #DIV/0! | AB3: =AVERAGE(Z3:Z9) -> #DIV/0!
A4: d | B4: =1+B3 -> 1
A5: s | B5: =1+B4 -> 2
A6: t | B6: =1+B5 -> 3
A7: q | B7: =1+B6 -> 4
A8: q | B8: =1+B7 -> 5
A9: s | B9: =1+B8 -> 6
A10: s | B10: =1+B9 -> 7 | C10: =1+C3 -> 2 | F10: =AVERAGE(E10:E16) -> #DIV/0! | G10: =F10-F3 -> #DIV/0! | H10: =(F10*100/F3)-100 -> #DIV/0! | J10: =AVERAGE(I10:I16) -> #DIV/0! | L10: =AVERAGE(K10:K16) -> #DIV/0! | R10: =AVERAGE(Q10:Q16) -> #DIV/0! | S10: =R10-P10 -> #DIV/0! | U10: =(P10-(X10*4+AA10*9))/4 -> 0 | V10: =AVERAGE(T10:T16) -> #DIV/0! | Y10: =AVERAGE(W10:W16) -> #DIV/0! | AB10: =AVERAGE(Z10:Z16) -> #DIV/0!
A11: d | B11: =1+B10 -> 8
A12: s | B12: =1+B11 -> 9
A13: t | B13: =1+B12 -> 10
A14: q | B14: =1+B13 -> 11
A15: q | B15: =1+B14 -> 12
A16: s | B16: =1+B15 -> 13
A17: s | B17: =1+B16 -> 14 | C17: =1+C10 -> 3 | F17: =AVERAGE(E17:E23) -> #DIV/0! | G17: =F17-F10 -> #DIV/0! | H17: =(F17*100/F10)-100 -> #DIV/0! | J17: =AVERAGE(I17:I23) -> #DIV/0! | L17: =AVERAGE(K17:K23) -> #DIV/0! | R17: =AVERAGE(Q17:Q23) -> #DIV/0! | S17: =R17-P17 -> #DIV/0! | U17: =(P17-(X17*4+AA17*9))/4 -> 0 | V17: =AVERAGE(T17:T23) -> #DIV/0! | Y17: =AVERAGE(W17:W23) -> #DIV/0! | AB17: =AVERAGE(Z17:Z23) -> #DIV/0!
A18: d | B18: =1+B17 -> 15
A19: s | B19: =1+B18 -> 16
A20: t | B20: =1+B19 -> 17
A21: q | B21: =1+B20 -> 18
A22: q | B22: =1+B21 -> 19
A23: s | B23: =1+B22 -> 20
A24: s | B24: =1+B23 -> 21 | C24: =1+C17 -> 4 | F24: =AVERAGE(E24:E30) -> #DIV/0! | G24: =F24-F17 -> #DIV/0! | H24: =(F24*100/F17)-100 -> #DIV/0! | J24: =AVERAGE(I24:I30) -> #DIV/0! | L24: =AVERAGE(K24:K30) -> #DIV/0! | R24: =AVERAGE(Q24:Q30) -> #DIV/0! | S24: =R24-P24 -> #DIV/0! | U24: =(P24-(X24*4+AA24*9))/4 -> 0 | V24: =AVERAGE(T24:T30) -> #DIV/0! | Y24: =AVERAGE(W24:W30) -> #DIV/0! | AB24: =AVERAGE(Z24:Z30) -> #DIV/0!
A25: d | B25: =1+B24 -> 22
A26: s | B26: =1+B25 -> 23
A27: t | B27: =1+B26 -> 24
A28: q | B28: =1+B27 -> 25
A29: q | B29: =1+B28 -> 26
A30: s | B30: =1+B29 -> 27
A31: s | B31: =1+B30 -> 28 | C31: =1+C24 -> 5 | F31: =AVERAGE(E31:E37) -> #DIV/0! | G31: =F31-F24 -> #DIV/0! | H31: =(F31*100/F24)-100 -> #DIV/0! | J31: =AVERAGE(I31:I37) -> #DIV/0! | L31: =AVERAGE(K31:K37) -> #DIV/0! | R31: =AVERAGE(Q31:Q37) -> #DIV/0! | S31: =R31-P31 -> #DIV/0! | U31: =(P31-(X31*4+AA31*9))/4 -> 0 | V31: =AVERAGE(T31:T37) -> #DIV/0! | Y31: =AVERAGE(W31:W37) -> #DIV/0! | AB31: =AVERAGE(Z31:Z37) -> #DIV/0!
A32: d | B32: =1+B31 -> 29
A33: s | B33: =1+B32 -> 30
A34: t | B34: =1+B33 -> 31
A35: q | B35: =1+B34 -> 32
A36: q | B36: =1+B35 -> 33
A37: s | B37: =1+B36 -> 34
A38: s | B38: =1+B37 -> 35 | C38: =1+C31 -> 6 | F38: =AVERAGE(E38:E44) -> #DIV/0! | G38: =F38-F31 -> #DIV/0! | H38: =(F38*100/F31)-100 -> #DIV/0! | J38: =AVERAGE(I38:I44) -> #DIV/0! | L38: =AVERAGE(K38:K44) -> #DIV/0! | R38: =AVERAGE(Q38:Q44) -> #DIV/0! | S38: =R38-P38 -> #DIV/0! | U38: =(P38-(X38*4+AA38*9))/4 -> 0 | V38: =AVERAGE(T38:T44) -> #DIV/0! | Y38: =AVERAGE(W38:W44) -> #DIV/0! | AB38: =AVERAGE(Z38:Z44) -> #DIV/0!
A39: d | B39: =1+B38 -> 36
A40: s | B40: =1+B39 -> 37
A41: t | B41: =1+B40 -> 38
A42: q | B42: =1+B41 -> 39
A43: q | B43: =1+B42 -> 40
A44: s | B44: =1+B43 -> 41
A45: s | B45: =1+B44 -> 42 | C45: =1+C38 -> 7 | F45: =AVERAGE(E45:E51) -> #DIV/0! | G45: =F45-F38 -> #DIV/0! | H45: =(F45*100/F38)-100 -> #DIV/0! | J45: =AVERAGE(I45:I51) -> #DIV/0! | L45: =AVERAGE(K45:K51) -> #DIV/0! | R45: =AVERAGE(Q45:Q51) -> #DIV/0! | S45: =R45-P45 -> #DIV/0! | U45: =(P45-(X45*4+AA45*9))/4 -> 0 | V45: =AVERAGE(T45:T51) -> #DIV/0! | Y45: =AVERAGE(W45:W51) -> #DIV/0! | AB45: =AVERAGE(Z45:Z51) -> #DIV/0!
A46: d | B46: =1+B45 -> 43
A47: s | B47: =1+B46 -> 44
A48: t | B48: =1+B47 -> 45
A49: q | B49: =1+B48 -> 46
A50: q | B50: =1+B49 -> 47
A51: s | B51: =1+B50 -> 48
A52: s | B52: =1+B51 -> 49 | C52: =1+C45 -> 8 | F52: =AVERAGE(E52:E58) -> #DIV/0! | G52: =F52-F45 -> #DIV/0! | H52: =(F52*100/F45)-100 -> #DIV/0! | J52: =AVERAGE(I52:I58) -> #DIV/0! | L52: =AVERAGE(K52:K58) -> #DIV/0! | R52: =AVERAGE(Q52:Q58) -> #DIV/0! | S52: =R52-P52 -> #DIV/0! | U52: =(P52-(X52*4+AA52*9))/4 -> 0 | V52: =AVERAGE(T52:T58) -> #DIV/0! | Y52: =AVERAGE(W52:W58) -> #DIV/0! | AB52: =AVERAGE(Z52:Z58) -> #DIV/0!
A53: d | B53: =1+B52 -> 50
A54: s | B54: =1+B53 -> 51
A55: t | B55: =1+B54 -> 52
A56: q | B56: =1+B55 -> 53
A57: q | B57: =1+B56 -> 54
A58: s | B58: =1+B57 -> 55

Sheet Perimetros
A1: Perimetros
D2: Objectivo:
D3: Data proximo update:
A4: Diferenças | C4: =C8-C7 -> 0 | D4: =D8-D7 -> 0 | E4: =E8-E7 -> 0 | F4: =F8-F7 -> 0 | H4: =H8-H7 -> 0 | K4: =K8-K7 -> 0
A6: Semana | B6: Data | C6: Peso | D6: Cintura | E6: Glúteo | F6: Coxa Drt. | G6: Coxa Esq. | H6: Braço Drt. | I6: Braço Esq. | J6: Gémeo Drt | K6: Gémeo Esq.

Sheet Plano treino
H1: Plano de Treino | Q1: Semana 1 | AE1: Semana 2 | AT1: Semana 3 | BI1: Semana 4 | BX1: Semana 5 | CM1: Semana 6 | DB1: Semana 7 | DQ1: Semana 8
Q2: Power inicial | R2: 1 | U2: 2 | X2: 3 | AA2: 4 | AD2: Total | AE2: Power inicial | AF2: 1 | AI2: 2 | AL2: 3 | AO2: 4 | AR2: Total | AT2: Power inicial | AU2: 1 | AX2: 2 | BA2: 3 | BD2: 4 | BG2: Total | BI2: Power inicial | BJ2: 1 | BM2: 2 | BP2: 3 | BS2: 4 | BV2: Total | BX2: Power inicial | BY2: 1 | CB2: 2 | CE2: 3 | CH2: 4 | CK2: Total | CM2: Power inicial | CN2: 1 | CQ2: 2 | CT2: 3 | CW2: 4 | CZ2: Total | DB2: Power inicial | DC2: 1 | DF2: 2 | DI2: 3 | DL2: 4 | DO2: Total | DQ2: Power inicial | DR2: 1 | DU2: 2 | DX2: 3 | EA2: 4 | ED2: Total
A3: 1 | B3: 1 | C3: 1 | D3: 0.5 | E3: 0.5 | F3: 0.3 | H3: MÚSCULO | I3: TOTAL DE SERIES | K3: TREINO | L3: EXERCÍCIO | M3: Video | N3: Séries | O3: Reps | P3: Descanso | R3: R | S3: C | T3: F | U3: R | V3: C | W3: F | X3: R | Y3: C | Z3: F | AA3: R | AB3: C | AC3: F | AF3: R | AG3: C | AH3: F | AI3: R | AJ3: C | AK3: F | AL3: R | AM3: C | AN3: F | AO3: R | AP3: C | AQ3: F | AR3: Sem. | AS3: Dif. | AU3: R | AV3: C | AW3: F | AX3: R | AY3: C | AZ3: F | BA3: R | BB3: C | BC3: F | BD3: R | BE3: C | BF3: F | BG3: Sem. | BH3: Dif. | BJ3: R | BK3: C | BL3: F | BM3: R | BN3: C | BO3: F | BP3: R | BQ3: C | BR3: F | BS3: R | BT3: C | BU3: F | BV3: Sem. | BW3: Dif. | BY3: R | BZ3: C | CA3: F | CB3: R | CC3: C | CD3: F | CE3: R | CF3: C | CG3: F | CH3: R | CI3: C | CJ3: F | CK3: Sem. | CL3: Dif. | CN3: R | CO3: C | CP3: F | CQ3: R | CR3: C | CS3: F | CT3: R | CU3: C | CV3: F | CW3: R | CX3: C | CY3: F | CZ3: Sem. | DA3: Dif. | DC3: R | DD3: C | DE3: F | DF3: R | DG3: C | DH3: F | DI3: R | DJ3: C | DK3: F | DL3: R | DM3: C | DN3: F | DO3: Sem. | DP3: Dif. | DR3: R | DS3: C | DT3: F | DU3: R | DV3: C | DW3: F | DX3: R | DY3: C | DZ3: F | EA3: R | EB3: C | EC3: F | ED3: Sem. | EE3: Dif.
A4: =IFERROR(VLOOKUP(L4,'Base dados Exercicios'!$C$4:$J$305,3,FALSE),"") | B4: =IFERROR(VLOOKUP(L4,'Base dados Exercicios'!$C$4:$J$305,4,FALSE),"") | C4: =IFERROR(VLOOKUP(L4,'Base dados Exercicios'!$C$4:$J$305,5,FALSE),"") | D4: =IFERROR(VLOOKUP(L4,'Base dados Exercicios'!$C$4:$J$305,6,FALSE),"") | E4: =IFERROR(VLOOKUP(L4,'Base dados Exercicios'!$C$4:$J$305,7,FALSE),"") | F4: =IFERROR(VLOOKUP(L4,'Base dados Exercicios'!$C$4:$J$305,8,FALSE),"") | H4: ='Base dados Exercicios'!L4 -> Biceps | I4: =SUMIF($A$4:$A$102,H4,$N$4:$N$102)+SUMIF($B$4:B$102,H4,$N$4:$N$102)+SUMIF($C$4:$C$102,H4,$N$4:$N$102)+(SUMIF($D$4:$D$102,H4,$N$4:$N$102)*0.5)+(SUMIF($E$4:$E$102,H4,$N$4:$N$102)*0.5)+(SUMIF($F$4:F$102,H4,$N$4:$N$102)*0.3) -> 0 | K4: 1 | M4: =IF(L4<>"", HYPERLINK(VLOOKUP(L4,'Base dados Exercicios'!$C$4:$D$83,2,FALSE),"Check"),"") | AD4: =(R4*S4)+(U4*V4)+(X4*Y4)+(AA4*AB4) -> 0 | AR4: =(AF4*AG4)+(AI4*AJ4)+(AL4*AM4)+(AO4*AP4) -> 0 | AS4: =AR4-AD4 -> 0 | BG4: =(AU4*AV4)+(AX4*AY4)+(BA4*BB4)+(BD4*BE4) -> 0 | BH4: =BG4-AR4 -> 0 | BV4: =(BJ4*BK4)+(BM4*BN4)+(BP4*BQ4)+(BS4*BT4) -> 0 | BW4: =BV4-BG4 -> 0 | CK4: =(BY4*BZ4)+(CB4*CC4)+(CE4*CF4)+(CH4*CI4) -> 0 | CL4: =CK4-BV4 -> 0 | CZ4: =(CN4*CO4)+(CQ4*CR4)+(CT4*CU4)+(CW4*CX4) -> 0 | DA4: =CZ4-CK4 -> 0 | DO4: =(DC4*DD4)+(DF4*DG4)+(DI4*DJ4)+(DL4*DM4) -> 0 | DP4: =DO4-CZ4 -> 0 | ED4: =(DR4*DS4)+(DU4*DV4)+(DX4*DY4)+(EA4*EB4) -> 0 | EE4: =ED4-DO4 -> 0
A5: =IFERROR(VLOOKUP(L5,'Base dados Exercicios'!$C$4:$J$305,3,FALSE),"") | B5: =IFERROR(VLOOKUP(L5,'Base dados Exercicios'!$C$4:$J$305,4,FALSE),"") | C5: =IFERROR(VLOOKUP(L5,'Base dados Exercicios'!$C$4:$J$305,5,FALSE),"") | D5: =IFERROR(VLOOKUP(L5,'Base dados Exercicios'!$C$4:$J$305,6,FALSE),"") | E5: =IFERROR(VLOOKUP(L5,'Base dados Exercicios'!$C$4:$J$305,7,FALSE),"") | F5: =IFERROR(VLOOKUP(L5,'Base dados Exercicios'!$C$4:$J$305,8,FALSE),"") | H5: ='Base dados Exercicios'!L5 -> Dorsal | I5: =SUMIF($A$4:$A$102,H5,$N$4:$N$102)+SUMIF($B$4:B$102,H5,$N$4:$N$102)+SUMIF($C$4:$C$102,H5,$N$4:$N$102)+(SUMIF($D$4:$D$102,H5,$N$4:$N$102)*0.5)+(SUMIF($E$4:$E$102,H5,$N$4:$N$102)*0.5)+(SUMIF($F$4:F$102,H5,$N$4:$N$102)*0.3) -> 0 | M5: =IF(L5<>"", HYPERLINK(VLOOKUP(L5,'Base dados Exercicios'!$C$4:$D$83,2,FALSE),"Check"),"") | AD5: =(R5*S5)+(U5*V5)+(X5*Y5)+(AA5*AB5) -> 0 | AR5: =(AF5*AG5)+(AI5*AJ5)+(AL5*AM5)+(AO5*AP5) -> 0 | AS5: =AR5-AD5 -> 0 | BG5: =(AU5*AV5)+(AX5*AY5)+(BA5*BB5)+(BD5*BE5) -> 0 | BH5: =BG5-AR5 -> 0 | BV5: =(BJ5*BK5)+(BM5*BN5)+(BP5*BQ5)+(BS5*BT5) -> 0 | BW5: =BV5-BG5 -> 0 | CK5: =(BY5*BZ5)+(CB5*CC5)+(CE5*CF5)+(CH5*CI5) -> 0 | CL5: =CK5-BV5 -> 0 | CZ5: =(CN5*CO5)+(CQ5*CR5)+(CT5*CU5)+(CW5*CX5) -> 0 | DA5: =CZ5-CK5 -> 0 | DO5: =(DC5*DD5)+(DF5*DG5)+(DI5*DJ5)+(DL5*DM5) -> 0 | DP5: =DO5-CZ5 -> 0 | ED5: =(DR5*DS5)+(DU5*DV5)+(DX5*DY5)+(EA5*EB5) -> 0 | EE5: =ED5-DO5 -> 0
A6: =IFERROR(VLOOKUP(L6,'Base dados Exercicios'!$C$4:$J$305,3,FALSE),"") | B6: =IFERROR(VLOOKUP(L6,'Base dados Exercicios'!$C$4:$J$305,4,FALSE),"") | C6: =IFERROR(VLOOKUP(L6,'Base dados Exercicios'!$C$4:$J$305,5,FALSE),"") | D6: =IFERROR(VLOOKUP(L6,'Base dados Exercicios'!$C$4:$J$305,6,FALSE),"") | E6: =IFERROR(VLOOKUP(L6,'Base dados Exercicios'!$C$4:$J$305,7,FALSE),"") | F6: =IFERROR(VLOOKUP(L6,'Base dados Exercicios'!$C$4:$J$305,8,FALSE),"") | H6: ='Base dados Exercicios'!L6 -> Ombro frontal | I6: =SUMIF($A$4:$A$102,H6,$N$4:$N$102)+SUMIF($B$4:B$102,H6,$N$4:$N$102)+SUMIF($C$4:$C$102,H6,$N$4:$N$102)+(SUMIF($D$4:$D$102,H6,$N$4:$N$102)*0.5)+(SUMIF($E$4:$E$102,H6,$N$4:$N$102)*0.5)+(SUMIF($F$4:F$102,H6,$N$4:$N$102)*0.3) -> 0 | M6: =IF(L6<>"", HYPERLINK(VLOOKUP(L6,'Base dados Exercicios'!$C$4:$D$83,2,FALSE),"Check"),"") | AD6: =(R6*S6)+(U6*V6)+(X6*Y6)+(AA6*AB6) -> 0 | AR6: =(AF6*AG6)+(AI6*AJ6)+(AL6*AM6)+(AO6*AP6) -> 0 | AS6: =AR6-AD6 -> 0 | BG6: =(AU6*AV6)+(AX6*AY6)+(BA6*BB6)+(BD6*BE6) -> 0 | BH6: =BG6-AR6 -> 0 | BV6: =(BJ6*BK6)+(BM6*BN6)+(BP6*BQ6)+(BS6*BT6) -> 0 | BW6: =BV6-BG6 -> 0 | CK6: =(BY6*BZ6)+(CB6*CC6)+(CE6*CF6)+(CH6*CI6) -> 0 | CL6: =CK6-BV6 -> 0 | CZ6: =(CN6*CO6)+(CQ6*CR6)+(CT6*CU6)+(CW6*CX6) -> 0 | DA6: =CZ6-CK6 -> 0 | DO6: =(DC6*DD6)+(DF6*DG6)+(DI6*DJ6)+(DL6*DM6) -> 0 | DP6: =DO6-CZ6 -> 0 | ED6: =(DR6*DS6)+(DU6*DV6)+(DX6*DY6)+(EA6*EB6) -> 0 | EE6: =ED6-DO6 -> 0
A7: =IFERROR(VLOOKUP(L7,'Base dados Exercicios'!$C$4:$J$305,3,FALSE),"") | B7: =IFERROR(VLOOKUP(L7,'Base dados Exercicios'!$C$4:$J$305,4,FALSE),"") | C7: =IFERROR(VLOOKUP(L7,'Base dados Exercicios'!$C$4:$J$305,5,FALSE),"") | D7: =IFERROR(VLOOKUP(L7,'Base dados Exercicios'!$C$4:$J$305,6,FALSE),"") | E7: =IFERROR(VLOOKUP(L7,'Base dados Exercicios'!$C$4:$J$305,7,FALSE),"") | F7: =IFERROR(VLOOKUP(L7,'Base dados Exercicios'!$C$4:$J$305,8,FALSE),"") | H7: ='Base dados Exercicios'!L11 -> Triceps | I7: =SUMIF($A$4:$A$102,H7,$N$4:$N$102)+SUMIF($B$4:B$102,H7,$N$4:$N$102)+SUMIF($C$4:$C$102,H7,$N$4:$N$102)+(SUMIF($D$4:$D$102,H7,$N$4:$N$102)*0.5)+(SUMIF($E$4:$E$102,H7,$N$4:$N$102)*0.5)+(SUMIF($F$4:F$102,H7,$N$4:$N$102)*0.3) -> 0 | M7: =IF(L7<>"", HYPERLINK(VLOOKUP(L7,'Base dados Exercicios'!$C$4:$D$83,2,FALSE),"Check"),"") | AD7: =(R7*S7)+(U7*V7)+(X7*Y7)+(AA7*AB7) -> 0 | AR7: =(AF7*AG7)+(AI7*AJ7)+(AL7*AM7)+(AO7*AP7) -> 0 | AS7: =AR7-AD7 -> 0 | BG7: =(AU7*AV7)+(AX7*AY7)+(BA7*BB7)+(BD7*BE7) -> 0 | BH7: =BG7-AR7 -> 0 | BV7: =(BJ7*BK7)+(BM7*BN7)+(BP7*BQ7)+(BS7*BT7) -> 0 | BW7: =BV7-BG7 -> 0 | CK7: =(BY7*BZ7)+(CB7*CC7)+(CE7*CF7)+(CH7*CI7) -> 0 | CL7: =CK7-BV7 -> 0 | CZ7: =(CN7*CO7)+(CQ7*CR7)+(CT7*CU7)+(CW7*CX7) -> 0 | DA7: =CZ7-CK7 -> 0 | DO7: =(DC7*DD7)+(DF7*DG7)+(DI7*DJ7)+(DL7*DM7) -> 0 | DP7: =DO7-CZ7 -> 0 | ED7: =(DR7*DS7)+(DU7*DV7)+(DX7*DY7)+(EA7*EB7) -> 0 | EE7: =ED7-DO7 -> 0
A8: =IFERROR(VLOOKUP(L8,'Base dados Exercicios'!$C$4:$J$305,3,FALSE),"") | B8: =IFERROR(VLOOKUP(L8,'Base dados Exercicios'!$C$4:$J$305,4,FALSE),"") | C8: =IFERROR(VLOOKUP(L8,'Base dados Exercicios'!$C$4:$J$305,5,FALSE),"") | D8: =IFERROR(VLOOKUP(L8,'Base dados Exercicios'!$C$4:$J$305,6,FALSE),"") | E8: =IFERROR(VLOOKUP(L8,'Base dados Exercicios'!$C$4:$J$305,7,FALSE),"") | F8: =IFERROR(VLOOKUP(L8,'Base dados Exercicios'!$C$4:$J$305,8,FALSE),"") | H8: ='Base dados Exercicios'!L9 -> Peito | I8: =SUMIF($A$4:$A$102,H8,$N$4:$N$102)+SUMIF($B$4:B$102,H8,$N$4:$N$102)+SUMIF($C$4:$C$102,H8,$N$4:$N$102)+(SUMIF($D$4:$D$102,H8,$N$4:$N$102)*0.5)+(SUMIF($E$4:$E$102,H8,$N$4:$N$102)*0.5)+(SUMIF($F$4:F$102,H8,$N$4:$N$102)*0.3) -> 0 | M8: =IF(L8<>"", HYPERLINK(VLOOKUP(L8,'Base dados Exercicios'!$C$4:$D$83,2,FALSE),"Check"),"") | AD8: =(R8*S8)+(U8*V8)+(X8*Y8)+(AA8*AB8) -> 0 | AR8: =(AF8*AG8)+(AI8*AJ8)+(AL8*AM8)+(AO8*AP8) -> 0 | AS8: =AR8-AD8 -> 0 | BG8: =(AU8*AV8)+(AX8*AY8)+(BA8*BB8)+(BD8*BE8) -> 0 | BH8: =BG8-AR8 -> 0 | BV8: =(BJ8*BK8)+(BM8*BN8)+(BP8*BQ8)+(BS8*BT8) -> 0 | BW8: =BV8-BG8 -> 0 | CK8: =(BY8*BZ8)+(CB8*CC8)+(CE8*CF8)+(CH8*CI8) -> 0 | CL8: =CK8-BV8 -> 0 | CZ8: =(CN8*CO8)+(CQ8*CR8)+(CT8*CU8)+(CW8*CX8) -> 0 | DA8: =CZ8-CK8 -> 0 | DO8: =(DC8*DD8)+(DF8*DG8)+(DI8*DJ8)+(DL8*DM8) -> 0 | DP8: =DO8-CZ8 -> 0 | ED8: =(DR8*DS8)+(DU8*DV8)+(DX8*DY8)+(EA8*EB8) -> 0 | EE8: =ED8-DO8 -> 0
A9: =IFERROR(VLOOKUP(L9,'Base dados Exercicios'!$C$4:$J$305,3,FALSE),"") | B9: =IFERROR(VLOOKUP(L9,'Base dados Exercicios'!$C$4:$J$305,4,FALSE),"") | C9: =IFERROR(VLOOKUP(L9,'Base dados Exercicios'!$C$4:$J$305,5,FALSE),"") | D9: =IFERROR(VLOOKUP(L9,'Base dados Exercicios'!$C$4:$J$305,6,FALSE),"") | E9: =IFERROR(VLOOKUP(L9,'Base dados Exercicios'!$C$4:$J$305,7,FALSE),"") | F9: =IFERROR(VLOOKUP(L9,'Base dados Exercicios'!$C$4:$J$305,8,FALSE),"") | H9: ='Base dados Exercicios'!L8 -> Ombro posterior | I9: =SUMIF($A$4:$A$102,H9,$N$4:$N$102)+SUMIF($B$4:B$102,H9,$N$4:$N$102)+SUMIF($C$4:$C$102,H9,$N$4:$N$102)+(SUMIF($D$4:$D$102,H9,$N$4:$N$102)*0.5)+(SUMIF($E$4:$E$102,H9,$N$4:$N$102)*0.5)+(SUMIF($F$4:F$102,H9,$N$4:$N$102)*0.3) -> 0 | M9: =IF(L9<>"", HYPERLINK(VLOOKUP(L9,'Base dados Exercicios'!$C$4:$D$83,2,FALSE),"Check"),"") | AD9: =(R9*S9)+(U9*V9)+(X9*Y9)+(AA9*AB9) -> 0 | AR9: =(AF9*AG9)+(AI9*AJ9)+(AL9*AM9)+(AO9*AP9) -> 0 | AS9: =AR9-AD9 -> 0 | BG9: =(AU9*AV9)+(AX9*AY9)+(BA9*BB9)+(BD9*BE9) -> 0 | BH9: =BG9-AR9 -> 0 | BV9: =(BJ9*BK9)+(BM9*BN9)+(BP9*BQ9)+(BS9*BT9) -> 0 | BW9: =BV9-BG9 -> 0 | CK9: =(BY9*BZ9)+(CB9*CC9)+(CE9*CF9)+(CH9*CI9) -> 0 | CL9: =CK9-BV9 -> 0 | CZ9: =(CN9*CO9)+(CQ9*CR9)+(CT9*CU9)+(CW9*CX9) -> 0 | DA9: =CZ9-CK9 -> 0 | DO9: =(DC9*DD9)+(DF9*DG9)+(DI9*DJ9)+(DL9*DM9) -> 0 | DP9: =DO9-CZ9 -> 0 | ED9: =(DR9*DS9)+(DU9*DV9)+(DX9*DY9)+(EA9*EB9) -> 0 | EE9: =ED9-DO9 -> 0
A10: =IFERROR(VLOOKUP(L10,'Base dados Exercicios'!$C$4:$J$305,3,FALSE),"") | B10: =IFERROR(VLOOKUP(L10,'Base dados Exercicios'!$C$4:$J$305,4,FALSE),"") | C10: =IFERROR(VLOOKUP(L10,'Base dados Exercicios'!$C$4:$J$305,5,FALSE),"") | D10: =IFERROR(VLOOKUP(L10,'Base dados Exercicios'!$C$4:$J$305,6,FALSE),"") | E10: =IFERROR(VLOOKUP(L10,'Base dados Exercicios'!$C$4:$J$305,7,FALSE),"") | F10: =IFERROR(VLOOKUP(L10,'Base dados Exercicios'!$C$4:$J$305,8,FALSE),"") | H10: ='Base dados Exercicios'!L7 -> Ombro médio | I10: =SUMIF($A$4:$A$102,H10,$N$4:$N$102)+SUMIF($B$4:B$102,H10,$N$4:$N$102)+SUMIF($C$4:$C$102,H10,$N$4:$N$102)+(SUMIF($D$4:$D$102,H10,$N$4:$N$102)*0.5)+(SUMIF($E$4:$E$102,H10,$N$4:$N$102)*0.5)+(SUMIF($F$4:F$102,H10,$N$4:$N$102)*0.3) -> 0 | M10: =IF(L10<>"", HYPERLINK(VLOOKUP(L10,'Base dados Exercicios'!$C$4:$D$83,2,FALSE),"Check"),"") | AD10: =(R10*S10)+(U10*V10)+(X10*Y10)+(AA10*AB10) -> 0 | AR10: =(AF10*AG10)+(AI10*AJ10)+(AL10*AM10)+(AO10*AP10) -> 0 | AS10: =AR10-AD10 -> 0 | BG10: =(AU10*AV10)+(AX10*AY10)+(BA10*BB10)+(BD10*BE10) -> 0 | BH10: =BG10-AR10 -> 0 | BV10: =(BJ10*BK10)+(BM10*BN10)+(BP10*BQ10)+(BS10*BT10) -> 0 | BW10: =BV10-BG10 -> 0 | CK10: =(BY10*BZ10)+(CB10*CC10)+(CE10*CF10)+(CH10*CI10) -> 0 | CL10: =CK10-BV10 -> 0 | CZ10: =(CN10*CO10)+(CQ10*CR10)+(CT10*CU10)+(CW10*CX10) -> 0 | DA10: =CZ10-CK10 -> 0 | DO10: =(DC10*DD10)+(DF10*DG10)+(DI10*DJ10)+(DL10*DM10) -> 0 | DP10: =DO10-CZ10 -> 0 | ED10: =(DR10*DS10)+(DU10*DV10)+(DX10*DY10)+(EA10*EB10) -> 0 | EE10: =ED10-DO10 -> 0
A11: =IFERROR(VLOOKUP(L11,'Base dados Exercicios'!$C$4:$J$305,3,FALSE),"") | B11: =IFERROR(VLOOKUP(L11,'Base dados Exercicios'!$C$4:$J$305,4,FALSE),"") | C11: =IFERROR(VLOOKUP(L11,'Base dados Exercicios'!$C$4:$J$305,5,FALSE),"") | D11: =IFERROR(VLOOKUP(L11,'Base dados Exercicios'!$C$4:$J$305,6,FALSE),"") | E11: =IFERROR(VLOOKUP(L11,'Base dados Exercicios'!$C$4:$J$305,7,FALSE),"") | F11: =IFERROR(VLOOKUP(L11,'Base dados Exercicios'!$C$4:$J$305,8,FALSE),"") | H11: ='Base dados Exercicios'!L10 -> Trapézio | I11: =SUMIF($A$4:$A$102,H11,$N$4:$N$102)+SUMIF($B$4:B$102,H11,$N$4:$N$102)+SUMIF($C$4:$C$102,H11,$N$4:$N$102)+(SUMIF($D$4:$D$102,H11,$N$4:$N$102)*0.5)+(SUMIF($E$4:$E$102,H11,$N$4:$N$102)*0.5)+(SUMIF($F$4:F$102,H11,$N$4:$N$102)*0.3) -> 0 | M11: =IF(L11<>"", HYPERLINK(VLOOKUP(L11,'Base dados Exercicios'!$C$4:$D$83,2,FALSE),"Check"),"") | AD11: =(R11*S11)+(U11*V11)+(X11*Y11)+(AA11*AB11) -> 0 | AR11: =(AF11*AG11)+(AI11*AJ11)+(AL11*AM11)+(AO11*AP11) -> 0 | AS11: =AR11-AD11 -> 0 | BG11: =(AU11*AV11)+(AX11*AY11)+(BA11*BB11)+(BD11*BE11) -> 0 | BH11: =BG11-AR11 -> 0 | BV11: =(BJ11*BK11)+(BM11*BN11)+(BP11*BQ11)+(BS11*BT11) -> 0 | BW11: =BV11-BG11 -> 0 | CK11: =(BY11*BZ11)+(CB11*CC11)+(CE11*CF11)+(CH11*CI11) -> 0 | CL11: =CK11-BV11 -> 0 | CZ11: =(CN11*CO11)+(CQ11*CR11)+(CT11*CU11)+(CW11*CX11) -> 0 | DA11: =CZ11-CK11 -> 0 | DO11: =(DC11*DD11)+(DF11*DG11)+(DI11*DJ11)+(DL11*DM11) -> 0 | DP11: =DO11-CZ11 -> 0 | ED11: =(DR11*DS11)+(DU11*DV11)+(DX11*DY11)+(EA11*EB11) -> 0 | EE11: =ED11-DO11 -> 0
A12: =IFERROR(VLOOKUP(L12,'Base dados Exercicios'!$C$4:$J$305,3,FALSE),"") | B12: =IFERROR(VLOOKUP(L12,'Base dados Exercicios'!$C$4:$J$305,4,FALSE),"") | C12: =IFERROR(VLOOKUP(L12,'Base dados Exercicios'!$C$4:$J$305,5,FALSE),"") | D12: =IFERROR(VLOOKUP(L12,'Base dados Exercicios'!$C$4:$J$305,6,FALSE),"") | E12: =IFERROR(VLOOKUP(L12,'Base dados Exercicios'!$C$4:$J$305,7,FALSE),"") | F12: =IFERROR(VLOOKUP(L12,'Base dados Exercicios'!$C$4:$J$305,8,FALSE),"") | H12: ='Base dados Exercicios'!L12 -> Quadriceps | I12: =SUMIF($A$4:$A$102,H12,$N$4:$N$102)+SUMIF($B$4:B$102,H12,$N$4:$N$102)+SUMIF($C$4:$C$102,H12,$N$4:$N$102)+(SUMIF($D$4:$D$102,H12,$N$4:$N$102)*0.5)+(SUMIF($E$4:$E$102,H12,$N$4:$N$102)*0.5)+(SUMIF($F$4:F$102,H12,$N$4:$N$102)*0.3) -> 0 | M12: =IF(L12<>"", HYPERLINK(VLOOKUP(L12,'Base dados Exercicios'!$C$4:$D$83,2,FALSE),"Check"),"") | AD12: =(R12*S12)+(U12*V12)+(X12*Y12)+(AA12*AB12) -> 0 | AR12: =(AF12*AG12)+(AI12*AJ12)+(AL12*AM12)+(AO12*AP12) -> 0 | AS12: =AR12-AD12 -> 0 | BG12: =(AU12*AV12)+(AX12*AY12)+(BA12*BB12)+(BD12*BE12) -> 0 | BH12: =BG12-AR12 -> 0 | BV12: =(BJ12*BK12)+(BM12*BN12)+(BP12*BQ12)+(BS12*BT12) -> 0 | BW12: =BV12-BG12 -> 0 | CK12: =(BY12*BZ12)+(CB12*CC12)+(CE12*CF12)+(CH12*CI12) -> 0 | CL12: =CK12-BV12 -> 0 | CZ12: =(CN12*CO12)+(CQ12*CR12)+(CT12*CU12)+(CW12*CX12) -> 0 | DA12: =CZ12-CK12 -> 0 | DO12: =(DC12*DD12)+(DF12*DG12)+(DI12*DJ12)+(DL12*DM12) -> 0 | DP12: =DO12-CZ12 -> 0 | ED12: =(DR12*DS12)+(DU12*DV12)+(DX12*DY12)+(EA12*EB12) -> 0 | EE12: =ED12-DO12 -> 0
A13: =IFERROR(VLOOKUP(L13,'Base dados Exercicios'!$C$4:$J$305,3,FALSE),"") | B13: =IFERROR(VLOOKUP(L13,'Base dados Exercicios'!$C$4:$J$305,4,FALSE),"") | C13: =IFERROR(VLOOKUP(L13,'Base dados Exercicios'!$C$4:$J$305,5,FALSE),"") | D13: =IFERROR(VLOOKUP(L13,'Base dados Exercicios'!$C$4:$J$305,6,FALSE),"") | E13: =IFERROR(VLOOKUP(L13,'Base dados Exercicios'!$C$4:$J$305,7,FALSE),"") | F13: =IFERROR(VLOOKUP(L13,'Base dados Exercicios'!$C$4:$J$305,8,FALSE),"") | H13: ='Base dados Exercicios'!L13 -> Posterior de coxa | I13: =SUMIF($A$4:$A$102,H13,$N$4:$N$102)+SUMIF($B$4:B$102,H13,$N$4:$N$102)+SUMIF($C$4:$C$102,H13,$N$4:$N$102)+(SUMIF($D$4:$D$102,H13,$N$4:$N$102)*0.5)+(SUMIF($E$4:$E$102,H13,$N$4:$N$102)*0.5)+(SUMIF($F$4:F$102,H13,$N$4:$N$102)*0.3) -> 0 | M13: =IF(L13<>"", HYPERLINK(VLOOKUP(L13,'Base dados Exercicios'!$C$4:$D$83,2,FALSE),"Check"),"") | Q13: NOTAS: | AE13: NOTAS: | AT13: NOTAS: | BI13: NOTAS: | BX13: NOTAS: | CM13: NOTAS: | DB13: NOTAS: | DQ13: NOTAS:
A14: =IFERROR(VLOOKUP(L14,'Base dados Exercicios'!$C$4:$J$305,3,FALSE),"") | B14: =IFERROR(VLOOKUP(L14,'Base dados Exercicios'!$C$4:$J$305,4,FALSE),"") | C14: =IFERROR(VLOOKUP(L14,'Base dados Exercicios'!$C$4:$J$305,5,FALSE),"") | D14: =IFERROR(VLOOKUP(L14,'Base dados Exercicios'!$C$4:$J$305,6,FALSE),"") | E14: =IFERROR(VLOOKUP(L14,'Base dados Exercicios'!$C$4:$J$305,7,FALSE),"") | F14: =IFERROR(VLOOKUP(L14,'Base dados Exercicios'!$C$4:$J$305,8,FALSE),"") | H14: ='Base dados Exercicios'!L14 -> Glúteo | I14: =SUMIF($A$4:$A$102,H14,$N$4:$N$102)+SUMIF($B$4:B$102,H14,$N$4:$N$102)+SUMIF($C$4:$C$102,H14,$N$4:$N$102)+(SUMIF($D$4:$D$102,H14,$N$4:$N$102)*0.5)+(SUMIF($E$4:$E$102,H14,$N$4:$N$102)*0.5)+(SUMIF($F$4:F$102,H14,$N$4:$N$102)*0.3) -> 0 | K14: 2 | M14: =IF(L14<>"", HYPERLINK(VLOOKUP(L14,'Base dados Exercicios'!$C$4:$D$83,2,FALSE),"Check"),"") | AD14: =(R14*S14)+(U14*V14)+(X14*Y14)+(AA14*AB14) -> 0 | AR14: =(AF14*AG14)+(AI14*AJ14)+(AL14*AM14)+(AO14*AP14) -> 0 | AS14: =AR14-AD14 -> 0 | BG14: =(AU14*AV14)+(AX14*AY14)+(BA14*BB14)+(BD14*BE14) -> 0 | BH14: =BG14-AR14 -> 0 | BV14: =(BJ14*BK14)+(BM14*BN14)+(BP14*BQ14)+(BS14*BT14) -> 0 | BW14: =BV14-BG14 -> 0 | CK14: =(BY14*BZ14)+(CB14*CC14)+(CE14*CF14)+(CH14*CI14) -> 0 | CL14: =CK14-BV14 -> 0 | CZ14: =(CN14*CO14)+(CQ14*CR14)+(CT14*CU14)+(CW14*CX14) -> 0 | DA14: =CZ14-CK14 -> 0 | DO14: =(DC14*DD14)+(DF14*DG14)+(DI14*DJ14)+(DL14*DM14) -> 0 | DP14: =DO14-CZ14 -> 0 | ED14: =(DR14*DS14)+(DU14*DV14)+(DX14*DY14)+(EA14*EB14) -> 0 | EE14: =ED14-DO14 -> 0
A15: =IFERROR(VLOOKUP(L15,'Base dados Exercicios'!$C$4:$J$305,3,FALSE),"") | B15: =IFERROR(VLOOKUP(L15,'Base dados Exercicios'!$C$4:$J$305,4,FALSE),"") | C15: =IFERROR(VLOOKUP(L15,'Base dados Exercicios'!$C$4:$J$305,5,FALSE),"") | D15: =IFERROR(VLOOKUP(L15,'Base dados Exercicios'!$C$4:$J$305,6,FALSE),"") | E15: =IFERROR(VLOOKUP(L15,'Base dados Exercicios'!$C$4:$J$305,7,FALSE),"") | F15: =IFERROR(VLOOKUP(L15,'Base dados Exercicios'!$C$4:$J$305,8,FALSE),"") | H15: ='Base dados Exercicios'!L15 -> Lombares | I15: =SUMIF($A$4:$A$102,H15,$N$4:$N$102)+SUMIF($B$4:B$102,H15,$N$4:$N$102)+SUMIF($C$4:$C$102,H15,$N$4:$N$102)+(SUMIF($D$4:$D$102,H15,$N$4:$N$102)*0.5)+(SUMIF($E$4:$E$102,H15,$N$4:$N$102)*0.5)+(SUMIF($F$4:F$102,H15,$N$4:$N$102)*0.3) -> 0 | M15: =IF(L15<>"", HYPERLINK(VLOOKUP(L15,'Base dados Exercicios'!$C$4:$D$83,2,FALSE),"Check"),"") | AD15: =(R15*S15)+(U15*V15)+(X15*Y15)+(AA15*AB15) -> 0 | AR15: =(AF15*AG15)+(AI15*AJ15)+(AL15*AM15)+(AO15*AP15) -> 0 | AS15: =AR15-AD15 -> 0 | BG15: =(AU15*AV15)+(AX15*AY15)+(BA15*BB15)+(BD15*BE15) -> 0 | BH15: =BG15-AR15 -> 0 | BV15: =(BJ15*BK15)+(BM15*BN15)+(BP15*BQ15)+(BS15*BT15) -> 0 | BW15: =BV15-BG15 -> 0 | CK15: =(BY15*BZ15)+(CB15*CC15)+(CE15*CF15)+(CH15*CI15) -> 0 | CL15: =CK15-BV15 -> 0 | CZ15: =(CN15*CO15)+(CQ15*CR15)+(CT15*CU15)+(CW15*CX15) -> 0 | DA15: =CZ15-CK15 -> 0 | DO15: =(DC15*DD15)+(DF15*DG15)+(DI15*DJ15)+(DL15*DM15) -> 0 | DP15: =DO15-CZ15 -> 0 | ED15: =(DR15*DS15)+(DU15*DV15)+(DX15*DY15)+(EA15*EB15) -> 0 | EE15: =ED15-DO15 -> 0
A16: =IFERROR(VLOOKUP(L16,'Base dados Exercicios'!$C$4:$J$305,3,FALSE),"") | B16: =IFERROR(VLOOKUP(L16,'Base dados Exercicios'!$C$4:$J$305,4,FALSE),"") | C16: =IFERROR(VLOOKUP(L16,'Base dados Exercicios'!$C$4:$J$305,5,FALSE),"") | D16: =IFERROR(VLOOKUP(L16,'Base dados Exercicios'!$C$4:$J$305,6,FALSE),"") | E16: =IFERROR(VLOOKUP(L16,'Base dados Exercicios'!$C$4:$J$305,7,FALSE),"") | F16: =IFERROR(VLOOKUP(L16,'Base dados Exercicios'!$C$4:$J$305,8,FALSE),"") | H16: ='Base dados Exercicios'!L16 -> Gémeos | I16: =SUMIF($A$4:$A$102,H16,$N$4:$N$102)+SUMIF($B$4:B$102,H16,$N$4:$N$102)+SUMIF($C$4:$C$102,H16,$N$4:$N$102)+(SUMIF($D$4:$D$102,H16,$N$4:$N$102)*0.5)+(SUMIF($E$4:$E$102,H16,$N$4:$N$102)*0.5)+(SUMIF($F$4:F$102,H16,$N$4:$N$102)*0.3) -> 0 | M16: =IF(L16<>"", HYPERLINK(VLOOKUP(L16,'Base dados Exercicios'!$C$4:$D$83,2,FALSE),"Check"),"") | AD16: =(R16*S16)+(U16*V16)+(X16*Y16)+(AA16*AB16) -> 0 | AR16: =(AF16*AG16)+(AI16*AJ16)+(AL16*AM16)+(AO16*AP16) -> 0 | AS16: =AR16-AD16 -> 0 | BG16: =(AU16*AV16)+(AX16*AY16)+(BA16*BB16)+(BD16*BE16) -> 0 | BH16: =BG16-AR16 -> 0 | BV16: =(BJ16*BK16)+(BM16*BN16)+(BP16*BQ16)+(BS16*BT16) -> 0 | BW16: =BV16-BG16 -> 0 | CK16: =(BY16*BZ16)+(CB16*CC16)+(CE16*CF16)+(CH16*CI16) -> 0 | CL16: =CK16-BV16 -> 0 | CZ16: =(CN16*CO16)+(CQ16*CR16)+(CT16*CU16)+(CW16*CX16) -> 0 | DA16: =CZ16-CK16 -> 0 | DO16: =(DC16*DD16)+(DF16*DG16)+(DI16*DJ16)+(DL16*DM16) -> 0 | DP16: =DO16-CZ16 -> 0 | ED16: =(DR16*DS16)+(DU16*DV16)+(DX16*DY16)+(EA16*EB16) -> 0 | EE16: =ED16-DO16 -> 0
A17: =IFERROR(VLOOKUP(L17,'Base dados Exercicios'!$C$4:$J$305,3,FALSE),"") | B17: =IFERROR(VLOOKUP(L17,'Base dados Exercicios'!$C$4:$J$305,4,FALSE),"") | C17: =IFERROR(VLOOKUP(L17,'Base dados Exercicios'!$C$4:$J$305,5,FALSE),"") | D17: =IFERROR(VLOOKUP(L17,'Base dados Exercicios'!$C$4:$J$305,6,FALSE),"") | E17: =IFERROR(VLOOKUP(L17,'Base dados Exercicios'!$C$4:$J$305,7,FALSE),"") | F17: =IFERROR(VLOOKUP(L17,'Base dados Exercicios'!$C$4:$J$305,8,FALSE),"") | M17: =IF(L17<>"", HYPERLINK(VLOOKUP(L17,'Base dados Exercicios'!$C$4:$D$83,2,FALSE),"Check"),"") | AD17: =(R17*S17)+(U17*V17)+(X17*Y17)+(AA17*AB17) -> 0 | AR17: =(AF17*AG17)+(AI17*AJ17)+(AL17*AM17)+(AO17*AP17) -> 0 | AS17: =AR17-AD17 -> 0 | BG17: =(AU17*AV17)+(AX17*AY17)+(BA17*BB17)+(BD17*BE17) -> 0 | BH17: =BG17-AR17 -> 0 | BV17: =(BJ17*BK17)+(BM17*BN17)+(BP17*BQ17)+(BS17*BT17) -> 0 | BW17: =BV17-BG17 -> 0 | CK17: =(BY17*BZ17)+(CB17*CC17)+(CE17*CF17)+(CH17*CI17) -> 0 | CL17: =CK17-BV17 -> 0 | CZ17: =(CN17*CO17)+(CQ17*CR17)+(CT17*CU17)+(CW17*CX17) -> 0 | DA17: =CZ17-CK17 -> 0 | DO17: =(DC17*DD17)+(DF17*DG17)+(DI17*DJ17)+(DL17*DM17) -> 0 | DP17: =DO17-CZ17 -> 0 | ED17: =(DR17*DS17)+(DU17*DV17)+(DX17*DY17)+(EA17*EB17) -> 0 | EE17: =ED17-DO17 -> 0
A18: =IFERROR(VLOOKUP(L18,'Base dados Exercicios'!$C$4:$J$305,3,FALSE),"") | B18: =IFERROR(VLOOKUP(L18,'Base dados Exercicios'!$C$4:$J$305,4,FALSE),"") | C18: =IFERROR(VLOOKUP(L18,'Base dados Exercicios'!$C$4:$J$305,5,FALSE),"") | D18: =IFERROR(VLOOKUP(L18,'Base dados Exercicios'!$C$4:$J$305,6,FALSE),"") | E18: =IFERROR(VLOOKUP(L18,'Base dados Exercicios'!$C$4:$J$305,7,FALSE),"") | F18: =IFERROR(VLOOKUP(L18,'Base dados Exercicios'!$C$4:$J$305,8,FALSE),"") | H18: Cardio | M18: =IF(L18<>"", HYPERLINK(VLOOKUP(L18,'Base dados Exercicios'!$C$4:$D$83,2,FALSE),"Check"),"") | AD18: =(R18*S18)+(U18*V18)+(X18*Y18)+(AA18*AB18) -> 0 | AR18: =(AF18*AG18)+(AI18*AJ18)+(AL18*AM18)+(AO18*AP18) -> 0 | AS18: =AR18-AD18 -> 0 | BG18: =(AU18*AV18)+(AX18*AY18)+(BA18*BB18)+(BD18*BE18) -> 0 | BH18: =BG18-AR18 -> 0 | BV18: =(BJ18*BK18)+(BM18*BN18)+(BP18*BQ18)+(BS18*BT18) -> 0 | BW18: =BV18-BG18 -> 0 | CK18: =(BY18*BZ18)+(CB18*CC18)+(CE18*CF18)+(CH18*CI18) -> 0 | CL18: =CK18-BV18 -> 0 | CZ18: =(CN18*CO18)+(CQ18*CR18)+(CT18*CU18)+(CW18*CX18) -> 0 | DA18: =CZ18-CK18 -> 0 | DO18: =(DC18*DD18)+(DF18*DG18)+(DI18*DJ18)+(DL18*DM18) -> 0 | DP18: =DO18-CZ18 -> 0 | ED18: =(DR18*DS18)+(DU18*DV18)+(DX18*DY18)+(EA18*EB18) -> 0 | EE18: =ED18-DO18 -> 0
A19: =IFERROR(VLOOKUP(L19,'Base dados Exercicios'!$C$4:$J$305,3,FALSE),"") | B19: =IFERROR(VLOOKUP(L19,'Base dados Exercicios'!$C$4:$J$305,4,FALSE),"") | C19: =IFERROR(VLOOKUP(L19,'Base dados Exercicios'!$C$4:$J$305,5,FALSE),"") | D19: =IFERROR(VLOOKUP(L19,'Base dados Exercicios'!$C$4:$J$305,6,FALSE),"") | E19: =IFERROR(VLOOKUP(L19,'Base dados Exercicios'!$C$4:$J$305,7,FALSE),"") | F19: =IFERROR(VLOOKUP(L19,'Base dados Exercicios'!$C$4:$J$305,8,FALSE),"") | M19: =IF(L19<>"", HYPERLINK(VLOOKUP(L19,'Base dados Exercicios'!$C$4:$D$83,2,FALSE),"Check"),"") | AD19: =(R19*S19)+(U19*V19)+(X19*Y19)+(AA19*AB19) -> 0 | AR19: =(AF19*AG19)+(AI19*AJ19)+(AL19*AM19)+(AO19*AP19) -> 0 | AS19: =AR19-AD19 -> 0 | BG19: =(AU19*AV19)+(AX19*AY19)+(BA19*BB19)+(BD19*BE19) -> 0 | BH19: =BG19-AR19 -> 0 | BV19: =(BJ19*BK19)+(BM19*BN19)+(BP19*BQ19)+(BS19*BT19) -> 0 | BW19: =BV19-BG19 -> 0 | CK19: =(BY19*BZ19)+(CB19*CC19)+(CE19*CF19)+(CH19*CI19) -> 0 | CL19: =CK19-BV19 -> 0 | CZ19: =(CN19*CO19)+(CQ19*CR19)+(CT19*CU19)+(CW19*CX19) -> 0 | DA19: =CZ19-CK19 -> 0 | DO19: =(DC19*DD19)+(DF19*DG19)+(DI19*DJ19)+(DL19*DM19) -> 0 | DP19: =DO19-CZ19 -> 0 | ED19: =(DR19*DS19)+(DU19*DV19)+(DX19*DY19)+(EA19*EB19) -> 0 | EE19: =ED19-DO19 -> 0
A20: =IFERROR(VLOOKUP(L20,'Base dados Exercicios'!$C$4:$J$305,3,FALSE),"") | B20: =IFERROR(VLOOKUP(L20,'Base dados Exercicios'!$C$4:$J$305,4,FALSE),"") | C20: =IFERROR(VLOOKUP(L20,'Base dados Exercicios'!$C$4:$J$305,5,FALSE),"") | D20: =IFERROR(VLOOKUP(L20,'Base dados Exercicios'!$C$4:$J$305,6,FALSE),"") | E20: =IFERROR(VLOOKUP(L20,'Base dados Exercicios'!$C$4:$J$305,7,FALSE),"") | F20: =IFERROR(VLOOKUP(L20,'Base dados Exercicios'!$C$4:$J$305,8,FALSE),"") | M20: =IF(L20<>"", HYPERLINK(VLOOKUP(L20,'Base dados Exercicios'!$C$4:$D$83,2,FALSE),"Check"),"") | AD20: =(R20*S20)+(U20*V20)+(X20*Y20)+(AA20*AB20) -> 0 | AR20: =(AF20*AG20)+(AI20*AJ20)+(AL20*AM20)+(AO20*AP20) -> 0 | AS20: =AR20-AD20 -> 0 | BG20: =(AU20*AV20)+(AX20*AY20)+(BA20*BB20)+(BD20*BE20) -> 0 | BH20: =BG20-AR20 -> 0 | BV20: =(BJ20*BK20)+(BM20*BN20)+(BP20*BQ20)+(BS20*BT20) -> 0 | BW20: =BV20-BG20 -> 0 | CK20: =(BY20*BZ20)+(CB20*CC20)+(CE20*CF20)+(CH20*CI20) -> 0 | CL20: =CK20-BV20 -> 0 | CZ20: =(CN20*CO20)+(CQ20*CR20)+(CT20*CU20)+(CW20*CX20) -> 0 | DA20: =CZ20-CK20 -> 0 | DO20: =(DC20*DD20)+(DF20*DG20)+(DI20*DJ20)+(DL20*DM20) -> 0 | DP20: =DO20-CZ20 -> 0 | ED20: =(DR20*DS20)+(DU20*DV20)+(DX20*DY20)+(EA20*EB20) -> 0 | EE20: =ED20-DO20 -> 0
A21: =IFERROR(VLOOKUP(L21,'Base dados Exercicios'!$C$4:$J$305,3,FALSE),"") | B21: =IFERROR(VLOOKUP(L21,'Base dados Exercicios'!$C$4:$J$305,4,FALSE),"") | C21: =IFERROR(VLOOKUP(L21,'Base dados Exercicios'!$C$4:$J$305,5,FALSE),"") | D21: =IFERROR(VLOOKUP(L21,'Base dados Exercicios'!$C$4:$J$305,6,FALSE),"") | E21: =IFERROR(VLOOKUP(L21,'Base dados Exercicios'!$C$4:$J$305,7,FALSE),"") | F21: =IFERROR(VLOOKUP(L21,'Base dados Exercicios'!$C$4:$J$305,8,FALSE),"") | M21: =IF(L21<>"", HYPERLINK(VLOOKUP(L21,'Base dados Exercicios'!$C$4:$D$83,2,FALSE),"Check"),"") | AD21: =(R21*S21)+(U21*V21)+(X21*Y21)+(AA21*AB21) -> 0 | AR21: =(AF21*AG21)+(AI21*AJ21)+(AL21*AM21)+(AO21*AP21) -> 0 | AS21: =AR21-AD21 -> 0 | BG21: =(AU21*AV21)+(AX21*AY21)+(BA21*BB21)+(BD21*BE21) -> 0 | BH21: =BG21-AR21 -> 0 | BV21: =(BJ21*BK21)+(BM21*BN21)+(BP21*BQ21)+(BS21*BT21) -> 0 | BW21: =BV21-BG21 -> 0 | CK21: =(BY21*BZ21)+(CB21*CC21)+(CE21*CF21)+(CH21*CI21) -> 0 | CL21: =CK21-BV21 -> 0 | CZ21: =(CN21*CO21)+(CQ21*CR21)+(CT21*CU21)+(CW21*CX21) -> 0 | DA21: =CZ21-CK21 -> 0 | DO21: =(DC21*DD21)+(DF21*DG21)+(DI21*DJ21)+(DL21*DM21) -> 0 | DP21: =DO21-CZ21 -> 0 | ED21: =(DR21*DS21)+(DU21*DV21)+(DX21*DY21)+(EA21*EB21) -> 0 | EE21: =ED21-DO21 -> 0
A22: =IFERROR(VLOOKUP(L22,'Base dados Exercicios'!$C$4:$J$305,3,FALSE),"") | B22: =IFERROR(VLOOKUP(L22,'Base dados Exercicios'!$C$4:$J$305,4,FALSE),"") | C22: =IFERROR(VLOOKUP(L22,'Base dados Exercicios'!$C$4:$J$305,5,FALSE),"") | D22: =IFERROR(VLOOKUP(L22,'Base dados Exercicios'!$C$4:$J$305,6,FALSE),"") | E22: =IFERROR(VLOOKUP(L22,'Base dados Exercicios'!$C$4:$J$305,7,FALSE),"") | F22: =IFERROR(VLOOKUP(L22,'Base dados Exercicios'!$C$4:$J$305,8,FALSE),"") | M22: =IF(L22<>"", HYPERLINK(VLOOKUP(L22,'Base dados Exercicios'!$C$4:$D$83,2,FALSE),"Check"),"") | AD22: =(R22*S22)+(U22*V22)+(X22*Y22)+(AA22*AB22) -> 0 | AR22: =(AF22*AG22)+(AI22*AJ22)+(AL22*AM22)+(AO22*AP22) -> 0 | AS22: =AR22-AD22 -> 0 | BG22: =(AU22*AV22)+(AX22*AY22)+(BA22*BB22)+(BD22*BE22) -> 0 | BH22: =BG22-AR22 -> 0 | BV22: =(BJ22*BK22)+(BM22*BN22)+(BP22*BQ22)+(BS22*BT22) -> 0 | BW22: =BV22-BG22 -> 0 | CK22: =(BY22*BZ22)+(CB22*CC22)+(CE22*CF22)+(CH22*CI22) -> 0 | CL22: =CK22-BV22 -> 0 | CZ22: =(CN22*CO22)+(CQ22*CR22)+(CT22*CU22)+(CW22*CX22) -> 0 | DA22: =CZ22-CK22 -> 0 | DO22: =(DC22*DD22)+(DF22*DG22)+(DI22*DJ22)+(DL22*DM22) -> 0 | DP22: =DO22-CZ22 -> 0 | ED22: =(DR22*DS22)+(DU22*DV22)+(DX22*DY22)+(EA22*EB22) -> 0 | EE22: =ED22-DO22 -> 0
A23: =IFERROR(VLOOKUP(L23,'Base dados Exercicios'!$C$4:$J$305,3,FALSE),"") | B23: =IFERROR(VLOOKUP(L23,'Base dados Exercicios'!$C$4:$J$305,4,FALSE),"") | C23: =IFERROR(VLOOKUP(L23,'Base dados Exercicios'!$C$4:$J$305,5,FALSE),"") | D23: =IFERROR(VLOOKUP(L23,'Base dados Exercicios'!$C$4:$J$305,6,FALSE),"") | E23: =IFERROR(VLOOKUP(L23,'Base dados Exercicios'!$C$4:$J$305,7,FALSE),"") | F23: =IFERROR(VLOOKUP(L23,'Base dados Exercicios'!$C$4:$J$305,8,FALSE),"") | H23: Dia 1 | M23: =IF(L23<>"", HYPERLINK(VLOOKUP(L23,'Base dados Exercicios'!$C$4:$D$83,2,FALSE),"Check"),"") | Q23: NOTAS: | AE23: NOTAS: | AT23: NOTAS: | BI23: NOTAS: | BX23: NOTAS: | CM23: NOTAS: | DB23: NOTAS: | DQ23: NOTAS:
A24: =IFERROR(VLOOKUP(L24,'Base dados Exercicios'!$C$4:$J$305,3,FALSE),"") | B24: =IFERROR(VLOOKUP(L24,'Base dados Exercicios'!$C$4:$J$305,4,FALSE),"") | C24: =IFERROR(VLOOKUP(L24,'Base dados Exercicios'!$C$4:$J$305,5,FALSE),"") | D24: =IFERROR(VLOOKUP(L24,'Base dados Exercicios'!$C$4:$J$305,6,FALSE),"") | E24: =IFERROR(VLOOKUP(L24,'Base dados Exercicios'!$C$4:$J$305,7,FALSE),"") | F24: =IFERROR(VLOOKUP(L24,'Base dados Exercicios'!$C$4:$J$305,8,FALSE),"") | H24: Dia 2 | K24: =I25 -> 0 | M24: =IF(L24<>"", HYPERLINK(VLOOKUP(L24,'Base dados Exercicios'!$C$4:$D$83,2,FALSE),"Check"),"") | AD24: =(R24*S24)+(U24*V24)+(X24*Y24)+(AA24*AB24) -> 0 | AR24: =(AF24*AG24)+(AI24*AJ24)+(AL24*AM24)+(AO24*AP24) -> 0 | AS24: =AR24-AD24 -> 0 | BG24: =(AU24*AV24)+(AX24*AY24)+(BA24*BB24)+(BD24*BE24) -> 0 | BH24: =BG24-AR24 -> 0 | BV24: =(BJ24*BK24)+(BM24*BN24)+(BP24*BQ24)+(BS24*BT24) -> 0 | BW24: =BV24-BG24 -> 0 | CK24: =(BY24*BZ24)+(CB24*CC24)+(CE24*CF24)+(CH24*CI24) -> 0 | CL24: =CK24-BV24 -> 0 | CZ24: =(CN24*CO24)+(CQ24*CR24)+(CT24*CU24)+(CW24*CX24) -> 0 | DA24: =CZ24-CK24 -> 0 | DO24: =(DC24*DD24)+(DF24*DG24)+(DI24*DJ24)+(DL24*DM24) -> 0 | DP24: =DO24-CZ24 -> 0 | ED24: =(DR24*DS24)+(DU24*DV24)+(DX24*DY24)+(EA24*EB24) -> 0 | EE24: =ED24-DO24 -> 0
A25: =IFERROR(VLOOKUP(L25,'Base dados Exercicios'!$C$4:$J$305,3,FALSE),"") | B25: =IFERROR(VLOOKUP(L25,'Base dados Exercicios'!$C$4:$J$305,4,FALSE),"") | C25: =IFERROR(VLOOKUP(L25,'Base dados Exercicios'!$C$4:$J$305,5,FALSE),"") | D25: =IFERROR(VLOOKUP(L25,'Base dados Exercicios'!$C$4:$J$305,6,FALSE),"") | E25: =IFERROR(VLOOKUP(L25,'Base dados Exercicios'!$C$4:$J$305,7,FALSE),"") | F25: =IFERROR(VLOOKUP(L25,'Base dados Exercicios'!$C$4:$J$305,8,FALSE),"") | H25: Dia 3 | M25: =IF(L25<>"", HYPERLINK(VLOOKUP(L25,'Base dados Exercicios'!$C$4:$D$83,2,FALSE),"Check"),"") | AD25: =(R25*S25)+(U25*V25)+(X25*Y25)+(AA25*AB25) -> 0 | AR25: =(AF25*AG25)+(AI25*AJ25)+(AL25*AM25)+(AO25*AP25) -> 0 | AS25: =AR25-AD25 -> 0 | BG25: =(AU25*AV25)+(AX25*AY25)+(BA25*BB25)+(BD25*BE25) -> 0 | BH25: =BG25-AR25 -> 0 | BV25: =(BJ25*BK25)+(BM25*BN25)+(BP25*BQ25)+(BS25*BT25) -> 0 | BW25: =BV25-BG25 -> 0 | CK25: =(BY25*BZ25)+(CB25*CC25)+(CE25*CF25)+(CH25*CI25) -> 0 | CL25: =CK25-BV25 -> 0 | CZ25: =(CN25*CO25)+(CQ25*CR25)+(CT25*CU25)+(CW25*CX25) -> 0 | DA25: =CZ25-CK25 -> 0 | DO25: =(DC25*DD25)+(DF25*DG25)+(DI25*DJ25)+(DL25*DM25) -> 0 | DP25: =DO25-CZ25 -> 0 | ED25: =(DR25*DS25)+(DU25*DV25)+(DX25*DY25)+(EA25*EB25) -> 0 | EE25: =ED25-DO25 -> 0
A26: =IFERROR(VLOOKUP(L26,'Base dados Exercicios'!$C$4:$J$305,3,FALSE),"") | B26: =IFERROR(VLOOKUP(L26,'Base dados Exercicios'!$C$4:$J$305,4,FALSE),"") | C26: =IFERROR(VLOOKUP(L26,'Base dados Exercicios'!$C$4:$J$305,5,FALSE),"") | D26: =IFERROR(VLOOKUP(L26,'Base dados Exercicios'!$C$4:$J$305,6,FALSE),"") | E26: =IFERROR(VLOOKUP(L26,'Base dados Exercicios'!$C$4:$J$305,7,FALSE),"") | F26: =IFERROR(VLOOKUP(L26,'Base dados Exercicios'!$C$4:$J$305,8,FALSE),"") | H26: Dia 4 | M26: =IF(L26<>"", HYPERLINK(VLOOKUP(L26,'Base dados Exercicios'!$C$4:$D$83,2,FALSE),"Check"),"") | AD26: =(R26*S26)+(U26*V26)+(X26*Y26)+(AA26*AB26) -> 0 | AR26: =(AF26*AG26)+(AI26*AJ26)+(AL26*AM26)+(AO26*AP26) -> 0 | AS26: =AR26-AD26 -> 0 | BG26: =(AU26*AV26)+(AX26*AY26)+(BA26*BB26)+(BD26*BE26) -> 0 | BH26: =BG26-AR26 -> 0 | BV26: =(BJ26*BK26)+(BM26*BN26)+(BP26*BQ26)+(BS26*BT26) -> 0 | BW26: =BV26-BG26 -> 0 | CK26: =(BY26*BZ26)+(CB26*CC26)+(CE26*CF26)+(CH26*CI26) -> 0 | CL26: =CK26-BV26 -> 0 | CZ26: =(CN26*CO26)+(CQ26*CR26)+(CT26*CU26)+(CW26*CX26) -> 0 | DA26: =CZ26-CK26 -> 0 | DO26: =(DC26*DD26)+(DF26*DG26)+(DI26*DJ26)+(DL26*DM26) -> 0 | DP26: =DO26-CZ26 -> 0 | ED26: =(DR26*DS26)+(DU26*DV26)+(DX26*DY26)+(EA26*EB26) -> 0 | EE26: =ED26-DO26 -> 0
A27: =IFERROR(VLOOKUP(L27,'Base dados Exercicios'!$C$4:$J$305,3,FALSE),"") | B27: =IFERROR(VLOOKUP(L27,'Base dados Exercicios'!$C$4:$J$305,4,FALSE),"") | C27: =IFERROR(VLOOKUP(L27,'Base dados Exercicios'!$C$4:$J$305,5,FALSE),"") | D27: =IFERROR(VLOOKUP(L27,'Base dados Exercicios'!$C$4:$J$305,6,FALSE),"") | E27: =IFERROR(VLOOKUP(L27,'Base dados Exercicios'!$C$4:$J$305,7,FALSE),"") | F27: =IFERROR(VLOOKUP(L27,'Base dados Exercicios'!$C$4:$J$305,8,FALSE),"") | H27: Dia 5 | M27: =IF(L27<>"", HYPERLINK(VLOOKUP(L27,'Base dados Exercicios'!$C$4:$D$83,2,FALSE),"Check"),"") | AD27: =(R27*S27)+(U27*V27)+(X27*Y27)+(AA27*AB27) -> 0 | AR27: =(AF27*AG27)+(AI27*AJ27)+(AL27*AM27)+(AO27*AP27) -> 0 | AS27: =AR27-AD27 -> 0 | BG27: =(AU27*AV27)+(AX27*AY27)+(BA27*BB27)+(BD27*BE27) -> 0 | BH27: =BG27-AR27 -> 0 | BV27: =(BJ27*BK27)+(BM27*BN27)+(BP27*BQ27)+(BS27*BT27) -> 0 | BW27: =BV27-BG27 -> 0 | CK27: =(BY27*BZ27)+(CB27*CC27)+(CE27*CF27)+(CH27*CI27) -> 0 | CL27: =CK27-BV27 -> 0 | CZ27: =(CN27*CO27)+(CQ27*CR27)+(CT27*CU27)+(CW27*CX27) -> 0 | DA27: =CZ27-CK27 -> 0 | DO27: =(DC27*DD27)+(DF27*DG27)+(DI27*DJ27)+(DL27*DM27) -> 0 | DP27: =DO27-CZ27 -> 0 | ED27: =(DR27*DS27)+(DU27*DV27)+(DX27*DY27)+(EA27*EB27) -> 0 | EE27: =ED27-DO27 -> 0
A28: =IFERROR(VLOOKUP(L28,'Base dados Exercicios'!$C$4:$J$305,3,FALSE),"") | B28: =IFERROR(VLOOKUP(L28,'Base dados Exercicios'!$C$4:$J$305,4,FALSE),"") | C28: =IFERROR(VLOOKUP(L28,'Base dados Exercicios'!$C$4:$J$305,5,FALSE),"") | D28: =IFERROR(VLOOKUP(L28,'Base dados Exercicios'!$C$4:$J$305,6,FALSE),"") | E28: =IFERROR(VLOOKUP(L28,'Base dados Exercicios'!$C$4:$J$305,7,FALSE),"") | F28: =IFERROR(VLOOKUP(L28,'Base dados Exercicios'!$C$4:$J$305,8,FALSE),"") | H28: Dia 6 | M28: =IF(L28<>"", HYPERLINK(VLOOKUP(L28,'Base dados Exercicios'!$C$4:$D$83,2,FALSE),"Check"),"") | AD28: =(R28*S28)+(U28*V28)+(X28*Y28)+(AA28*AB28) -> 0 | AR28: =(AF28*AG28)+(AI28*AJ28)+(AL28*AM28)+(AO28*AP28) -> 0 | AS28: =AR28-AD28 -> 0 | BG28: =(AU28*AV28)+(AX28*AY28)+(BA28*BB28)+(BD28*BE28) -> 0 | BH28: =BG28-AR28 -> 0 | BV28: =(BJ28*BK28)+(BM28*BN28)+(BP28*BQ28)+(BS28*BT28) -> 0 | BW28: =BV28-BG28 -> 0 | CK28: =(BY28*BZ28)+(CB28*CC28)+(CE28*CF28)+(CH28*CI28) -> 0 | CL28: =CK28-BV28 -> 0 | CZ28: =(CN28*CO28)+(CQ28*CR28)+(CT28*CU28)+(CW28*CX28) -> 0 | DA28: =CZ28-CK28 -> 0 | DO28: =(DC28*DD28)+(DF28*DG28)+(DI28*DJ28)+(DL28*DM28) -> 0 | DP28: =DO28-CZ28 -> 0 | ED28: =(DR28*DS28)+(DU28*DV28)+(DX28*DY28)+(EA28*EB28) -> 0 | EE28: =ED28-DO28 -> 0
A29: =IFERROR(VLOOKUP(L29,'Base dados Exercicios'!$C$4:$J$305,3,FALSE),"") | B29: =IFERROR(VLOOKUP(L29,'Base dados Exercicios'!$C$4:$J$305,4,FALSE),"") | C29: =IFERROR(VLOOKUP(L29,'Base dados Exercicios'!$C$4:$J$305,5,FALSE),"") | D29: =IFERROR(VLOOKUP(L29,'Base dados Exercicios'!$C$4:$J$305,6,FALSE),"") | E29: =IFERROR(VLOOKUP(L29,'Base dados Exercicios'!$C$4:$J$305,7,FALSE),"") | F29: =IFERROR(VLOOKUP(L29,'Base dados Exercicios'!$C$4:$J$305,8,FALSE),"") | H29: Dia 7 | M29: =IF(L29<>"", HYPERLINK(VLOOKUP(L29,'Base dados Exercicios'!$C$4:$D$83,2,FALSE),"Check"),"") | AD29: =(R29*S29)+(U29*V29)+(X29*Y29)+(AA29*AB29) -> 0 | AR29: =(AF29*AG29)+(AI29*AJ29)+(AL29*AM29)+(AO29*AP29) -> 0 | AS29: =AR29-AD29 -> 0 | BG29: =(AU29*AV29)+(AX29*AY29)+(BA29*BB29)+(BD29*BE29) -> 0 | BH29: =BG29-AR29 -> 0 | BV29: =(BJ29*BK29)+(BM29*BN29)+(BP29*BQ29)+(BS29*BT29) -> 0 | BW29: =BV29-BG29 -> 0 | CK29: =(BY29*BZ29)+(CB29*CC29)+(CE29*CF29)+(CH29*CI29) -> 0 | CL29: =CK29-BV29 -> 0 | CZ29: =(CN29*CO29)+(CQ29*CR29)+(CT29*CU29)+(CW29*CX29) -> 0 | DA29: =CZ29-CK29 -> 0 | DO29: =(DC29*DD29)+(DF29*DG29)+(DI29*DJ29)+(DL29*DM29) -> 0 | DP29: =DO29-CZ29 -> 0 | ED29: =(DR29*DS29)+(DU29*DV29)+(DX29*DY29)+(EA29*EB29) -> 0 | EE29: =ED29-DO29 -> 0
A30: =IFERROR(VLOOKUP(L30,'Base dados Exercicios'!$C$4:$J$305,3,FALSE),"") | B30: =IFERROR(VLOOKUP(L30,'Base dados Exercicios'!$C$4:$J$305,4,FALSE),"") | C30: =IFERROR(VLOOKUP(L30,'Base dados Exercicios'!$C$4:$J$305,5,FALSE),"") | D30: =IFERROR(VLOOKUP(L30,'Base dados Exercicios'!$C$4:$J$305,6,FALSE),"") | E30: =IFERROR(VLOOKUP(L30,'Base dados Exercicios'!$C$4:$J$305,7,FALSE),"") | F30: =IFERROR(VLOOKUP(L30,'Base dados Exercicios'!$C$4:$J$305,8,FALSE),"") | M30: =IF(L30<>"", HYPERLINK(VLOOKUP(L30,'Base dados Exercicios'!$C$4:$D$83,2,FALSE),"Check"),"") | AD30: =(R30*S30)+(U30*V30)+(X30*Y30)+(AA30*AB30) -> 0 | AR30: =(AF30*AG30)+(AI30*AJ30)+(AL30*AM30)+(AO30*AP30) -> 0 | AS30: =AR30-AD30 -> 0 | BG30: =(AU30*AV30)+(AX30*AY30)+(BA30*BB30)+(BD30*BE30) -> 0 | BH30: =BG30-AR30 -> 0 | BV30: =(BJ30*BK30)+(BM30*BN30)+(BP30*BQ30)+(BS30*BT30) -> 0 | BW30: =BV30-BG30 -> 0 | CK30: =(BY30*BZ30)+(CB30*CC30)+(CE30*CF30)+(CH30*CI30) -> 0 | CL30: =CK30-BV30 -> 0 | CZ30: =(CN30*CO30)+(CQ30*CR30)+(CT30*CU30)+(CW30*CX30) -> 0 | DA30: =CZ30-CK30 -> 0 | DO30: =(DC30*DD30)+(DF30*DG30)+(DI30*DJ30)+(DL30*DM30) -> 0 | DP30: =DO30-CZ30 -> 0 | ED30: =(DR30*DS30)+(DU30*DV30)+(DX30*DY30)+(EA30*EB30) -> 0 | EE30: =ED30-DO30 -> 0
A31: =IFERROR(VLOOKUP(L31,'Base dados Exercicios'!$C$4:$J$305,3,FALSE),"") | B31: =IFERROR(VLOOKUP(L31,'Base dados Exercicios'!$C$4:$J$305,4,FALSE),"") | C31: =IFERROR(VLOOKUP(L31,'Base dados Exercicios'!$C$4:$J$305,5,FALSE),"") | D31: =IFERROR(VLOOKUP(L31,'Base dados Exercicios'!$C$4:$J$305,6,FALSE),"") | E31: =IFERROR(VLOOKUP(L31,'Base dados Exercicios'!$C$4:$J$305,7,FALSE),"") | F31: =IFERROR(VLOOKUP(L31,'Base dados Exercicios'!$C$4:$J$305,8,FALSE),"") | H31: NOTAS IMPORTANTES | M31: =IF(L31<>"", HYPERLINK(VLOOKUP(L31,'Base dados Exercicios'!$C$4:$D$83,2,FALSE),"Check"),"") | AD31: =(R31*S31)+(U31*V31)+(X31*Y31)+(AA31*AB31) -> 0 | AR31: =(AF31*AG31)+(AI31*AJ31)+(AL31*AM31)+(AO31*AP31) -> 0 | AS31: =AR31-AD31 -> 0 | BG31: =(AU31*AV31)+(AX31*AY31)+(BA31*BB31)+(BD31*BE31) -> 0 | BH31: =BG31-AR31 -> 0 | BV31: =(BJ31*BK31)+(BM31*BN31)+(BP31*BQ31)+(BS31*BT31) -> 0 | BW31: =BV31-BG31 -> 0 | CK31: =(BY31*BZ31)+(CB31*CC31)+(CE31*CF31)+(CH31*CI31) -> 0 | CL31: =CK31-BV31 -> 0 | CZ31: =(CN31*CO31)+(CQ31*CR31)+(CT31*CU31)+(CW31*CX31) -> 0 | DA31: =CZ31-CK31 -> 0 | DO31: =(DC31*DD31)+(DF31*DG31)+(DI31*DJ31)+(DL31*DM31) -> 0 | DP31: =DO31-CZ31 -> 0 | ED31: =(DR31*DS31)+(DU31*DV31)+(DX31*DY31)+(EA31*EB31) -> 0 | EE31: =ED31-DO31 -> 0
A32: =IFERROR(VLOOKUP(L32,'Base dados Exercicios'!$C$4:$J$305,3,FALSE),"") | B32: =IFERROR(VLOOKUP(L32,'Base dados Exercicios'!$C$4:$J$305,4,FALSE),"") | C32: =IFERROR(VLOOKUP(L32,'Base dados Exercicios'!$C$4:$J$305,5,FALSE),"") | D32: =IFERROR(VLOOKUP(L32,'Base dados Exercicios'!$C$4:$J$305,6,FALSE),"") | E32: =IFERROR(VLOOKUP(L32,'Base dados Exercicios'!$C$4:$J$305,7,FALSE),"") | F32: =IFERROR(VLOOKUP(L32,'Base dados Exercicios'!$C$4:$J$305,8,FALSE),"") | H32: Aquecimento para primeiro exercicio: 30% da carga, 15 repetições/ 60% da carga, 8-10 repetições/ 80% da carga, 5 a 6 repetições, 100% da carga 2 a 3 repetições https://www.instagram.com/reel/CrWG0H9A7KB/?igshid=YmMyMTA2M2Y= | M32: =IF(L32<>"", HYPERLINK(VLOOKUP(L32,'Base dados Exercicios'!$C$4:$D$83,2,FALSE),"Check"),"") | AD32: =(R32*S32)+(U32*V32)+(X32*Y32)+(AA32*AB32) -> 0 | AR32: =(AF32*AG32)+(AI32*AJ32)+(AL32*AM32)+(AO32*AP32) -> 0 | AS32: =AR32-AD32 -> 0 | BG32: =(AU32*AV32)+(AX32*AY32)+(BA32*BB32)+(BD32*BE32) -> 0 | BH32: =BG32-AR32 -> 0 | BV32: =(BJ32*BK32)+(BM32*BN32)+(BP32*BQ32)+(BS32*BT32) -> 0 | BW32: =BV32-BG32 -> 0 | CK32: =(BY32*BZ32)+(CB32*CC32)+(CE32*CF32)+(CH32*CI32) -> 0 | CL32: =CK32-BV32 -> 0 | CZ32: =(CN32*CO32)+(CQ32*CR32)+(CT32*CU32)+(CW32*CX32) -> 0 | DA32: =CZ32-CK32 -> 0 | DO32: =(DC32*DD32)+(DF32*DG32)+(DI32*DJ32)+(DL32*DM32) -> 0 | DP32: =DO32-CZ32 -> 0 | ED32: =(DR32*DS32)+(DU32*DV32)+(DX32*DY32)+(EA32*EB32) -> 0 | EE32: =ED32-DO32 -> 0
A33: =IFERROR(VLOOKUP(L33,'Base dados Exercicios'!$C$4:$J$305,3,FALSE),"") | B33: =IFERROR(VLOOKUP(L33,'Base dados Exercicios'!$C$4:$J$305,4,FALSE),"") | C33: =IFERROR(VLOOKUP(L33,'Base dados Exercicios'!$C$4:$J$305,5,FALSE),"") | D33: =IFERROR(VLOOKUP(L33,'Base dados Exercicios'!$C$4:$J$305,6,FALSE),"") | E33: =IFERROR(VLOOKUP(L33,'Base dados Exercicios'!$C$4:$J$305,7,FALSE),"") | F33: =IFERROR(VLOOKUP(L33,'Base dados Exercicios'!$C$4:$J$305,8,FALSE),"") | M33: =IF(L33<>"", HYPERLINK(VLOOKUP(L33,'Base dados Exercicios'!$C$4:$D$83,2,FALSE),"Check"),"") | Q33: NOTAS: | AE33: NOTAS: | AT33: NOTAS: | BI33: NOTAS: | BX33: NOTAS: | CM33: NOTAS: | DB33: NOTAS: | DQ33: NOTAS:
A34: =IFERROR(VLOOKUP(L34,'Base dados Exercicios'!$C$4:$J$305,3,FALSE),"") | B34: =IFERROR(VLOOKUP(L34,'Base dados Exercicios'!$C$4:$J$305,4,FALSE),"") | C34: =IFERROR(VLOOKUP(L34,'Base dados Exercicios'!$C$4:$J$305,5,FALSE),"") | D34: =IFERROR(VLOOKUP(L34,'Base dados Exercicios'!$C$4:$J$305,6,FALSE),"") | E34: =IFERROR(VLOOKUP(L34,'Base dados Exercicios'!$C$4:$J$305,7,FALSE),"") | F34: =IFERROR(VLOOKUP(L34,'Base dados Exercicios'!$C$4:$J$305,8,FALSE),"") | K34: =I26 -> 0 | M34: =IF(L34<>"", HYPERLINK(VLOOKUP(L34,'Base dados Exercicios'!$C$4:$D$83,2,FALSE),"Check"),"") | AD34: =(R34*S34)+(U34*V34)+(X34*Y34)+(AA34*AB34) -> 0 | AR34: =(AF34*AG34)+(AI34*AJ34)+(AL34*AM34)+(AO34*AP34) -> 0 | AS34: =AR34-AD34 -> 0 | BG34: =(AU34*AV34)+(AX34*AY34)+(BA34*BB34)+(BD34*BE34) -> 0 | BH34: =BG34-AR34 -> 0 | BV34: =(BJ34*BK34)+(BM34*BN34)+(BP34*BQ34)+(BS34*BT34) -> 0 | BW34: =BV34-BG34 -> 0 | CK34: =(BY34*BZ34)+(CB34*CC34)+(CE34*CF34)+(CH34*CI34) -> 0 | CL34: =CK34-BV34 -> 0 | CZ34: =(CN34*CO34)+(CQ34*CR34)+(CT34*CU34)+(CW34*CX34) -> 0 | DA34: =CZ34-CK34 -> 0 | DO34: =(DC34*DD34)+(DF34*DG34)+(DI34*DJ34)+(DL34*DM34) -> 0 | DP34: =DO34-CZ34 -> 0 | ED34: =(DR34*DS34)+(DU34*DV34)+(DX34*DY34)+(EA34*EB34) -> 0 | EE34: =ED34-DO34 -> 0
A35: =IFERROR(VLOOKUP(L35,'Base dados Exercicios'!$C$4:$J$305,3,FALSE),"") | B35: =IFERROR(VLOOKUP(L35,'Base dados Exercicios'!$C$4:$J$305,4,FALSE),"") | C35: =IFERROR(VLOOKUP(L35,'Base dados Exercicios'!$C$4:$J$305,5,FALSE),"") | D35: =IFERROR(VLOOKUP(L35,'Base dados Exercicios'!$C$4:$J$305,6,FALSE),"") | E35: =IFERROR(VLOOKUP(L35,'Base dados Exercicios'!$C$4:$J$305,7,FALSE),"") | F35: =IFERROR(VLOOKUP(L35,'Base dados Exercicios'!$C$4:$J$305,8,FALSE),"") | M35: =IF(L35<>"", HYPERLINK(VLOOKUP(L35,'Base dados Exercicios'!$C$4:$D$83,2,FALSE),"Check"),"") | AD35: =(R35*S35)+(U35*V35)+(X35*Y35)+(AA35*AB35) -> 0 | AR35: =(AF35*AG35)+(AI35*AJ35)+(AL35*AM35)+(AO35*AP35) -> 0 | AS35: =AR35-AD35 -> 0 | BG35: =(AU35*AV35)+(AX35*AY35)+(BA35*BB35)+(BD35*BE35) -> 0 | BH35: =BG35-AR35 -> 0 | BV35: =(BJ35*BK35)+(BM35*BN35)+(BP35*BQ35)+(BS35*BT35) -> 0 | BW35: =BV35-BG35 -> 0 | CK35: =(BY35*BZ35)+(CB35*CC35)+(CE35*CF35)+(CH35*CI35) -> 0 | CL35: =CK35-BV35 -> 0 | CZ35: =(CN35*CO35)+(CQ35*CR35)+(CT35*CU35)+(CW35*CX35) -> 0 | DA35: =CZ35-CK35 -> 0 | DO35: =(DC35*DD35)+(DF35*DG35)+(DI35*DJ35)+(DL35*DM35) -> 0 | DP35: =DO35-CZ35 -> 0 | ED35: =(DR35*DS35)+(DU35*DV35)+(DX35*DY35)+(EA35*EB35) -> 0 | EE35: =ED35-DO35 -> 0
A36: =IFERROR(VLOOKUP(L36,'Base dados Exercicios'!$C$4:$J$305,3,FALSE),"") | B36: =IFERROR(VLOOKUP(L36,'Base dados Exercicios'!$C$4:$J$305,4,FALSE),"") | C36: =IFERROR(VLOOKUP(L36,'Base dados Exercicios'!$C$4:$J$305,5,FALSE),"") | D36: =IFERROR(VLOOKUP(L36,'Base dados Exercicios'!$C$4:$J$305,6,FALSE),"") | E36: =IFERROR(VLOOKUP(L36,'Base dados Exercicios'!$C$4:$J$305,7,FALSE),"") | F36: =IFERROR(VLOOKUP(L36,'Base dados Exercicios'!$C$4:$J$305,8,FALSE),"") | M36: =IF(L36<>"", HYPERLINK(VLOOKUP(L36,'Base dados Exercicios'!$C$4:$D$83,2,FALSE),"Check"),"") | AD36: =(R36*S36)+(U36*V36)+(X36*Y36)+(AA36*AB36) -> 0 | AR36: =(AF36*AG36)+(AI36*AJ36)+(AL36*AM36)+(AO36*AP36) -> 0 | AS36: =AR36-AD36 -> 0 | BG36: =(AU36*AV36)+(AX36*AY36)+(BA36*BB36)+(BD36*BE36) -> 0 | BH36: =BG36-AR36 -> 0 | BV36: =(BJ36*BK36)+(BM36*BN36)+(BP36*BQ36)+(BS36*BT36) -> 0 | BW36: =BV36-BG36 -> 0 | CK36: =(BY36*BZ36)+(CB36*CC36)+(CE36*CF36)+(CH36*CI36) -> 0 | CL36: =CK36-BV36 -> 0 | CZ36: =(CN36*CO36)+(CQ36*CR36)+(CT36*CU36)+(CW36*CX36) -> 0 | DA36: =CZ36-CK36 -> 0 | DO36: =(DC36*DD36)+(DF36*DG36)+(DI36*DJ36)+(DL36*DM36) -> 0 | DP36: =DO36-CZ36 -> 0 | ED36: =(DR36*DS36)+(DU36*DV36)+(DX36*DY36)+(EA36*EB36) -> 0 | EE36: =ED36-DO36 -> 0
A37: =IFERROR(VLOOKUP(L37,'Base dados Exercicios'!$C$4:$J$305,3,FALSE),"") | B37: =IFERROR(VLOOKUP(L37,'Base dados Exercicios'!$C$4:$J$305,4,FALSE),"") | C37: =IFERROR(VLOOKUP(L37,'Base dados Exercicios'!$C$4:$J$305,5,FALSE),"") | D37: =IFERROR(VLOOKUP(L37,'Base dados Exercicios'!$C$4:$J$305,6,FALSE),"") | E37: =IFERROR(VLOOKUP(L37,'Base dados Exercicios'!$C$4:$J$305,7,FALSE),"") | F37: =IFERROR(VLOOKUP(L37,'Base dados Exercicios'!$C$4:$J$305,8,FALSE),"") | M37: =IF(L37<>"", HYPERLINK(VLOOKUP(L37,'Base dados Exercicios'!$C$4:$D$83,2,FALSE),"Check"),"") | AD37: =(R37*S37)+(U37*V37)+(X37*Y37)+(AA37*AB37) -> 0 | AR37: =(AF37*AG37)+(AI37*AJ37)+(AL37*AM37)+(AO37*AP37) -> 0 | AS37: =AR37-AD37 -> 0 | BG37: =(AU37*AV37)+(AX37*AY37)+(BA37*BB37)+(BD37*BE37) -> 0 | BH37: =BG37-AR37 -> 0 | BV37: =(BJ37*BK37)+(BM37*BN37)+(BP37*BQ37)+(BS37*BT37) -> 0 | BW37: =BV37-BG37 -> 0 | CK37: =(BY37*BZ37)+(CB37*CC37)+(CE37*CF37)+(CH37*CI37) -> 0 | CL37: =CK37-BV37 -> 0 | CZ37: =(CN37*CO37)+(CQ37*CR37)+(CT37*CU37)+(CW37*CX37) -> 0 | DA37: =CZ37-CK37 -> 0 | DO37: =(DC37*DD37)+(DF37*DG37)+(DI37*DJ37)+(DL37*DM37) -> 0 | DP37: =DO37-CZ37 -> 0 | ED37: =(DR37*DS37)+(DU37*DV37)+(DX37*DY37)+(EA37*EB37) -> 0 | EE37: =ED37-DO37 -> 0
A38: =IFERROR(VLOOKUP(L38,'Base dados Exercicios'!$C$4:$J$305,3,FALSE),"") | B38: =IFERROR(VLOOKUP(L38,'Base dados Exercicios'!$C$4:$J$305,4,FALSE),"") | C38: =IFERROR(VLOOKUP(L38,'Base dados Exercicios'!$C$4:$J$305,5,FALSE),"") | D38: =IFERROR(VLOOKUP(L38,'Base dados Exercicios'!$C$4:$J$305,6,FALSE),"") | E38: =IFERROR(VLOOKUP(L38,'Base dados Exercicios'!$C$4:$J$305,7,FALSE),"") | F38: =IFERROR(VLOOKUP(L38,'Base dados Exercicios'!$C$4:$J$305,8,FALSE),"") | H38: As séries do treino são séries de trabalho, deves ficar entre as 2 e as 0 repetições da falhga muscular | M38: =IF(L38<>"", HYPERLINK(VLOOKUP(L38,'Base dados Exercicios'!$C$4:$D$83,2,FALSE),"Check"),"") | AD38: =(R38*S38)+(U38*V38)+(X38*Y38)+(AA38*AB38) -> 0 | AR38: =(AF38*AG38)+(AI38*AJ38)+(AL38*AM38)+(AO38*AP38) -> 0 | AS38: =AR38-AD38 -> 0 | BG38: =(AU38*AV38)+(AX38*AY38)+(BA38*BB38)+(BD38*BE38) -> 0 | BH38: =BG38-AR38 -> 0 | BV38: =(BJ38*BK38)+(BM38*BN38)+(BP38*BQ38)+(BS38*BT38) -> 0 | BW38: =BV38-BG38 -> 0 | CK38: =(BY38*BZ38)+(CB38*CC38)+(CE38*CF38)+(CH38*CI38) -> 0 | CL38: =CK38-BV38 -> 0 | CZ38: =(CN38*CO38)+(CQ38*CR38)+(CT38*CU38)+(CW38*CX38) -> 0 | DA38: =CZ38-CK38 -> 0 | DO38: =(DC38*DD38)+(DF38*DG38)+(DI38*DJ38)+(DL38*DM38) -> 0 | DP38: =DO38-CZ38 -> 0 | ED38: =(DR38*DS38)+(DU38*DV38)+(DX38*DY38)+(EA38*EB38) -> 0 | EE38: =ED38-DO38 -> 0
A39: =IFERROR(VLOOKUP(L39,'Base dados Exercicios'!$C$4:$J$305,3,FALSE),"") | B39: =IFERROR(VLOOKUP(L39,'Base dados Exercicios'!$C$4:$J$305,4,FALSE),"") | C39: =IFERROR(VLOOKUP(L39,'Base dados Exercicios'!$C$4:$J$305,5,FALSE),"") | D39: =IFERROR(VLOOKUP(L39,'Base dados Exercicios'!$C$4:$J$305,6,FALSE),"") | E39: =IFERROR(VLOOKUP(L39,'Base dados Exercicios'!$C$4:$J$305,7,FALSE),"") | F39: =IFERROR(VLOOKUP(L39,'Base dados Exercicios'!$C$4:$J$305,8,FALSE),"") | M39: =IF(L39<>"", HYPERLINK(VLOOKUP(L39,'Base dados Exercicios'!$C$4:$D$83,2,FALSE),"Check"),"") | AD39: =(R39*S39)+(U39*V39)+(X39*Y39)+(AA39*AB39) -> 0 | AR39: =(AF39*AG39)+(AI39*AJ39)+(AL39*AM39)+(AO39*AP39) -> 0 | AS39: =AR39-AD39 -> 0 | BG39: =(AU39*AV39)+(AX39*AY39)+(BA39*BB39)+(BD39*BE39) -> 0 | BH39: =BG39-AR39 -> 0 | BV39: =(BJ39*BK39)+(BM39*BN39)+(BP39*BQ39)+(BS39*BT39) -> 0 | BW39: =BV39-BG39 -> 0 | CK39: =(BY39*BZ39)+(CB39*CC39)+(CE39*CF39)+(CH39*CI39) -> 0 | CL39: =CK39-BV39 -> 0 | CZ39: =(CN39*CO39)+(CQ39*CR39)+(CT39*CU39)+(CW39*CX39) -> 0 | DA39: =CZ39-CK39 -> 0 | DO39: =(DC39*DD39)+(DF39*DG39)+(DI39*DJ39)+(DL39*DM39) -> 0 | DP39: =DO39-CZ39 -> 0 | ED39: =(DR39*DS39)+(DU39*DV39)+(DX39*DY39)+(EA39*EB39) -> 0 | EE39: =ED39-DO39 -> 0
A40: =IFERROR(VLOOKUP(L40,'Base dados Exercicios'!$C$4:$J$305,3,FALSE),"") | B40: =IFERROR(VLOOKUP(L40,'Base dados Exercicios'!$C$4:$J$305,4,FALSE),"") | C40: =IFERROR(VLOOKUP(L40,'Base dados Exercicios'!$C$4:$J$305,5,FALSE),"") | D40: =IFERROR(VLOOKUP(L40,'Base dados Exercicios'!$C$4:$J$305,6,FALSE),"") | E40: =IFERROR(VLOOKUP(L40,'Base dados Exercicios'!$C$4:$J$305,7,FALSE),"") | F40: =IFERROR(VLOOKUP(L40,'Base dados Exercicios'!$C$4:$J$305,8,FALSE),"") | M40: =IF(L40<>"", HYPERLINK(VLOOKUP(L40,'Base dados Exercicios'!$C$4:$D$83,2,FALSE),"Check"),"") | AD40: =(R40*S40)+(U40*V40)+(X40*Y40)+(AA40*AB40) -> 0 | AR40: =(AF40*AG40)+(AI40*AJ40)+(AL40*AM40)+(AO40*AP40) -> 0 | AS40: =AR40-AD40 -> 0 | BG40: =(AU40*AV40)+(AX40*AY40)+(BA40*BB40)+(BD40*BE40) -> 0 | BH40: =BG40-AR40 -> 0 | BV40: =(BJ40*BK40)+(BM40*BN40)+(BP40*BQ40)+(BS40*BT40) -> 0 | BW40: =BV40-BG40 -> 0 | CK40: =(BY40*BZ40)+(CB40*CC40)+(CE40*CF40)+(CH40*CI40) -> 0 | CL40: =CK40-BV40 -> 0 | CZ40: =(CN40*CO40)+(CQ40*CR40)+(CT40*CU40)+(CW40*CX40) -> 0 | DA40: =CZ40-CK40 -> 0 | DO40: =(DC40*DD40)+(DF40*DG40)+(DI40*DJ40)+(DL40*DM40) -> 0 | DP40: =DO40-CZ40 -> 0 | ED40: =(DR40*DS40)+(DU40*DV40)+(DX40*DY40)+(EA40*EB40) -> 0 | EE40: =ED40-DO40 -> 0
A41: =IFERROR(VLOOKUP(L41,'Base dados Exercicios'!$C$4:$J$305,3,FALSE),"") | B41: =IFERROR(VLOOKUP(L41,'Base dados Exercicios'!$C$4:$J$305,4,FALSE),"") | C41: =IFERROR(VLOOKUP(L41,'Base dados Exercicios'!$C$4:$J$305,5,FALSE),"") | D41: =IFERROR(VLOOKUP(L41,'Base dados Exercicios'!$C$4:$J$305,6,FALSE),"") | E41: =IFERROR(VLOOKUP(L41,'Base dados Exercicios'!$C$4:$J$305,7,FALSE),"") | F41: =IFERROR(VLOOKUP(L41,'Base dados Exercicios'!$C$4:$J$305,8,FALSE),"") | H41: Sempre que conseguires fazer o limite máximo de repetições, na série seguinte aumenta a carga. Sempre que não conseguiures fazer o limite minimo de repetições, na série seguinte diminui a carga. | M41: =IF(L41<>"", HYPERLINK(VLOOKUP(L41,'Base dados Exercicios'!$C$4:$D$83,2,FALSE),"Check"),"") | AD41: =(R41*S41)+(U41*V41)+(X41*Y41)+(AA41*AB41) -> 0 | AR41: =(AF41*AG41)+(AI41*AJ41)+(AL41*AM41)+(AO41*AP41) -> 0 | AS41: =AR41-AD41 -> 0 | BG41: =(AU41*AV41)+(AX41*AY41)+(BA41*BB41)+(BD41*BE41) -> 0 | BH41: =BG41-AR41 -> 0 | BV41: =(BJ41*BK41)+(BM41*BN41)+(BP41*BQ41)+(BS41*BT41) -> 0 | BW41: =BV41-BG41 -> 0 | CK41: =(BY41*BZ41)+(CB41*CC41)+(CE41*CF41)+(CH41*CI41) -> 0 | CL41: =CK41-BV41 -> 0 | CZ41: =(CN41*CO41)+(CQ41*CR41)+(CT41*CU41)+(CW41*CX41) -> 0 | DA41: =CZ41-CK41 -> 0 | DO41: =(DC41*DD41)+(DF41*DG41)+(DI41*DJ41)+(DL41*DM41) -> 0 | DP41: =DO41-CZ41 -> 0 | ED41: =(DR41*DS41)+(DU41*DV41)+(DX41*DY41)+(EA41*EB41) -> 0 | EE41: =ED41-DO41 -> 0
A42: =IFERROR(VLOOKUP(L42,'Base dados Exercicios'!$C$4:$J$305,3,FALSE),"") | B42: =IFERROR(VLOOKUP(L42,'Base dados Exercicios'!$C$4:$J$305,4,FALSE),"") | C42: =IFERROR(VLOOKUP(L42,'Base dados Exercicios'!$C$4:$J$305,5,FALSE),"") | D42: =IFERROR(VLOOKUP(L42,'Base dados Exercicios'!$C$4:$J$305,6,FALSE),"") | E42: =IFERROR(VLOOKUP(L42,'Base dados Exercicios'!$C$4:$J$305,7,FALSE),"") | F42: =IFERROR(VLOOKUP(L42,'Base dados Exercicios'!$C$4:$J$305,8,FALSE),"") | M42: =IF(L42<>"", HYPERLINK(VLOOKUP(L42,'Base dados Exercicios'!$C$4:$D$83,2,FALSE),"Check"),"") | AD42: =(R42*S42)+(U42*V42)+(X42*Y42)+(AA42*AB42) -> 0 | AR42: =(AF42*AG42)+(AI42*AJ42)+(AL42*AM42)+(AO42*AP42) -> 0 | AS42: =AR42-AD42 -> 0 | BG42: =(AU42*AV42)+(AX42*AY42)+(BA42*BB42)+(BD42*BE42) -> 0 | BH42: =BG42-AR42 -> 0 | BV42: =(BJ42*BK42)+(BM42*BN42)+(BP42*BQ42)+(BS42*BT42) -> 0 | BW42: =BV42-BG42 -> 0 | CK42: =(BY42*BZ42)+(CB42*CC42)+(CE42*CF42)+(CH42*CI42) -> 0 | CL42: =CK42-BV42 -> 0 | CZ42: =(CN42*CO42)+(CQ42*CR42)+(CT42*CU42)+(CW42*CX42) -> 0 | DA42: =CZ42-CK42 -> 0 | DO42: =(DC42*DD42)+(DF42*DG42)+(DI42*DJ42)+(DL42*DM42) -> 0 | DP42: =DO42-CZ42 -> 0 | ED42: =(DR42*DS42)+(DU42*DV42)+(DX42*DY42)+(EA42*EB42) -> 0 | EE42: =ED42-DO42 -> 0
A43: =IFERROR(VLOOKUP(L43,'Base dados Exercicios'!$C$4:$J$305,3,FALSE),"") | B43: =IFERROR(VLOOKUP(L43,'Base dados Exercicios'!$C$4:$J$305,4,FALSE),"") | C43: =IFERROR(VLOOKUP(L43,'Base dados Exercicios'!$C$4:$J$305,5,FALSE),"") | D43: =IFERROR(VLOOKUP(L43,'Base dados Exercicios'!$C$4:$J$305,6,FALSE),"") | E43: =IFERROR(VLOOKUP(L43,'Base dados Exercicios'!$C$4:$J$305,7,FALSE),"") | F43: =IFERROR(VLOOKUP(L43,'Base dados Exercicios'!$C$4:$J$305,8,FALSE),"") | M43: =IF(L43<>"", HYPERLINK(VLOOKUP(L43,'Base dados Exercicios'!$C$4:$D$83,2,FALSE),"Check"),"") | Q43: NOTAS: | AE43: NOTAS: | AT43: NOTAS: | BI43: NOTAS: | BX43: NOTAS: | CM43: NOTAS: | DB43: NOTAS: | DQ43: NOTAS:
A44: =IFERROR(VLOOKUP(L44,'Base dados Exercicios'!$C$4:$J$305,3,FALSE),"") | B44: =IFERROR(VLOOKUP(L44,'Base dados Exercicios'!$C$4:$J$305,4,FALSE),"") | C44: =IFERROR(VLOOKUP(L44,'Base dados Exercicios'!$C$4:$J$305,5,FALSE),"") | D44: =IFERROR(VLOOKUP(L44,'Base dados Exercicios'!$C$4:$J$305,6,FALSE),"") | E44: =IFERROR(VLOOKUP(L44,'Base dados Exercicios'!$C$4:$J$305,7,FALSE),"") | F44: =IFERROR(VLOOKUP(L44,'Base dados Exercicios'!$C$4:$J$305,8,FALSE),"") | K44: =I27 -> 0 | M44: =IF(L44<>"", HYPERLINK(VLOOKUP(L44,'Base dados Exercicios'!$C$4:$D$83,2,FALSE),"Check"),"") | AD44: =(R44*S44)+(U44*V44)+(X44*Y44)+(AA44*AB44) -> 0 | AR44: =(AF44*AG44)+(AI44*AJ44)+(AL44*AM44)+(AO44*AP44) -> 0 | AS44: =AR44-AD44 -> 0 | BG44: =(AU44*AV44)+(AX44*AY44)+(BA44*BB44)+(BD44*BE44) -> 0 | BH44: =BG44-AR44 -> 0 | BV44: =(BJ44*BK44)+(BM44*BN44)+(BP44*BQ44)+(BS44*BT44) -> 0 | BW44: =BV44-BG44 -> 0 | CK44: =(BY44*BZ44)+(CB44*CC44)+(CE44*CF44)+(CH44*CI44) -> 0 | CL44: =CK44-BV44 -> 0 | CZ44: =(CN44*CO44)+(CQ44*CR44)+(CT44*CU44)+(CW44*CX44) -> 0 | DA44: =CZ44-CK44 -> 0 | DO44: =(DC44*DD44)+(DF44*DG44)+(DI44*DJ44)+(DL44*DM44) -> 0 | DP44: =DO44-CZ44 -> 0 | ED44: =(DR44*DS44)+(DU44*DV44)+(DX44*DY44)+(EA44*EB44) -> 0 | EE44: =ED44-DO44 -> 0
A45: =IFERROR(VLOOKUP(L45,'Base dados Exercicios'!$C$4:$J$305,3,FALSE),"") | B45: =IFERROR(VLOOKUP(L45,'Base dados Exercicios'!$C$4:$J$305,4,FALSE),"") | C45: =IFERROR(VLOOKUP(L45,'Base dados Exercicios'!$C$4:$J$305,5,FALSE),"") | D45: =IFERROR(VLOOKUP(L45,'Base dados Exercicios'!$C$4:$J$305,6,FALSE),"") | E45: =IFERROR(VLOOKUP(L45,'Base dados Exercicios'!$C$4:$J$305,7,FALSE),"") | F45: =IFERROR(VLOOKUP(L45,'Base dados Exercicios'!$C$4:$J$305,8,FALSE),"") | M45: =IF(L45<>"", HYPERLINK(VLOOKUP(L45,'Base dados Exercicios'!$C$4:$D$83,2,FALSE),"Check"),"") | AD45: =(R45*S45)+(U45*V45)+(X45*Y45)+(AA45*AB45) -> 0 | AR45: =(AF45*AG45)+(AI45*AJ45)+(AL45*AM45)+(AO45*AP45) -> 0 | AS45: =AR45-AD45 -> 0 | BG45: =(AU45*AV45)+(AX45*AY45)+(BA45*BB45)+(BD45*BE45) -> 0 | BH45: =BG45-AR45 -> 0 | BV45: =(BJ45*BK45)+(BM45*BN45)+(BP45*BQ45)+(BS45*BT45) -> 0 | BW45: =BV45-BG45 -> 0 | CK45: =(BY45*BZ45)+(CB45*CC45)+(CE45*CF45)+(CH45*CI45) -> 0 | CL45: =CK45-BV45 -> 0 | CZ45: =(CN45*CO45)+(CQ45*CR45)+(CT45*CU45)+(CW45*CX45) -> 0 | DA45: =CZ45-CK45 -> 0 | DO45: =(DC45*DD45)+(DF45*DG45)+(DI45*DJ45)+(DL45*DM45) -> 0 | DP45: =DO45-CZ45 -> 0 | ED45: =(DR45*DS45)+(DU45*DV45)+(DX45*DY45)+(EA45*EB45) -> 0 | EE45: =ED45-DO45 -> 0
A46: =IFERROR(VLOOKUP(L46,'Base dados Exercicios'!$C$4:$J$305,3,FALSE),"") | B46: =IFERROR(VLOOKUP(L46,'Base dados Exercicios'!$C$4:$J$305,4,FALSE),"") | C46: =IFERROR(VLOOKUP(L46,'Base dados Exercicios'!$C$4:$J$305,5,FALSE),"") | D46: =IFERROR(VLOOKUP(L46,'Base dados Exercicios'!$C$4:$J$305,6,FALSE),"") | E46: =IFERROR(VLOOKUP(L46,'Base dados Exercicios'!$C$4:$J$305,7,FALSE),"") | F46: =IFERROR(VLOOKUP(L46,'Base dados Exercicios'!$C$4:$J$305,8,FALSE),"") | H46: O foco deve estar na técnica, amplitude e controle do movmento | M46: =IF(L46<>"", HYPERLINK(VLOOKUP(L46,'Base dados Exercicios'!$C$4:$D$83,2,FALSE),"Check"),"") | AD46: =(R46*S46)+(U46*V46)+(X46*Y46)+(AA46*AB46) -> 0 | AR46: =(AF46*AG46)+(AI46*AJ46)+(AL46*AM46)+(AO46*AP46) -> 0 | AS46: =AR46-AD46 -> 0 | BG46: =(AU46*AV46)+(AX46*AY46)+(BA46*BB46)+(BD46*BE46) -> 0 | BH46: =BG46-AR46 -> 0 | BV46: =(BJ46*BK46)+(BM46*BN46)+(BP46*BQ46)+(BS46*BT46) -> 0 | BW46: =BV46-BG46 -> 0 | CK46: =(BY46*BZ46)+(CB46*CC46)+(CE46*CF46)+(CH46*CI46) -> 0 | CL46: =CK46-BV46 -> 0 | CZ46: =(CN46*CO46)+(CQ46*CR46)+(CT46*CU46)+(CW46*CX46) -> 0 | DA46: =CZ46-CK46 -> 0 | DO46: =(DC46*DD46)+(DF46*DG46)+(DI46*DJ46)+(DL46*DM46) -> 0 | DP46: =DO46-CZ46 -> 0 | ED46: =(DR46*DS46)+(DU46*DV46)+(DX46*DY46)+(EA46*EB46) -> 0 | EE46: =ED46-DO46 -> 0
A47: =IFERROR(VLOOKUP(L47,'Base dados Exercicios'!$C$4:$J$305,3,FALSE),"") | B47: =IFERROR(VLOOKUP(L47,'Base dados Exercicios'!$C$4:$J$305,4,FALSE),"") | C47: =IFERROR(VLOOKUP(L47,'Base dados Exercicios'!$C$4:$J$305,5,FALSE),"") | D47: =IFERROR(VLOOKUP(L47,'Base dados Exercicios'!$C$4:$J$305,6,FALSE),"") | E47: =IFERROR(VLOOKUP(L47,'Base dados Exercicios'!$C$4:$J$305,7,FALSE),"") | F47: =IFERROR(VLOOKUP(L47,'Base dados Exercicios'!$C$4:$J$305,8,FALSE),"") | M47: =IF(L47<>"", HYPERLINK(VLOOKUP(L47,'Base dados Exercicios'!$C$4:$D$83,2,FALSE),"Check"),"") | AD47: =(R47*S47)+(U47*V47)+(X47*Y47)+(AA47*AB47) -> 0 | AR47: =(AF47*AG47)+(AI47*AJ47)+(AL47*AM47)+(AO47*AP47) -> 0 | AS47: =AR47-AD47 -> 0 | BG47: =(AU47*AV47)+(AX47*AY47)+(BA47*BB47)+(BD47*BE47) -> 0 | BH47: =BG47-AR47 -> 0 | BV47: =(BJ47*BK47)+(BM47*BN47)+(BP47*BQ47)+(BS47*BT47) -> 0 | BW47: =BV47-BG47 -> 0 | CK47: =(BY47*BZ47)+(CB47*CC47)+(CE47*CF47)+(CH47*CI47) -> 0 | CL47: =CK47-BV47 -> 0 | CZ47: =(CN47*CO47)+(CQ47*CR47)+(CT47*CU47)+(CW47*CX47) -> 0 | DA47: =CZ47-CK47 -> 0 | DO47: =(DC47*DD47)+(DF47*DG47)+(DI47*DJ47)+(DL47*DM47) -> 0 | DP47: =DO47-CZ47 -> 0 | ED47: =(DR47*DS47)+(DU47*DV47)+(DX47*DY47)+(EA47*EB47) -> 0 | EE47: =ED47-DO47 -> 0
A48: =IFERROR(VLOOKUP(L48,'Base dados Exercicios'!$C$4:$J$305,3,FALSE),"") | B48: =IFERROR(VLOOKUP(L48,'Base dados Exercicios'!$C$4:$J$305,4,FALSE),"") | C48: =IFERROR(VLOOKUP(L48,'Base dados Exercicios'!$C$4:$J$305,5,FALSE),"") | D48: =IFERROR(VLOOKUP(L48,'Base dados Exercicios'!$C$4:$J$305,6,FALSE),"") | E48: =IFERROR(VLOOKUP(L48,'Base dados Exercicios'!$C$4:$J$305,7,FALSE),"") | F48: =IFERROR(VLOOKUP(L48,'Base dados Exercicios'!$C$4:$J$305,8,FALSE),"") | M48: =IF(L48<>"", HYPERLINK(VLOOKUP(L48,'Base dados Exercicios'!$C$4:$D$83,2,FALSE),"Check"),"") | AD48: =(R48*S48)+(U48*V48)+(X48*Y48)+(AA48*AB48) -> 0 | AR48: =(AF48*AG48)+(AI48*AJ48)+(AL48*AM48)+(AO48*AP48) -> 0 | AS48: =AR48-AD48 -> 0 | BG48: =(AU48*AV48)+(AX48*AY48)+(BA48*BB48)+(BD48*BE48) -> 0 | BH48: =BG48-AR48 -> 0 | BV48: =(BJ48*BK48)+(BM48*BN48)+(BP48*BQ48)+(BS48*BT48) -> 0 | BW48: =BV48-BG48 -> 0 | CK48: =(BY48*BZ48)+(CB48*CC48)+(CE48*CF48)+(CH48*CI48) -> 0 | CL48: =CK48-BV48 -> 0 | CZ48: =(CN48*CO48)+(CQ48*CR48)+(CT48*CU48)+(CW48*CX48) -> 0 | DA48: =CZ48-CK48 -> 0 | DO48: =(DC48*DD48)+(DF48*DG48)+(DI48*DJ48)+(DL48*DM48) -> 0 | DP48: =DO48-CZ48 -> 0 | ED48: =(DR48*DS48)+(DU48*DV48)+(DX48*DY48)+(EA48*EB48) -> 0 | EE48: =ED48-DO48 -> 0
A49: =IFERROR(VLOOKUP(L49,'Base dados Exercicios'!$C$4:$J$305,3,FALSE),"") | B49: =IFERROR(VLOOKUP(L49,'Base dados Exercicios'!$C$4:$J$305,4,FALSE),"") | C49: =IFERROR(VLOOKUP(L49,'Base dados Exercicios'!$C$4:$J$305,5,FALSE),"") | D49: =IFERROR(VLOOKUP(L49,'Base dados Exercicios'!$C$4:$J$305,6,FALSE),"") | E49: =IFERROR(VLOOKUP(L49,'Base dados Exercicios'!$C$4:$J$305,7,FALSE),"") | F49: =IFERROR(VLOOKUP(L49,'Base dados Exercicios'!$C$4:$J$305,8,FALSE),"") | M49: =IF(L49<>"", HYPERLINK(VLOOKUP(L49,'Base dados Exercicios'!$C$4:$D$83,2,FALSE),"Check"),"") | AD49: =(R49*S49)+(U49*V49)+(X49*Y49)+(AA49*AB49) -> 0 | AR49: =(AF49*AG49)+(AI49*AJ49)+(AL49*AM49)+(AO49*AP49) -> 0 | AS49: =AR49-AD49 -> 0 | BG49: =(AU49*AV49)+(AX49*AY49)+(BA49*BB49)+(BD49*BE49) -> 0 | BH49: =BG49-AR49 -> 0 | BV49: =(BJ49*BK49)+(BM49*BN49)+(BP49*BQ49)+(BS49*BT49) -> 0 | BW49: =BV49-BG49 -> 0 | CK49: =(BY49*BZ49)+(CB49*CC49)+(CE49*CF49)+(CH49*CI49) -> 0 | CL49: =CK49-BV49 -> 0 | CZ49: =(CN49*CO49)+(CQ49*CR49)+(CT49*CU49)+(CW49*CX49) -> 0 | DA49: =CZ49-CK49 -> 0 | DO49: =(DC49*DD49)+(DF49*DG49)+(DI49*DJ49)+(DL49*DM49) -> 0 | DP49: =DO49-CZ49 -> 0 | ED49: =(DR49*DS49)+(DU49*DV49)+(DX49*DY49)+(EA49*EB49) -> 0 | EE49: =ED49-DO49 -> 0
A50: =IFERROR(VLOOKUP(L50,'Base dados Exercicios'!$C$4:$J$305,3,FALSE),"") | B50: =IFERROR(VLOOKUP(L50,'Base dados Exercicios'!$C$4:$J$305,4,FALSE),"") | C50: =IFERROR(VLOOKUP(L50,'Base dados Exercicios'!$C$4:$J$305,5,FALSE),"") | D50: =IFERROR(VLOOKUP(L50,'Base dados Exercicios'!$C$4:$J$305,6,FALSE),"") | E50: =IFERROR(VLOOKUP(L50,'Base dados Exercicios'!$C$4:$J$305,7,FALSE),"") | F50: =IFERROR(VLOOKUP(L50,'Base dados Exercicios'!$C$4:$J$305,8,FALSE),"") | M50: =IF(L50<>"", HYPERLINK(VLOOKUP(L50,'Base dados Exercicios'!$C$4:$D$83,2,FALSE),"Check"),"") | AD50: =(R50*S50)+(U50*V50)+(X50*Y50)+(AA50*AB50) -> 0 | AR50: =(AF50*AG50)+(AI50*AJ50)+(AL50*AM50)+(AO50*AP50) -> 0 | AS50: =AR50-AD50 -> 0 | BG50: =(AU50*AV50)+(AX50*AY50)+(BA50*BB50)+(BD50*BE50) -> 0 | BH50: =BG50-AR50 -> 0 | BV50: =(BJ50*BK50)+(BM50*BN50)+(BP50*BQ50)+(BS50*BT50) -> 0 | BW50: =BV50-BG50 -> 0 | CK50: =(BY50*BZ50)+(CB50*CC50)+(CE50*CF50)+(CH50*CI50) -> 0 | CL50: =CK50-BV50 -> 0 | CZ50: =(CN50*CO50)+(CQ50*CR50)+(CT50*CU50)+(CW50*CX50) -> 0 | DA50: =CZ50-CK50 -> 0 | DO50: =(DC50*DD50)+(DF50*DG50)+(DI50*DJ50)+(DL50*DM50) -> 0 | DP50: =DO50-CZ50 -> 0 | ED50: =(DR50*DS50)+(DU50*DV50)+(DX50*DY50)+(EA50*EB50) -> 0 | EE50: =ED50-DO50 -> 0
A51: =IFERROR(VLOOKUP(L51,'Base dados Exercicios'!$C$4:$J$305,3,FALSE),"") | B51: =IFERROR(VLOOKUP(L51,'Base dados Exercicios'!$C$4:$J$305,4,FALSE),"") | C51: =IFERROR(VLOOKUP(L51,'Base dados Exercicios'!$C$4:$J$305,5,FALSE),"") | D51: =IFERROR(VLOOKUP(L51,'Base dados Exercicios'!$C$4:$J$305,6,FALSE),"") | E51: =IFERROR(VLOOKUP(L51,'Base dados Exercicios'!$C$4:$J$305,7,FALSE),"") | F51: =IFERROR(VLOOKUP(L51,'Base dados Exercicios'!$C$4:$J$305,8,FALSE),"") | M51: =IF(L51<>"", HYPERLINK(VLOOKUP(L51,'Base dados Exercicios'!$C$4:$D$83,2,FALSE),"Check"),"") | AD51: =(R51*S51)+(U51*V51)+(X51*Y51)+(AA51*AB51) -> 0 | AR51: =(AF51*AG51)+(AI51*AJ51)+(AL51*AM51)+(AO51*AP51) -> 0 | AS51: =AR51-AD51 -> 0 | BG51: =(AU51*AV51)+(AX51*AY51)+(BA51*BB51)+(BD51*BE51) -> 0 | BH51: =BG51-AR51 -> 0 | BV51: =(BJ51*BK51)+(BM51*BN51)+(BP51*BQ51)+(BS51*BT51) -> 0 | BW51: =BV51-BG51 -> 0 | CK51: =(BY51*BZ51)+(CB51*CC51)+(CE51*CF51)+(CH51*CI51) -> 0 | CL51: =CK51-BV51 -> 0 | CZ51: =(CN51*CO51)+(CQ51*CR51)+(CT51*CU51)+(CW51*CX51) -> 0 | DA51: =CZ51-CK51 -> 0 | DO51: =(DC51*DD51)+(DF51*DG51)+(DI51*DJ51)+(DL51*DM51) -> 0 | DP51: =DO51-CZ51 -> 0 | ED51: =(DR51*DS51)+(DU51*DV51)+(DX51*DY51)+(EA51*EB51) -> 0 | EE51: =ED51-DO51 -> 0
A52: =IFERROR(VLOOKUP(L52,'Base dados Exercicios'!$C$4:$J$305,3,FALSE),"") | B52: =IFERROR(VLOOKUP(L52,'Base dados Exercicios'!$C$4:$J$305,4,FALSE),"") | C52: =IFERROR(VLOOKUP(L52,'Base dados Exercicios'!$C$4:$J$305,5,FALSE),"") | D52: =IFERROR(VLOOKUP(L52,'Base dados Exercicios'!$C$4:$J$305,6,FALSE),"") | E52: =IFERROR(VLOOKUP(L52,'Base dados Exercicios'!$C$4:$J$305,7,FALSE),"") | F52: =IFERROR(VLOOKUP(L52,'Base dados Exercicios'!$C$4:$J$305,8,FALSE),"") | M52: =IF(L52<>"", HYPERLINK(VLOOKUP(L52,'Base dados Exercicios'!$C$4:$D$83,2,FALSE),"Check"),"") | AD52: =(R52*S52)+(U52*V52)+(X52*Y52)+(AA52*AB52) -> 0 | AR52: =(AF52*AG52)+(AI52*AJ52)+(AL52*AM52)+(AO52*AP52) -> 0 | AS52: =AR52-AD52 -> 0 | BG52: =(AU52*AV52)+(AX52*AY52)+(BA52*BB52)+(BD52*BE52) -> 0 | BH52: =BG52-AR52 -> 0 | BV52: =(BJ52*BK52)+(BM52*BN52)+(BP52*BQ52)+(BS52*BT52) -> 0 | BW52: =BV52-BG52 -> 0 | CK52: =(BY52*BZ52)+(CB52*CC52)+(CE52*CF52)+(CH52*CI52) -> 0 | CL52: =CK52-BV52 -> 0 | CZ52: =(CN52*CO52)+(CQ52*CR52)+(CT52*CU52)+(CW52*CX52) -> 0 | DA52: =CZ52-CK52 -> 0 | DO52: =(DC52*DD52)+(DF52*DG52)+(DI52*DJ52)+(DL52*DM52) -> 0 | DP52: =DO52-CZ52 -> 0 | ED52: =(DR52*DS52)+(DU52*DV52)+(DX52*DY52)+(EA52*EB52) -> 0 | EE52: =ED52-DO52 -> 0
A53: =IFERROR(VLOOKUP(L53,'Base dados Exercicios'!$C$4:$J$305,3,FALSE),"") | B53: =IFERROR(VLOOKUP(L53,'Base dados Exercicios'!$C$4:$J$305,4,FALSE),"") | C53: =IFERROR(VLOOKUP(L53,'Base dados Exercicios'!$C$4:$J$305,5,FALSE),"") | D53: =IFERROR(VLOOKUP(L53,'Base dados Exercicios'!$C$4:$J$305,6,FALSE),"") | E53: =IFERROR(VLOOKUP(L53,'Base dados Exercicios'!$C$4:$J$305,7,FALSE),"") | F53: =IFERROR(VLOOKUP(L53,'Base dados Exercicios'!$C$4:$J$305,8,FALSE),"") | M53: =IF(L53<>"", HYPERLINK(VLOOKUP(L53,'Base dados Exercicios'!$C$4:$D$83,2,FALSE),"Check"),"") | Q53: NOTAS: | AE53: NOTAS: | AT53: NOTAS: | BI53: NOTAS: | BX53: NOTAS: | CM53: NOTAS: | DB53: NOTAS: | DQ53: NOTAS:
A54: =IFERROR(VLOOKUP(L54,'Base dados Exercicios'!$C$4:$J$305,3,FALSE),"") | B54: =IFERROR(VLOOKUP(L54,'Base dados Exercicios'!$C$4:$J$305,4,FALSE),"") | C54: =IFERROR(VLOOKUP(L54,'Base dados Exercicios'!$C$4:$J$305,5,FALSE),"") | D54: =IFERROR(VLOOKUP(L54,'Base dados Exercicios'!$C$4:$J$305,6,FALSE),"") | E54: =IFERROR(VLOOKUP(L54,'Base dados Exercicios'!$C$4:$J$305,7,FALSE),"") | F54: =IFERROR(VLOOKUP(L54,'Base dados Exercicios'!$C$4:$J$305,8,FALSE),"") | K54: =I28 -> 0 | M54: =IF(L54<>"", HYPERLINK(VLOOKUP(L54,'Base dados Exercicios'!$C$4:$D$83,2,FALSE),"Check"),"") | AD54: =(R54*S54)+(U54*V54)+(X54*Y54)+(AA54*AB54) -> 0 | AR54: =(AF54*AG54)+(AI54*AJ54)+(AL54*AM54)+(AO54*AP54) -> 0 | AS54: =AR54-AD54 -> 0 | BG54: =(AU54*AV54)+(AX54*AY54)+(BA54*BB54)+(BD54*BE54) -> 0 | BH54: =BG54-AR54 -> 0 | BV54: =(BJ54*BK54)+(BM54*BN54)+(BP54*BQ54)+(BS54*BT54) -> 0 | BW54: =BV54-BG54 -> 0 | CK54: =(BY54*BZ54)+(CB54*CC54)+(CE54*CF54)+(CH54*CI54) -> 0 | CL54: =CK54-BV54 -> 0 | CZ54: =(CN54*CO54)+(CQ54*CR54)+(CT54*CU54)+(CW54*CX54) -> 0 | DA54: =CZ54-CK54 -> 0 | DO54: =(DC54*DD54)+(DF54*DG54)+(DI54*DJ54)+(DL54*DM54) -> 0 | DP54: =DO54-CZ54 -> 0 | ED54: =(DR54*DS54)+(DU54*DV54)+(DX54*DY54)+(EA54*EB54) -> 0 | EE54: =ED54-DO54 -> 0
A55: =IFERROR(VLOOKUP(L55,'Base dados Exercicios'!$C$4:$J$305,3,FALSE),"") | B55: =IFERROR(VLOOKUP(L55,'Base dados Exercicios'!$C$4:$J$305,4,FALSE),"") | C55: =IFERROR(VLOOKUP(L55,'Base dados Exercicios'!$C$4:$J$305,5,FALSE),"") | D55: =IFERROR(VLOOKUP(L55,'Base dados Exercicios'!$C$4:$J$305,6,FALSE),"") | E55: =IFERROR(VLOOKUP(L55,'Base dados Exercicios'!$C$4:$J$305,7,FALSE),"") | F55: =IFERROR(VLOOKUP(L55,'Base dados Exercicios'!$C$4:$J$305,8,FALSE),"") | M55: =IF(L55<>"", HYPERLINK(VLOOKUP(L55,'Base dados Exercicios'!$C$4:$D$83,2,FALSE),"Check"),"") | AD55: =(R55*S55)+(U55*V55)+(X55*Y55)+(AA55*AB55) -> 0 | AR55: =(AF55*AG55)+(AI55*AJ55)+(AL55*AM55)+(AO55*AP55) -> 0 | AS55: =AR55-AD55 -> 0 | BG55: =(AU55*AV55)+(AX55*AY55)+(BA55*BB55)+(BD55*BE55) -> 0 | BH55: =BG55-AR55 -> 0 | BV55: =(BJ55*BK55)+(BM55*BN55)+(BP55*BQ55)+(BS55*BT55) -> 0 | BW55: =BV55-BG55 -> 0 | CK55: =(BY55*BZ55)+(CB55*CC55)+(CE55*CF55)+(CH55*CI55) -> 0 | CL55: =CK55-BV55 -> 0 | CZ55: =(CN55*CO55)+(CQ55*CR55)+(CT55*CU55)+(CW55*CX55) -> 0 | DA55: =CZ55-CK55 -> 0 | DO55: =(DC55*DD55)+(DF55*DG55)+(DI55*DJ55)+(DL55*DM55) -> 0 | DP55: =DO55-CZ55 -> 0 | ED55: =(DR55*DS55)+(DU55*DV55)+(DX55*DY55)+(EA55*EB55) -> 0 | EE55: =ED55-DO55 -> 0
A56: =IFERROR(VLOOKUP(L56,'Base dados Exercicios'!$C$4:$J$305,3,FALSE),"") | B56: =IFERROR(VLOOKUP(L56,'Base dados Exercicios'!$C$4:$J$305,4,FALSE),"") | C56: =IFERROR(VLOOKUP(L56,'Base dados Exercicios'!$C$4:$J$305,5,FALSE),"") | D56: =IFERROR(VLOOKUP(L56,'Base dados Exercicios'!$C$4:$J$305,6,FALSE),"") | E56: =IFERROR(VLOOKUP(L56,'Base dados Exercicios'!$C$4:$J$305,7,FALSE),"") | F56: =IFERROR(VLOOKUP(L56,'Base dados Exercicios'!$C$4:$J$305,8,FALSE),"") | M56: =IF(L56<>"", HYPERLINK(VLOOKUP(L56,'Base dados Exercicios'!$C$4:$D$83,2,FALSE),"Check"),"") | AD56: =(R56*S56)+(U56*V56)+(X56*Y56)+(AA56*AB56) -> 0 | AR56: =(AF56*AG56)+(AI56*AJ56)+(AL56*AM56)+(AO56*AP56) -> 0 | AS56: =AR56-AD56 -> 0 | BG56: =(AU56*AV56)+(AX56*AY56)+(BA56*BB56)+(BD56*BE56) -> 0 | BH56: =BG56-AR56 -> 0 | BV56: =(BJ56*BK56)+(BM56*BN56)+(BP56*BQ56)+(BS56*BT56) -> 0 | BW56: =BV56-BG56 -> 0 | CK56: =(BY56*BZ56)+(CB56*CC56)+(CE56*CF56)+(CH56*CI56) -> 0 | CL56: =CK56-BV56 -> 0 | CZ56: =(CN56*CO56)+(CQ56*CR56)+(CT56*CU56)+(CW56*CX56) -> 0 | DA56: =CZ56-CK56 -> 0 | DO56: =(DC56*DD56)+(DF56*DG56)+(DI56*DJ56)+(DL56*DM56) -> 0 | DP56: =DO56-CZ56 -> 0 | ED56: =(DR56*DS56)+(DU56*DV56)+(DX56*DY56)+(EA56*EB56) -> 0 | EE56: =ED56-DO56 -> 0
A57: =IFERROR(VLOOKUP(L57,'Base dados Exercicios'!$C$4:$J$305,3,FALSE),"") | B57: =IFERROR(VLOOKUP(L57,'Base dados Exercicios'!$C$4:$J$305,4,FALSE),"") | C57: =IFERROR(VLOOKUP(L57,'Base dados Exercicios'!$C$4:$J$305,5,FALSE),"") | D57: =IFERROR(VLOOKUP(L57,'Base dados Exercicios'!$C$4:$J$305,6,FALSE),"") | E57: =IFERROR(VLOOKUP(L57,'Base dados Exercicios'!$C$4:$J$305,7,FALSE),"") | F57: =IFERROR(VLOOKUP(L57,'Base dados Exercicios'!$C$4:$J$305,8,FALSE),"") | M57: =IF(L57<>"", HYPERLINK(VLOOKUP(L57,'Base dados Exercicios'!$C$4:$D$83,2,FALSE),"Check"),"") | AD57: =(R57*S57)+(U57*V57)+(X57*Y57)+(AA57*AB57) -> 0 | AR57: =(AF57*AG57)+(AI57*AJ57)+(AL57*AM57)+(AO57*AP57) -> 0 | AS57: =AR57-AD57 -> 0 | BG57: =(AU57*AV57)+(AX57*AY57)+(BA57*BB57)+(BD57*BE57) -> 0 | BH57: =BG57-AR57 -> 0 | BV57: =(BJ57*BK57)+(BM57*BN57)+(BP57*BQ57)+(BS57*BT57) -> 0 | BW57: =BV57-BG57 -> 0 | CK57: =(BY57*BZ57)+(CB57*CC57)+(CE57*CF57)+(CH57*CI57) -> 0 | CL57: =CK57-BV57 -> 0 | CZ57: =(CN57*CO57)+(CQ57*CR57)+(CT57*CU57)+(CW57*CX57) -> 0 | DA57: =CZ57-CK57 -> 0 | DO57: =(DC57*DD57)+(DF57*DG57)+(DI57*DJ57)+(DL57*DM57) -> 0 | DP57: =DO57-CZ57 -> 0 | ED57: =(DR57*DS57)+(DU57*DV57)+(DX57*DY57)+(EA57*EB57) -> 0 | EE57: =ED57-DO57 -> 0
A58: =IFERROR(VLOOKUP(L58,'Base dados Exercicios'!$C$4:$J$305,3,FALSE),"") | B58: =IFERROR(VLOOKUP(L58,'Base dados Exercicios'!$C$4:$J$305,4,FALSE),"") | C58: =IFERROR(VLOOKUP(L58,'Base dados Exercicios'!$C$4:$J$305,5,FALSE),"") | D58: =IFERROR(VLOOKUP(L58,'Base dados Exercicios'!$C$4:$J$305,6,FALSE),"") | E58: =IFERROR(VLOOKUP(L58,'Base dados Exercicios'!$C$4:$J$305,7,FALSE),"") | F58: =IFERROR(VLOOKUP(L58,'Base dados Exercicios'!$C$4:$J$305,8,FALSE),"") | M58: =IF(L58<>"", HYPERLINK(VLOOKUP(L58,'Base dados Exercicios'!$C$4:$D$83,2,FALSE),"Check"),"") | AD58: =(R58*S58)+(U58*V58)+(X58*Y58)+(AA58*AB58) -> 0 | AR58: =(AF58*AG58)+(AI58*AJ58)+(AL58*AM58)+(AO58*AP58) -> 0 | AS58: =AR58-AD58 -> 0 | BG58: =(AU58*AV58)+(AX58*AY58)+(BA58*BB58)+(BD58*BE58) -> 0 | BH58: =BG58-AR58 -> 0 | BV58: =(BJ58*BK58)+(BM58*BN58)+(BP58*BQ58)+(BS58*BT58) -> 0 | BW58: =BV58-BG58 -> 0 | CK58: =(BY58*BZ58)+(CB58*CC58)+(CE58*CF58)+(CH58*CI58) -> 0 | CL58: =CK58-BV58 -> 0 | CZ58: =(CN58*CO58)+(CQ58*CR58)+(CT58*CU58)+(CW58*CX58) -> 0 | DA58: =CZ58-CK58 -> 0 | DO58: =(DC58*DD58)+(DF58*DG58)+(DI58*DJ58)+(DL58*DM58) -> 0 | DP58: =DO58-CZ58 -> 0 | ED58: =(DR58*DS58)+(DU58*DV58)+(DX58*DY58)+(EA58*EB58) -> 0 | EE58: =ED58-DO58 -> 0
A59: =IFERROR(VLOOKUP(L59,'Base dados Exercicios'!$C$4:$J$305,3,FALSE),"") | B59: =IFERROR(VLOOKUP(L59,'Base dados Exercicios'!$C$4:$J$305,4,FALSE),"") | C59: =IFERROR(VLOOKUP(L59,'Base dados Exercicios'!$C$4:$J$305,5,FALSE),"") | D59: =IFERROR(VLOOKUP(L59,'Base dados Exercicios'!$C$4:$J$305,6,FALSE),"") | E59: =IFERROR(VLOOKUP(L59,'Base dados Exercicios'!$C$4:$J$305,7,FALSE),"") | F59: =IFERROR(VLOOKUP(L59,'Base dados Exercicios'!$C$4:$J$305,8,FALSE),"") | M59: =IF(L59<>"", HYPERLINK(VLOOKUP(L59,'Base dados Exercicios'!$C$4:$D$83,2,FALSE),"Check"),"") | AD59: =(R59*S59)+(U59*V59)+(X59*Y59)+(AA59*AB59) -> 0 | AR59: =(AF59*AG59)+(AI59*AJ59)+(AL59*AM59)+(AO59*AP59) -> 0 | AS59: =AR59-AD59 -> 0 | BG59: =(AU59*AV59)+(AX59*AY59)+(BA59*BB59)+(BD59*BE59) -> 0 | BH59: =BG59-AR59 -> 0 | BV59: =(BJ59*BK59)+(BM59*BN59)+(BP59*BQ59)+(BS59*BT59) -> 0 | BW59: =BV59-BG59 -> 0 | CK59: =(BY59*BZ59)+(CB59*CC59)+(CE59*CF59)+(CH59*CI59) -> 0 | CL59: =CK59-BV59 -> 0 | CZ59: =(CN59*CO59)+(CQ59*CR59)+(CT59*CU59)+(CW59*CX59) -> 0 | DA59: =CZ59-CK59 -> 0 | DO59: =(DC59*DD59)+(DF59*DG59)+(DI59*DJ59)+(DL59*DM59) -> 0 | DP59: =DO59-CZ59 -> 0 | ED59: =(DR59*DS59)+(DU59*DV59)+(DX59*DY59)+(EA59*EB59) -> 0 | EE59: =ED59-DO59 -> 0
A60: =IFERROR(VLOOKUP(L60,'Base dados Exercicios'!$C$4:$J$305,3,FALSE),"") | B60: =IFERROR(VLOOKUP(L60,'Base dados Exercicios'!$C$4:$J$305,4,FALSE),"") | C60: =IFERROR(VLOOKUP(L60,'Base dados Exercicios'!$C$4:$J$305,5,FALSE),"") | D60: =IFERROR(VLOOKUP(L60,'Base dados Exercicios'!$C$4:$J$305,6,FALSE),"") | E60: =IFERROR(VLOOKUP(L60,'Base dados Exercicios'!$C$4:$J$305,7,FALSE),"") | F60: =IFERROR(VLOOKUP(L60,'Base dados Exercicios'!$C$4:$J$305,8,FALSE),"") | M60: =IF(L60<>"", HYPERLINK(VLOOKUP(L60,'Base dados Exercicios'!$C$4:$D$83,2,FALSE),"Check"),"") | AD60: =(R60*S60)+(U60*V60)+(X60*Y60)+(AA60*AB60) -> 0 | AR60: =(AF60*AG60)+(AI60*AJ60)+(AL60*AM60)+(AO60*AP60) -> 0 | AS60: =AR60-AD60 -> 0 | BG60: =(AU60*AV60)+(AX60*AY60)+(BA60*BB60)+(BD60*BE60) -> 0 | BH60: =BG60-AR60 -> 0 | BV60: =(BJ60*BK60)+(BM60*BN60)+(BP60*BQ60)+(BS60*BT60) -> 0 | BW60: =BV60-BG60 -> 0 | CK60: =(BY60*BZ60)+(CB60*CC60)+(CE60*CF60)+(CH60*CI60) -> 0 | CL60: =CK60-BV60 -> 0 | CZ60: =(CN60*CO60)+(CQ60*CR60)+(CT60*CU60)+(CW60*CX60) -> 0 | DA60: =CZ60-CK60 -> 0 | DO60: =(DC60*DD60)+(DF60*DG60)+(DI60*DJ60)+(DL60*DM60) -> 0 | DP60: =DO60-CZ60 -> 0 | ED60: =(DR60*DS60)+(DU60*DV60)+(DX60*DY60)+(EA60*EB60) -> 0 | EE60: =ED60-DO60 -> 0
A61: =IFERROR(VLOOKUP(L61,'Base dados Exercicios'!$C$4:$J$305,3,FALSE),"") | B61: =IFERROR(VLOOKUP(L61,'Base dados Exercicios'!$C$4:$J$305,4,FALSE),"") | C61: =IFERROR(VLOOKUP(L61,'Base dados Exercicios'!$C$4:$J$305,5,FALSE),"") | D61: =IFERROR(VLOOKUP(L61,'Base dados Exercicios'!$C$4:$J$305,6,FALSE),"") | E61: =IFERROR(VLOOKUP(L61,'Base dados Exercicios'!$C$4:$J$305,7,FALSE),"") | F61: =IFERROR(VLOOKUP(L61,'Base dados Exercicios'!$C$4:$J$305,8,FALSE),"") | M61: =IF(L61<>"", HYPERLINK(VLOOKUP(L61,'Base dados Exercicios'!$C$4:$D$83,2,FALSE),"Check"),"") | AD61: =(R61*S61)+(U61*V61)+(X61*Y61)+(AA61*AB61) -> 0 | AR61: =(AF61*AG61)+(AI61*AJ61)+(AL61*AM61)+(AO61*AP61) -> 0 | AS61: =AR61-AD61 -> 0 | BG61: =(AU61*AV61)+(AX61*AY61)+(BA61*BB61)+(BD61*BE61) -> 0 | BH61: =BG61-AR61 -> 0 | BV61: =(BJ61*BK61)+(BM61*BN61)+(BP61*BQ61)+(BS61*BT61) -> 0 | BW61: =BV61-BG61 -> 0 | CK61: =(BY61*BZ61)+(CB61*CC61)+(CE61*CF61)+(CH61*CI61) -> 0 | CL61: =CK61-BV61 -> 0 | CZ61: =(CN61*CO61)+(CQ61*CR61)+(CT61*CU61)+(CW61*CX61) -> 0 | DA61: =CZ61-CK61 -> 0 | DO61: =(DC61*DD61)+(DF61*DG61)+(DI61*DJ61)+(DL61*DM61) -> 0 | DP61: =DO61-CZ61 -> 0 | ED61: =(DR61*DS61)+(DU61*DV61)+(DX61*DY61)+(EA61*EB61) -> 0 | EE61: =ED61-DO61 -> 0
A62: =IFERROR(VLOOKUP(L62,'Base dados Exercicios'!$C$4:$J$305,3,FALSE),"") | B62: =IFERROR(VLOOKUP(L62,'Base dados Exercicios'!$C$4:$J$305,4,FALSE),"") | C62: =IFERROR(VLOOKUP(L62,'Base dados Exercicios'!$C$4:$J$305,5,FALSE),"") | D62: =IFERROR(VLOOKUP(L62,'Base dados Exercicios'!$C$4:$J$305,6,FALSE),"") | E62: =IFERROR(VLOOKUP(L62,'Base dados Exercicios'!$C$4:$J$305,7,FALSE),"") | F62: =IFERROR(VLOOKUP(L62,'Base dados Exercicios'!$C$4:$J$305,8,FALSE),"") | M62: =IF(L62<>"", HYPERLINK(VLOOKUP(L62,'Base dados Exercicios'!$C$4:$D$83,2,FALSE),"Check"),"") | AD62: =(R62*S62)+(U62*V62)+(X62*Y62)+(AA62*AB62) -> 0 | AR62: =(AF62*AG62)+(AI62*AJ62)+(AL62*AM62)+(AO62*AP62) -> 0 | AS62: =AR62-AD62 -> 0 | BG62: =(AU62*AV62)+(AX62*AY62)+(BA62*BB62)+(BD62*BE62) -> 0 | BH62: =BG62-AR62 -> 0 | BV62: =(BJ62*BK62)+(BM62*BN62)+(BP62*BQ62)+(BS62*BT62) -> 0 | BW62: =BV62-BG62 -> 0 | CK62: =(BY62*BZ62)+(CB62*CC62)+(CE62*CF62)+(CH62*CI62) -> 0 | CL62: =CK62-BV62 -> 0 | CZ62: =(CN62*CO62)+(CQ62*CR62)+(CT62*CU62)+(CW62*CX62) -> 0 | DA62: =CZ62-CK62 -> 0 | DO62: =(DC62*DD62)+(DF62*DG62)+(DI62*DJ62)+(DL62*DM62) -> 0 | DP62: =DO62-CZ62 -> 0 | ED62: =(DR62*DS62)+(DU62*DV62)+(DX62*DY62)+(EA62*EB62) -> 0 | EE62: =ED62-DO62 -> 0
A63: =IFERROR(VLOOKUP(L63,'Base dados Exercicios'!$C$4:$J$305,3,FALSE),"") | B63: =IFERROR(VLOOKUP(L63,'Base dados Exercicios'!$C$4:$J$305,4,FALSE),"") | C63: =IFERROR(VLOOKUP(L63,'Base dados Exercicios'!$C$4:$J$305,5,FALSE),"") | D63: =IFERROR(VLOOKUP(L63,'Base dados Exercicios'!$C$4:$J$305,6,FALSE),"") | E63: =IFERROR(VLOOKUP(L63,'Base dados Exercicios'!$C$4:$J$305,7,FALSE),"") | F63: =IFERROR(VLOOKUP(L63,'Base dados Exercicios'!$C$4:$J$305,8,FALSE),"") | M63: =IF(L63<>"", HYPERLINK(VLOOKUP(L63,'Base dados Exercicios'!$C$4:$D$83,2,FALSE),"Check"),"") | Q63: NOTAS: | AE63: NOTAS: | AT63: NOTAS: | BI63: NOTAS: | BX63: NOTAS: | CM63: NOTAS: | DB63: NOTAS: | DQ63: NOTAS:
A64: =IFERROR(VLOOKUP(L64,'Base dados Exercicios'!$C$4:$J$305,3,FALSE),"") | B64: =IFERROR(VLOOKUP(L64,'Base dados Exercicios'!$C$4:$J$305,4,FALSE),"") | C64: =IFERROR(VLOOKUP(L64,'Base dados Exercicios'!$C$4:$J$305,5,FALSE),"") | D64: =IFERROR(VLOOKUP(L64,'Base dados Exercicios'!$C$4:$J$305,6,FALSE),"") | E64: =IFERROR(VLOOKUP(L64,'Base dados Exercicios'!$C$4:$J$305,7,FALSE),"") | F64: =IFERROR(VLOOKUP(L64,'Base dados Exercicios'!$C$4:$J$305,8,FALSE),"") | K64: =I29 -> 0 | M64: =IF(L64<>"", HYPERLINK(VLOOKUP(L64,'Base dados Exercicios'!$C$4:$D$83,2,FALSE),"Check"),"") | AD64: =(R64*S64)+(U64*V64)+(X64*Y64)+(AA64*AB64) -> 0 | AR64: =(AF64*AG64)+(AI64*AJ64)+(AL64*AM64)+(AO64*AP64) -> 0 | AS64: =AR64-AD64 -> 0 | BG64: =(AU64*AV64)+(AX64*AY64)+(BA64*BB64)+(BD64*BE64) -> 0 | BH64: =BG64-AR64 -> 0 | BV64: =(BJ64*BK64)+(BM64*BN64)+(BP64*BQ64)+(BS64*BT64) -> 0 | BW64: =BV64-BG64 -> 0 | CK64: =(BY64*BZ64)+(CB64*CC64)+(CE64*CF64)+(CH64*CI64) -> 0 | CL64: =CK64-BV64 -> 0 | CZ64: =(CN64*CO64)+(CQ64*CR64)+(CT64*CU64)+(CW64*CX64) -> 0 | DA64: =CZ64-CK64 -> 0 | DO64: =(DC64*DD64)+(DF64*DG64)+(DI64*DJ64)+(DL64*DM64) -> 0 | DP64: =DO64-CZ64 -> 0 | ED64: =(DR64*DS64)+(DU64*DV64)+(DX64*DY64)+(EA64*EB64) -> 0 | EE64: =ED64-DO64 -> 0
A65: =IFERROR(VLOOKUP(L65,'Base dados Exercicios'!$C$4:$J$305,3,FALSE),"") | B65: =IFERROR(VLOOKUP(L65,'Base dados Exercicios'!$C$4:$J$305,4,FALSE),"") | C65: =IFERROR(VLOOKUP(L65,'Base dados Exercicios'!$C$4:$J$305,5,FALSE),"") | D65: =IFERROR(VLOOKUP(L65,'Base dados Exercicios'!$C$4:$J$305,6,FALSE),"") | E65: =IFERROR(VLOOKUP(L65,'Base dados Exercicios'!$C$4:$J$305,7,FALSE),"") | F65: =IFERROR(VLOOKUP(L65,'Base dados Exercicios'!$C$4:$J$305,8,FALSE),"") | M65: =IF(L65<>"", HYPERLINK(VLOOKUP(L65,'Base dados Exercicios'!$C$4:$D$83,2,FALSE),"Check"),"") | AD65: =(R65*S65)+(U65*V65)+(X65*Y65)+(AA65*AB65) -> 0 | AR65: =(AF65*AG65)+(AI65*AJ65)+(AL65*AM65)+(AO65*AP65) -> 0 | AS65: =AR65-AD65 -> 0 | BG65: =(AU65*AV65)+(AX65*AY65)+(BA65*BB65)+(BD65*BE65) -> 0 | BH65: =BG65-AR65 -> 0 | BV65: =(BJ65*BK65)+(BM65*BN65)+(BP65*BQ65)+(BS65*BT65) -> 0 | BW65: =BV65-BG65 -> 0 | CK65: =(BY65*BZ65)+(CB65*CC65)+(CE65*CF65)+(CH65*CI65) -> 0 | CL65: =CK65-BV65 -> 0 | CZ65: =(CN65*CO65)+(CQ65*CR65)+(CT65*CU65)+(CW65*CX65) -> 0 | DA65: =CZ65-CK65 -> 0 | DO65: =(DC65*DD65)+(DF65*DG65)+(DI65*DJ65)+(DL65*DM65) -> 0 | DP65: =DO65-CZ65 -> 0 | ED65: =(DR65*DS65)+(DU65*DV65)+(DX65*DY65)+(EA65*EB65) -> 0 | EE65: =ED65-DO65 -> 0
A66: =IFERROR(VLOOKUP(L66,'Base dados Exercicios'!$C$4:$J$305,3,FALSE),"") | B66: =IFERROR(VLOOKUP(L66,'Base dados Exercicios'!$C$4:$J$305,4,FALSE),"") | C66: =IFERROR(VLOOKUP(L66,'Base dados Exercicios'!$C$4:$J$305,5,FALSE),"") | D66: =IFERROR(VLOOKUP(L66,'Base dados Exercicios'!$C$4:$J$305,6,FALSE),"") | E66: =IFERROR(VLOOKUP(L66,'Base dados Exercicios'!$C$4:$J$305,7,FALSE),"") | F66: =IFERROR(VLOOKUP(L66,'Base dados Exercicios'!$C$4:$J$305,8,FALSE),"") | M66: =IF(L66<>"", HYPERLINK(VLOOKUP(L66,'Base dados Exercicios'!$C$4:$D$83,2,FALSE),"Check"),"") | AD66: =(R66*S66)+(U66*V66)+(X66*Y66)+(AA66*AB66) -> 0 | AR66: =(AF66*AG66)+(AI66*AJ66)+(AL66*AM66)+(AO66*AP66) -> 0 | AS66: =AR66-AD66 -> 0 | BG66: =(AU66*AV66)+(AX66*AY66)+(BA66*BB66)+(BD66*BE66) -> 0 | BH66: =BG66-AR66 -> 0 | BV66: =(BJ66*BK66)+(BM66*BN66)+(BP66*BQ66)+(BS66*BT66) -> 0 | BW66: =BV66-BG66 -> 0 | CK66: =(BY66*BZ66)+(CB66*CC66)+(CE66*CF66)+(CH66*CI66) -> 0 | CL66: =CK66-BV66 -> 0 | CZ66: =(CN66*CO66)+(CQ66*CR66)+(CT66*CU66)+(CW66*CX66) -> 0 | DA66: =CZ66-CK66 -> 0 | DO66: =(DC66*DD66)+(DF66*DG66)+(DI66*DJ66)+(DL66*DM66) -> 0 | DP66: =DO66-CZ66 -> 0 | ED66: =(DR66*DS66)+(DU66*DV66)+(DX66*DY66)+(EA66*EB66) -> 0 | EE66: =ED66-DO66 -> 0
A67: =IFERROR(VLOOKUP(L67,'Base dados Exercicios'!$C$4:$J$305,3,FALSE),"") | B67: =IFERROR(VLOOKUP(L67,'Base dados Exercicios'!$C$4:$J$305,4,FALSE),"") | C67: =IFERROR(VLOOKUP(L67,'Base dados Exercicios'!$C$4:$J$305,5,FALSE),"") | D67: =IFERROR(VLOOKUP(L67,'Base dados Exercicios'!$C$4:$J$305,6,FALSE),"") | E67: =IFERROR(VLOOKUP(L67,'Base dados Exercicios'!$C$4:$J$305,7,FALSE),"") | F67: =IFERROR(VLOOKUP(L67,'Base dados Exercicios'!$C$4:$J$305,8,FALSE),"") | M67: =IF(L67<>"", HYPERLINK(VLOOKUP(L67,'Base dados Exercicios'!$C$4:$D$83,2,FALSE),"Check"),"") | AD67: =(R67*S67)+(U67*V67)+(X67*Y67)+(AA67*AB67) -> 0 | AR67: =(AF67*AG67)+(AI67*AJ67)+(AL67*AM67)+(AO67*AP67) -> 0 | AS67: =AR67-AD67 -> 0 | BG67: =(AU67*AV67)+(AX67*AY67)+(BA67*BB67)+(BD67*BE67) -> 0 | BH67: =BG67-AR67 -> 0 | BV67: =(BJ67*BK67)+(BM67*BN67)+(BP67*BQ67)+(BS67*BT67) -> 0 | BW67: =BV67-BG67 -> 0 | CK67: =(BY67*BZ67)+(CB67*CC67)+(CE67*CF67)+(CH67*CI67) -> 0 | CL67: =CK67-BV67 -> 0 | CZ67: =(CN67*CO67)+(CQ67*CR67)+(CT67*CU67)+(CW67*CX67) -> 0 | DA67: =CZ67-CK67 -> 0 | DO67: =(DC67*DD67)+(DF67*DG67)+(DI67*DJ67)+(DL67*DM67) -> 0 | DP67: =DO67-CZ67 -> 0 | ED67: =(DR67*DS67)+(DU67*DV67)+(DX67*DY67)+(EA67*EB67) -> 0 | EE67: =ED67-DO67 -> 0
A68: =IFERROR(VLOOKUP(L68,'Base dados Exercicios'!$C$4:$J$305,3,FALSE),"") | B68: =IFERROR(VLOOKUP(L68,'Base dados Exercicios'!$C$4:$J$305,4,FALSE),"") | C68: =IFERROR(VLOOKUP(L68,'Base dados Exercicios'!$C$4:$J$305,5,FALSE),"") | D68: =IFERROR(VLOOKUP(L68,'Base dados Exercicios'!$C$4:$J$305,6,FALSE),"") | E68: =IFERROR(VLOOKUP(L68,'Base dados Exercicios'!$C$4:$J$305,7,FALSE),"") | F68: =IFERROR(VLOOKUP(L68,'Base dados Exercicios'!$C$4:$J$305,8,FALSE),"") | M68: =IF(L68<>"", HYPERLINK(VLOOKUP(L68,'Base dados Exercicios'!$C$4:$D$83,2,FALSE),"Check"),"") | AD68: =(R68*S68)+(U68*V68)+(X68*Y68)+(AA68*AB68) -> 0 | AR68: =(AF68*AG68)+(AI68*AJ68)+(AL68*AM68)+(AO68*AP68) -> 0 | AS68: =AR68-AD68 -> 0 | BG68: =(AU68*AV68)+(AX68*AY68)+(BA68*BB68)+(BD68*BE68) -> 0 | BH68: =BG68-AR68 -> 0 | BV68: =(BJ68*BK68)+(BM68*BN68)+(BP68*BQ68)+(BS68*BT68) -> 0 | BW68: =BV68-BG68 -> 0 | CK68: =(BY68*BZ68)+(CB68*CC68)+(CE68*CF68)+(CH68*CI68) -> 0 | CL68: =CK68-BV68 -> 0 | CZ68: =(CN68*CO68)+(CQ68*CR68)+(CT68*CU68)+(CW68*CX68) -> 0 | DA68: =CZ68-CK68 -> 0 | DO68: =(DC68*DD68)+(DF68*DG68)+(DI68*DJ68)+(DL68*DM68) -> 0 | DP68: =DO68-CZ68 -> 0 | ED68: =(DR68*DS68)+(DU68*DV68)+(DX68*DY68)+(EA68*EB68) -> 0 | EE68: =ED68-DO68 -> 0
A69: =IFERROR(VLOOKUP(L69,'Base dados Exercicios'!$C$4:$J$305,3,FALSE),"") | B69: =IFERROR(VLOOKUP(L69,'Base dados Exercicios'!$C$4:$J$305,4,FALSE),"") | C69: =IFERROR(VLOOKUP(L69,'Base dados Exercicios'!$C$4:$J$305,5,FALSE),"") | D69: =IFERROR(VLOOKUP(L69,'Base dados Exercicios'!$C$4:$J$305,6,FALSE),"") | E69: =IFERROR(VLOOKUP(L69,'Base dados Exercicios'!$C$4:$J$305,7,FALSE),"") | F69: =IFERROR(VLOOKUP(L69,'Base dados Exercicios'!$C$4:$J$305,8,FALSE),"") | M69: =IF(L69<>"", HYPERLINK(VLOOKUP(L69,'Base dados Exercicios'!$C$4:$D$83,2,FALSE),"Check"),"") | AD69: =(R69*S69)+(U69*V69)+(X69*Y69)+(AA69*AB69) -> 0 | AR69: =(AF69*AG69)+(AI69*AJ69)+(AL69*AM69)+(AO69*AP69) -> 0 | AS69: =AR69-AD69 -> 0 | BG69: =(AU69*AV69)+(AX69*AY69)+(BA69*BB69)+(BD69*BE69) -> 0 | BH69: =BG69-AR69 -> 0 | BV69: =(BJ69*BK69)+(BM69*BN69)+(BP69*BQ69)+(BS69*BT69) -> 0 | BW69: =BV69-BG69 -> 0 | CK69: =(BY69*BZ69)+(CB69*CC69)+(CE69*CF69)+(CH69*CI69) -> 0 | CL69: =CK69-BV69 -> 0 | CZ69: =(CN69*CO69)+(CQ69*CR69)+(CT69*CU69)+(CW69*CX69) -> 0 | DA69: =CZ69-CK69 -> 0 | DO69: =(DC69*DD69)+(DF69*DG69)+(DI69*DJ69)+(DL69*DM69) -> 0 | DP69: =DO69-CZ69 -> 0 | ED69: =(DR69*DS69)+(DU69*DV69)+(DX69*DY69)+(EA69*EB69) -> 0 | EE69: =ED69-DO69 -> 0
A70: =IFERROR(VLOOKUP(L70,'Base dados Exercicios'!$C$4:$J$305,3,FALSE),"") | B70: =IFERROR(VLOOKUP(L70,'Base dados Exercicios'!$C$4:$J$305,4,FALSE),"") | C70: =IFERROR(VLOOKUP(L70,'Base dados Exercicios'!$C$4:$J$305,5,FALSE),"") | D70: =IFERROR(VLOOKUP(L70,'Base dados Exercicios'!$C$4:$J$305,6,FALSE),"") | E70: =IFERROR(VLOOKUP(L70,'Base dados Exercicios'!$C$4:$J$305,7,FALSE),"") | F70: =IFERROR(VLOOKUP(L70,'Base dados Exercicios'!$C$4:$J$305,8,FALSE),"") | M70: =IF(L70<>"", HYPERLINK(VLOOKUP(L70,'Base dados Exercicios'!$C$4:$D$83,2,FALSE),"Check"),"") | AD70: =(R70*S70)+(U70*V70)+(X70*Y70)+(AA70*AB70) -> 0 | AR70: =(AF70*AG70)+(AI70*AJ70)+(AL70*AM70)+(AO70*AP70) -> 0 | AS70: =AR70-AD70 -> 0 | BG70: =(AU70*AV70)+(AX70*AY70)+(BA70*BB70)+(BD70*BE70) -> 0 | BH70: =BG70-AR70 -> 0 | BV70: =(BJ70*BK70)+(BM70*BN70)+(BP70*BQ70)+(BS70*BT70) -> 0 | BW70: =BV70-BG70 -> 0 | CK70: =(BY70*BZ70)+(CB70*CC70)+(CE70*CF70)+(CH70*CI70) -> 0 | CL70: =CK70-BV70 -> 0 | CZ70: =(CN70*CO70)+(CQ70*CR70)+(CT70*CU70)+(CW70*CX70) -> 0 | DA70: =CZ70-CK70 -> 0 | DO70: =(DC70*DD70)+(DF70*DG70)+(DI70*DJ70)+(DL70*DM70) -> 0 | DP70: =DO70-CZ70 -> 0 | ED70: =(DR70*DS70)+(DU70*DV70)+(DX70*DY70)+(EA70*EB70) -> 0 | EE70: =ED70-DO70 -> 0
A71: =IFERROR(VLOOKUP(L71,'Base dados Exercicios'!$C$4:$J$305,3,FALSE),"") | B71: =IFERROR(VLOOKUP(L71,'Base dados Exercicios'!$C$4:$J$305,4,FALSE),"") | C71: =IFERROR(VLOOKUP(L71,'Base dados Exercicios'!$C$4:$J$305,5,FALSE),"") | D71: =IFERROR(VLOOKUP(L71,'Base dados Exercicios'!$C$4:$J$305,6,FALSE),"") | E71: =IFERROR(VLOOKUP(L71,'Base dados Exercicios'!$C$4:$J$305,7,FALSE),"") | F71: =IFERROR(VLOOKUP(L71,'Base dados Exercicios'!$C$4:$J$305,8,FALSE),"") | M71: =IF(L71<>"", HYPERLINK(VLOOKUP(L71,'Base dados Exercicios'!$C$4:$D$83,2,FALSE),"Check"),"") | AD71: =(R71*S71)+(U71*V71)+(X71*Y71)+(AA71*AB71) -> 0 | AR71: =(AF71*AG71)+(AI71*AJ71)+(AL71*AM71)+(AO71*AP71) -> 0 | AS71: =AR71-AD71 -> 0 | BG71: =(AU71*AV71)+(AX71*AY71)+(BA71*BB71)+(BD71*BE71) -> 0 | BH71: =BG71-AR71 -> 0 | BV71: =(BJ71*BK71)+(BM71*BN71)+(BP71*BQ71)+(BS71*BT71) -> 0 | BW71: =BV71-BG71 -> 0 | CK71: =(BY71*BZ71)+(CB71*CC71)+(CE71*CF71)+(CH71*CI71) -> 0 | CL71: =CK71-BV71 -> 0 | CZ71: =(CN71*CO71)+(CQ71*CR71)+(CT71*CU71)+(CW71*CX71) -> 0 | DA71: =CZ71-CK71 -> 0 | DO71: =(DC71*DD71)+(DF71*DG71)+(DI71*DJ71)+(DL71*DM71) -> 0 | DP71: =DO71-CZ71 -> 0 | ED71: =(DR71*DS71)+(DU71*DV71)+(DX71*DY71)+(EA71*EB71) -> 0 | EE71: =ED71-DO71 -> 0
A72: =IFERROR(VLOOKUP(L72,'Base dados Exercicios'!$C$4:$J$305,3,FALSE),"") | B72: =IFERROR(VLOOKUP(L72,'Base dados Exercicios'!$C$4:$J$305,4,FALSE),"") | C72: =IFERROR(VLOOKUP(L72,'Base dados Exercicios'!$C$4:$J$305,5,FALSE),"") | D72: =IFERROR(VLOOKUP(L72,'Base dados Exercicios'!$C$4:$J$305,6,FALSE),"") | E72: =IFERROR(VLOOKUP(L72,'Base dados Exercicios'!$C$4:$J$305,7,FALSE),"") | F72: =IFERROR(VLOOKUP(L72,'Base dados Exercicios'!$C$4:$J$305,8,FALSE),"") | M72: =IF(L72<>"", HYPERLINK(VLOOKUP(L72,'Base dados Exercicios'!$C$4:$D$83,2,FALSE),"Check"),"") | AD72: =(R72*S72)+(U72*V72)+(X72*Y72)+(AA72*AB72) -> 0 | AR72: =(AF72*AG72)+(AI72*AJ72)+(AL72*AM72)+(AO72*AP72) -> 0 | AS72: =AR72-AD72 -> 0 | BG72: =(AU72*AV72)+(AX72*AY72)+(BA72*BB72)+(BD72*BE72) -> 0 | BH72: =BG72-AR72 -> 0 | BV72: =(BJ72*BK72)+(BM72*BN72)+(BP72*BQ72)+(BS72*BT72) -> 0 | BW72: =BV72-BG72 -> 0 | CK72: =(BY72*BZ72)+(CB72*CC72)+(CE72*CF72)+(CH72*CI72) -> 0 | CL72: =CK72-BV72 -> 0 | CZ72: =(CN72*CO72)+(CQ72*CR72)+(CT72*CU72)+(CW72*CX72) -> 0 | DA72: =CZ72-CK72 -> 0 | DO72: =(DC72*DD72)+(DF72*DG72)+(DI72*DJ72)+(DL72*DM72) -> 0 | DP72: =DO72-CZ72 -> 0 | ED72: =(DR72*DS72)+(DU72*DV72)+(DX72*DY72)+(EA72*EB72) -> 0 | EE72: =ED72-DO72 -> 0
A73: =IFERROR(VLOOKUP(L73,'Base dados Exercicios'!$C$4:$J$305,3,FALSE),"") | B73: =IFERROR(VLOOKUP(L73,'Base dados Exercicios'!$C$4:$J$305,4,FALSE),"") | C73: =IFERROR(VLOOKUP(L73,'Base dados Exercicios'!$C$4:$J$305,5,FALSE),"") | D73: =IFERROR(VLOOKUP(L73,'Base dados Exercicios'!$C$4:$J$305,6,FALSE),"") | E73: =IFERROR(VLOOKUP(L73,'Base dados Exercicios'!$C$4:$J$305,7,FALSE),"") | F73: =IFERROR(VLOOKUP(L73,'Base dados Exercicios'!$C$4:$J$305,8,FALSE),"") | M73: =IF(L73<>"", HYPERLINK(VLOOKUP(L73,'Base dados Exercicios'!$C$4:$D$83,2,FALSE),"Check"),"") | Q73: NOTAS:

Sheet Feedback semanal
A1: FEEDBACK SEMANAL | B1: 1
A2: Ajuda-me a ajudar-te! Responde ás seguintes questões para que eu possa da melhor forma ajustar todas as variáveis para a próxima semana.
A3: · O que achaste da semana em geral (progressão/regressão)?
A6: · O que correu bem (dieta/treino/descanso)?
A9: · Que dificuldade sentiste (dieta/treino/descanso)?
A12: · Qual a tua perspectiva para a próxima semana?
A15: · Qual a tua motivação para a próxima semana (1-10)?
A16: FEEDBACK SEMANAL | B16: =1+B1 -> 2
A17: Ajuda-me a ajudar-te! Responde ás seguintes questões para que eu possa da melhor forma ajustar todas as variáveis para a próxima semana.
A18: · O que achaste da semana em geral (progressão/regressão)?
A21: · O que correu bem (dieta/treino/descanso)?
A24: · Que dificuldade sentiste (dieta/treino/descanso)?
A27: · Qual a tua perspectiva para a próxima semana?
A30: · Qual a tua motivação para a próxima semana (1-10)?
A31: FEEDBACK SEMANAL | B31: =1+B16 -> 3
A32: Ajuda-me a ajudar-te! Responde ás seguintes questões para que eu possa da melhor forma ajustar todas as variáveis para a próxima semana.
A33: · O que achaste da semana em geral (progressão/regressão)?
A36: · O que correu bem (dieta/treino/descanso)?
A39: · Que dificuldade sentiste (dieta/treino/descanso)?
A42: · Qual a tua perspectiva para a próxima semana?
A45: · Qual a tua motivação para a próxima semana (1-10)?
A46: FEEDBACK SEMANAL | B46: =1+B31 -> 4
A47: Ajuda-me a ajudar-te! Responde ás seguintes questões para que eu possa da melhor forma ajustar todas as variáveis para a próxima semana.
A48: · O que achaste da semana em geral (progressão/regressão)?
A51: · O que correu bem (dieta/treino/descanso)?
A54: · Que dificuldade sentiste (dieta/treino/descanso)?
A57: · Qual a tua perspectiva para a próxima semana?
A60: · Qual a tua motivação para a próxima semana (1-10)?
A61: FEEDBACK SEMANAL | B61: =1+B46 -> 5
A62: Ajuda-me a ajudar-te! Responde ás seguintes questões para que eu possa da melhor forma ajustar todas as variáveis para a próxima semana.
A63: · O que achaste da semana em geral (progressão/regressão)?
A66: · O que correu bem (dieta/treino/descanso)?
A69: · Que dificuldade sentiste (dieta/treino/descanso)?
A72: · Qual a tua perspectiva para a próxima semana?
A75: · Qual a tua motivação para a próxima semana (1-10)?
A76: FEEDBACK SEMANAL | B76: =1+B61 -> 6
A77: Ajuda-me a ajudar-te! Responde ás seguintes questões para que eu possa da melhor forma ajustar todas as variáveis para a próxima semana.
A78: · O que achaste da semana em geral (progressão/regressão)?
A81: · O que correu bem (dieta/treino/descanso)?
A84: · Que dificuldade sentiste (dieta/treino/descanso)?
A87: · Qual a tua perspectiva para a próxima semana?
A90: · Qual a tua motivação para a próxima semana (1-10)?
A91: FEEDBACK SEMANAL | B91: =1+B76 -> 7
A92: Ajuda-me a ajudar-te! Responde ás seguintes questões para que eu possa da melhor forma ajustar todas as variáveis para a próxima semana.
A93: · O que achaste da semana em geral (progressão/regressão)?
A96: · O que correu bem (dieta/treino/descanso)?
A99: · Que dificuldade sentiste (dieta/treino/descanso)?
A102: · Qual a tua perspectiva para a próxima semana?
A105: · Qual a tua motivação para a próxima semana (1-10)?
A106: FEEDBACK SEMANAL | B106: =1+B91 -> 8
A107: Ajuda-me a ajudar-te! Responde ás seguintes questões para que eu possa da melhor forma ajustar todas as variáveis para a próxima semana.
A108: · O que achaste da semana em geral (progressão/regressão)?
A111: · O que correu bem (dieta/treino/descanso)?
A114: · Que dificuldade sentiste (dieta/treino/descanso)?
A117: · Qual a tua perspectiva para a próxima semana?
A120: · Qual a tua motivação para a próxima semana (1-10)?

Sheet Suplementos
A2: Base
A3: Produto | B3: link | C3: Dose | D3: Motivo
A4: Omega 3 concentrado | B4: https://www.prozis.com/pt/pt/prozis/omega-3-epa-plus-90-softgels | C4: 1 almoço ou jantar | D4: Antiinflamatório e saúde
A5: Multivitaminico | B5: https://www.prozis.com/pt/pt/prozis/multi-prz-200-caps | C5: 1 almoço ou jantar | D5: Se não comes vegetais nem fruta
A6: Creatina | B6: https://www.prozis.com/pt/pt/prozis/creatina-mono-hidratada-300-g | C6: 5g por dia em qualquer altura | D6: Mais força, músculo e recuperação fisica
A7: Cafeína | B7: https://www.prozis.com/pt/pt/prozis/cafeina-200-mg-90-capsulas | C7: Depende, fala comigo | D7: Mais energia, foco e concentração
A8: Beta-Alanina | B8: https://www.prozis.com/pt/pt/prozis/beta-alanina-300-g?label=TlVUMDAvMTM5MDk2MDE2Mg%3D%3D | C8: 3g dia | D8: Retardador de fadiga
A9: Melatonina | B9: https://www.prozis.com/pt/pt/prozis/melatonina-180-capsulas | C9: 1 ao deitar | D9: Ajuda na qualidade do sono
A10: Aswaganda | B10: https://www.prozis.com/pt/pt/prozis/extrato-de-ashwagandha-450-mg-90-capsulas-vegetarianas | C10: 1 dia ao acordar ou deitar | D10: Controle de ansiedade e stress
A11: H2O Infusion | B11: https://www.prozis.com/pt/pt/prozis/36-x-h2o-infusion-9-g | C11: -
A12: Cookin'Spray - Óleo Antiaderente | B12: https://www.prozis.com/pt/pt/prozis/cookinspray-oleo-antiaderente-em-spray-200-ml | C12: -
A14: Snacks Proteicos
A15: Nome | B15: link | C15: kcal | D15: proteina
A16: XTRACORE 80 g | B16: https://www.prozis.com/pt/pt/prozis/8-x-xtracore-80-g?label=TlVUMDAvMTUxODkwMDczNg%3D%3D | C16: 325 | D16: 23.2
A17: Protein Gourmet Bar 80 g | B17: https://www.prozis.com/pt/pt/prozis/12-x-protein-gourmet-bar-80-g | C17: 344 | D17: 22.4
A18: ZERO Cookie 60 g | B18: https://www.prozis.com/pt/pt/prozis/12-x-zero-cookie-60-g | C18: 180 | D18: 22.2
A19: Protein Brownie - Original 80 g | B19: https://www.prozis.com/pt/pt/prozis/8-x-protein-brownie-original-80-g?label=TlVUMDAvMTc1MDYwMDYzMw%3D%3D | C19: 340 | D19: 21
A20: POW! - Protein Cookie 60 g | B20: https://www.prozis.com/pt/pt/prozis/12-x-pow-protein-cookie-60-g | C20: 224 | D20: 20
A21: Melty 60 g | B21: https://www.prozis.com/pt/pt/prozis/10-x-melty-60-g-barra-proteica-com-baixo-teor-de-acucares?label=TlVUMDAvMTQ5NjMzMDAxMA%3D%3D | C21: 210 | D21: 18
A22: Barlicious Barra Proteica 70 g | B22: https://www.prozis.com/pt/pt/prozis/8-x-barlicious-barra-proteica-70-g | C22: 325 | D22: 15.4
A23: Billion - Barra Proteica 65 g | B23: https://www.prozis.com/pt/pt/prozis/9-x-billion-barra-proteica-de-amendoim-65-g | C23: 315 | D23: 15
A24: Billion - Barra Proteica 65 g branco | B24: https://www.prozis.com/pt/pt/prozis/9-x-billion-barra-proteica-de-amendoim-e-chocolate-branco-65-g | C24: 290 | D24: 13.65
A25: Zero Snack 35 g | B25: https://www.prozis.com/pt/pt/prozis/12-x-zero-snack-35-g?label=TlVUMDAvMTQwMzMxMDAxMA%3D%3D | C25: 123 | D25: 13
A26: Diet Bar 35 g | B26: https://www.prozis.com/pt/pt/prozis/12-x-diet-bar-35-g | C26: 123 | D26: 13
A27: Zero Bar 40 g | B27: https://www.prozis.com/pt/pt/prozis/12-x-zero-bar-40-g-baixo-teor-de-acucares | C27: 140 | D27: 12
... A31: High Protein Waffles - Original 25 g | B31: https://www.prozis.com/pt/pt/prozis/6-x-high-protein-waffles-original-25-g?label=TlVUMDAvMTY2OTgzMDYzMw%3D%3D | C31: 94 | D31: 5.5
A33: Receitas
A34: Nome | B34: link | C34: kcal | D34: proteina
A35: Wrap Proteico | B35: https://www.prozis.com/pt/pt/prozis/4-x-wrap-proteico?label=TlVUMDAvMTY4MTUxMDYzMw%3D%3D | C35: 213 | D35: 15.4
A36: Pancake + Protein – Panquecas de aveia com proteína | B36: https://www.prozis.com/pt/pt/prozis/pancake-protein-panquecas-de-aveia-com-proteina-400-g?label=TlVUMDAvMTQwMzUwMTQ5MQ%3D%3D | C36: 91 | D36: 13.75
A37: Oatmeal + Whey | B37: https://www.prozis.com/pt/pt/prozis/oatmeal-whey-aveia-e-proteina-whey-1000-g?label=TlVUMDAvMTM5NzQwMDA2NQ%3D%3D | C37: 298 | D37: 24.8
A38: Lean Bread - Pão Multicereais | B38: https://www.prozis.com/pt/pt/prozis/lean-bread-pao-multicereais-360-g?label=TlVUMDAvMTQwMTIyMDAwMA%3D%3D | C38: 245 | D38: 17
A39: Aveia em pó | B39: https://www.prozis.com/pt/pt/prozis/aveia-instantanea-em-po-1250-g | C39: 385 | D39: 12
A40: Refeições | B40: https://www.prozis.com/pt/pt/alimentacao-saudavel/refeicoes | C40: - | D40: -
A41: Claras de ovo | B41: https://www.prozis.com/pt/pt/prozis/100-clara-de-ovo-liquida-albumina-1000-g | C41: 45 | D41: 10
A42: Mantiga amendoim | B42: https://www.prozis.com/pt/pt/prozis/manteiga-de-amendoim-1000-g#modal-nutrition_table | C42: 630 | D42: 26
A43: Molhos zero | B43: https://www.prozis.com/pt/pt/alimentacao-saudavel/molhos-xaropes-e-compotas/molhos-zero | C43: 0 | D43: 0
A45: Massa muscular
A46: Produto | B46: link
A47: Dextrose | B47: https://www.prozis.com/pt/pt/prozis/dextrose-2000-g | C47: .
A48: Manteiga de amendoim | B48: https://www.prozis.com/pt/pt/prozis/manteiga-de-amendoim-1000-g | C48: ,
A49: Xtreme Mass Gainer | B49: https://www.prozis.com/pt/pt/prozis/xtreme-mass-gainer-2722-g?label=TlVUMDAvMTMyNjYxMDAwNg%3D%3D | C49: .
A51: Emagrecer
A52: Produto | B52: link
A53: Casca de Psílio 1000 mg | B53: https://www.prozis.com/pt/pt/prozis/casca-de-psilio-1000-mg-60-capsulas-vegetarianas | C53: .
A54: Fiber Mix - Mistura de Fibras | B54: https://www.prozis.com/pt/pt/prozis/fiber-mix-mistura-de-fibras?label=TlVUMDAvMTY4NzE5MDAwMA%3D%3D | C54: .
A56: Proteinas
A57: Nome | B57: link | C57: kcal | D57: proteina
A58: 100% Whey Hydro Isolate PRO | B58: https://www.prozis.com/pt/pt/prozis/100-whey-hydro-isolate-pro-2000-g | C58: 385 | D58: 84
A59: 100% Proteína de Soja | B59: https://www.prozis.com/pt/pt/prozis/100-proteina-de-soja-900-g | C59: 385 | D59: 86
A60: 100% Proteína de Arroz | B60: https://www.prozis.com/pt/pt/prozis/100-proteina-de-arroz-900-g | C60: 418 | D60: 84
A61: 100% Proteína de Ervilha | B61: https://www.prozis.com/pt/pt/prozis/100-pea-protein-900-g | C61: 399 | D61: 77
A62: Clear Whey Isolate | B62: https://www.prozis.com/pt/pt/prozis/clear-whey-isolate-manga-e-pessego-500-g | C62: 363 | D62: 83
A63: Real whey | B63: https://www.prozis.com/pt/pt/prozis/100-real-whey-protein-1000-g?ot=GAPTSS&campaignid=18580646313&adgroupid=&keyword=&placement=&utm_source=PRZGAPT&gclid=CjwKCAjw44mlBhAQEiwAqP3eVp9ehjMX1RDTfhS0x2AXUw1sM-d91SYkmh5KY3t9zR1MmJ-q8v9OQhoCibgQAvD_BwE | C63: 394 | D63: 76
A64: Proteina vegetal | B64: https://www.prozis.com/pt/pt/prozis/100-vegan-protein-900-g | C64: 390 | D64: 82
A65: 100% Whey Prime | B65: https://www.prozis.com/pt/pt/prozis/100-whey-prime-1000-g | C65: 391 | D65: 82 | E65: 1,5g creatina por dose
A66: Whey Protein Fusion | B66: https://www.prozis.com/pt/pt/prozis/whey-protein-fusion-900-g | C66: 388 | D66: 80 | E66: 1,55g creatina por dose

Sheet Base dados Exercicios
E1: Músculo-alvo
C2: Exercicio | D2: Link | E2: 1 | F2: 1 | G2: 1 | H2: 0.5 | I2: 0.5 | J2: 0.3 | L2: MÚSCULO
A3: Puxar | B3: Biceps curl | C3: Biceps crul halteres deitado | D3: https://youtu.be/WcUsU8gNmGI | E3: Biceps | L3: Abs
A4: Puxar | B4: Biceps curl | C4: Biceps crul barra pé direita | D4: https://youtu.be/tPIZtS0j1Hg | E4: Biceps | L4: Biceps | N4: 1 | O4: 0
A5: Puxar | B5: Biceps curl | C5: Biceps crul barra pé Z | E5: Biceps | L5: Dorsal | N5: 2 | O5: 1
A6: Puxar | B6: Biceps curl | C6: Biceps curl banco inclinado halteres | D6: https://youtu.be/9JbUuix8X4o | E6: Biceps | L6: Ombro frontal | N6: 3 | O6: 2
A7: Puxar | B7: Biceps curl | C7: Biceps curl cristo cabos | D7: https://youtu.be/1m6fZSun6ME | E7: Biceps | L7: Ombro médio | N7: 4 | O7: 3
A8: Puxar | B8: Biceps curl | C8: Biceps curl concentrado | D8: https://youtube.com/shorts/pXQojCQjmZA?feature=share | E8: Biceps | L8: Ombro posterior | N8: 5 | O8: 4+
A9: Puxar | B9: Biceps curl | C9: Biceps curl elástico | D9: https://youtu.be/n1RomOv6TWw | E9: Biceps | L9: Peito | N9: 6
A10: Puxar | B10: Biceps curl | C10: Biceps curl maquina scott | D10: https://youtu.be/Kzkeb3Ce_pk | E10: Biceps | L10: Trapézio | N10: 7
A11: Puxar | B11: Biceps curl | C11: Biceps curl nos cabos cross | D11: https://youtu.be/orDUcRQnH3k | E11: Biceps | L11: Triceps | N11: 8
A12: Puxar | B12: Biceps curl | C12: Biceps curl pé cabos pronado | D12: https://youtu.be/rzhZ9k73ryA | E12: Biceps | L12: Quadriceps | N12: 9
A13: Puxar | B13: Biceps curl | C13: Biceps curl pé cabos supinado | E13: Biceps | L13: Posterior de coxa | N13: 10
A14: Puxar | B14: Biceps curl | C14: Biceps curl rosca pé | D14: https://youtu.be/Eg9Kwr92gS0 | E14: Biceps | L14: Glúteo
A15: Puxar | B15: Biceps curl | C15: Biceps curl scott unilateral | D15: https://youtu.be/pYMAEfw5HXA | E15: Biceps | L15: Lombares
A16: Puxar | B16: Biceps curl | C16: Biceps curl scott unilateral cabos | D16: https://youtu.be/8LFPPPaYISo | E16: Biceps | L16: Gémeos
A17: Puxar | B17: Biceps curl | C17: Biceps martelo pé corda | D17: https://youtu.be/qo92P0K2jb0 | E17: Biceps | L17: Adutores
A18: Puxar | B18: Biceps curl | C18: Bicesp curl TRX | D18: https://youtu.be/g93I74fnOpk | E18: Biceps
A19: Puxar | B19: Elevações/puxadas vertical | C19: Alavanca | D19: https://youtu.be/NgrgYoDFPoc | E19: Dorsal | I19: Biceps | J19: Trapézio
A20: Puxar | B20: Elevações/puxadas vertical | C20: Alavanca unilateral | D20: https://youtu.be/UW2PZRGpAFU | E20: Dorsal | I20: Biceps | J20: Trapézio
A21: Puxar | B21: Elevações/puxadas vertical | C21: Elevações assistidas | D21: https://youtube.com/shorts/H2V6HlpaEyE?feature=share | E21: Dorsal | I21: Biceps | J21: Trapézio
A22: Puxar | B22: Elevações/puxadas vertical | C22: Elevações elástico | D22: https://youtu.be/lIJXCLxzZvI | E22: Dorsal | I22: Biceps | J22: Trapézio
A23: Puxar | B23: Elevações/puxadas vertical | C23: Elevações negativas | D23: https://youtu.be/381QNvqq_5s | E23: Dorsal | I23: Biceps | J23: Trapézio
A24: Puxar | B24: Elevações/puxadas vertical | C24: Elevações pega neutra | D24: https://youtu.be/x6IKM5FNbzQ | E24: Dorsal | I24: Biceps | J24: Trapézio
A25: Puxar | B25: Elevações/puxadas vertical | C25: Elevações pega supinada | E25: Dorsal | I25: Biceps | J25: Trapézio
A26: Puxar | B26: Elevações/puxadas vertical | C26: Elevações pronadas | D26: https://youtu.be/Gadiybic1jk | E26: Dorsal | I26: Biceps | J26: Trapézio
A27: Puxar | B27: Elevações/puxadas vertical | C27: Puxador dorsal unilateral no banco | D27: https://youtube.com/shorts/uc1H5C-tpEU?feature=share | E27: Dorsal | I27: Biceps | J27: Trapézio
A28: Puxar | B28: Elevações/puxadas vertical | C28: Puxada vertical elástico | D28: https://youtu.be/WvehBL6yQnE | E28: Dorsal | I28: Biceps | J28: Trapézio
A29: Puxar | B29: Elevações/puxadas vertical | C29: Puxada vertical TRX | D29: https://youtu.be/gEfc9YVoySs | E29: Dorsal | I29: Biceps | J29: Trapézio
A30: Puxar | B30: Elevações/puxadas vertical | C30: Puxador vertical dorsal neutra | D30: https://youtu.be/dY6KGH9LsbI | E30: Dorsal | I30: Biceps | J30: Trapézio
A31: Puxar | B31: Elevações/puxadas vertical | C31: Puxador vertical dorsal pronado | D31: https://youtu.be/kF3nRuX99rw | E31: Dorsal | I31: Biceps | J31: Trapézio
A32: Puxar | B32: Elevações/puxadas vertical | C32: Puxador vertical dorsal supinado | E32: Dorsal | I32: Biceps | J32: Trapézio
A33: Puxar | B33: Elevações/puxadas vertical | C33: Puxador vertical unilateral cruzado | D33: https://youtube.com/shorts/A9Eqjm4W9_g?feature=share | E33: Dorsal | I33: Biceps | J33: Trapézio
A34: Puxar | B34: Elevações/puxadas vertical | C34: Puxador vertical inclinado no banco | D34: https://youtu.be/ZUt7vr8tZb0 | E34: Dorsal | I34: Biceps | J34: Trapézio
A35: Puxar | B35: Elevações/puxadas vertical | C35: Puxador vertical cruzada unilateral joelhos | D35: https://youtu.be/-tH0kO5CgWk | E35: Dorsal | I35: Biceps | J35: Trapézio
A36: Puxar | B36: Pull Faces | C36: Pull face cabos pé | D36: https://youtu.be/EvaEXreIYEU | E36: Ombro posterior | F36: Trapézio | H36: Ombro médio | J36: Biceps
A37: Puxar | B37: Pull Faces | C37: Pull face cabos sentado | D37: https://youtu.be/lrmgEHkHfNU | E37: Ombro posterior | F37: Trapézio | H37: Ombro médio | J37: Biceps
A38: Puxar | B38: Pull Faces | C38: Pull face TRX | D38: https://youtu.be/zoM5p9QCslY | E38: Ombro posterior | F38: Trapézio | H38: Ombro médio | J38: Biceps
A39: Puxar | B39: Pull over Cabos | C39: Pull over cabos em pé | D39: https://youtu.be/F8kzp7ldavg | E39: Dorsal | I39: Trapézio | J39: Triceps
A40: Puxar | B40: Pull over Cabos | C40: Pull over deitado halteres | D40: https://youtube.com/shorts/KgvssqlufQM?feature=share | E40: Dorsal | I40: Trapézio | J40: Triceps
A41: Puxar | B41: Pull over Cabos | C41: Pull over deslizante | D41: https://youtu.be/fPXRvw6LmJI | E41: Dorsal | I41: Trapézio | J41: Triceps
A42: Puxar | B42: Remada aberta | C42: Remada aberta sentado cabos | D42: https://youtube.com/shorts/wo1rfNoCgTQ?feature=share | E42: Ombro posterior | F42: Trapézio | I42: Lombares | J42: Biceps
A43: Puxar | B43: Remada aberta | C43: Remada aberta apoio banco | D43: https://youtu.be/NZaNK2IIGts | E43: Ombro posterior | F43: Trapézio | J43: Biceps
A44: Puxar | B44: Remada aberta | C44: Remada aberta pé elastico | D44: https://youtu.be/cbrbksVsuQ4 | E44: Ombro posterior | F44: Trapézio | I44: Lombares | J44: Biceps
A45: Puxar | B45: Remada aberta | C45: Remada aberta TRX | D45: https://youtu.be/oEjRAgKCUwc | E45: Ombro posterior | F45: Trapézio | I45: Lombares | J45: Biceps
A46: Puxar | B46: Remada aberta | C46: Remada alta barra | D46: https://youtu.be/EwfwfhTPhe0 | E46: Ombro médio | F46: Ombro posterior | H46: Trapézio | J46: Biceps
A47: Puxar | B47: Remada aberta | C47: Remada alta cabos | E47: Ombro médio | F47: Ombro posterior | H47: Trapézio | J47: Biceps
A48: Puxar | B48: Remada aberta | C48: Remada alta halteres | E48: Ombro médio | F48: Ombro posterior | H48: Trapézio | J48: Biceps
A49: Puxar | B49: Remada aberta | C49: Remada aberta banco inclinado halteres | D49: https://youtube.com/shorts/jQIwRsyq3Yc?feature=share | E49: Ombro posterior | F49: Trapézio | J49: Biceps
A50: Puxar | B50: Remada aberta | C50: Remada curva encosto aberta | D50: https://youtu.be/qwNF1WDCfI4 | E50: Ombro posterior | F50: Trapézio | H50: Dorsal | J50: Biceps
A51: Puxar | B51: Remada aberta | C51: Remada sentado nos cabos pronado | D51: https://youtu.be/xXh1dFX60cs | E51: Ombro posterior | F51: Trapézio | H51: Dorsal | I51: Lombares | J51: Biceps
A52: Puxar | B52: Remada aberta | C52: Remada baixa barra pronada | D52: https://youtu.be/CoUt2wXKquA | E52: Ombro posterior | F52: Trapézio | H52: Dorsal | I52: Lombares | J52: Biceps
A53: Puxar | B53: Remada fechada | C53: Remada baixa barra supinada | D53: https://youtu.be/1Hj4DtaPADE | E53: Dorsal | F53: Trapézio | H53: Lombares | I53: Ombro posterior | J53: Biceps
A54: Puxar | B54: Remada fechada | C54: Remada baixa barra supinada apoio banco | D54: https://youtu.be/QwWFTQPGHSY | E54: Dorsal | F54: Trapézio | I54: Ombro posterior | J54: Biceps
A55: Puxar | B55: Remada fechada | C55: Remada baixa halteres apoio banco | D55: https://youtube.com/shorts/eJ0MLjjbbjk?feature=share | E55: Dorsal | F55: Trapézio | I55: Ombro posterior | J55: Biceps
A56: Puxar | B56: Remada fechada | C56: Remada baixa halteres neutro | D56: https://youtube.com/shorts/IZRQMn9rc0o?feature=share | E56: Dorsal | F56: Trapézio | H56: Lombares | I56: Ombro posterior | J56: Biceps
A57: Puxar | B57: Remada fechada | C57: Remada baixa mochila | D57: https://youtu.be/GUS7wdRfRNk | E57: Dorsal | F57: Trapézio | H57: Lombares | I57: Ombro posterior | J57: Biceps
A58: Puxar | B58: Remada fechada | C58: Remada banco inclinado halteres | D58: https://youtu.be/VOgtP6qh9Ws | E58: Dorsal | F58: Trapézio | I58: Ombro posterior | J58: Biceps
A59: Puxar | B59: Remada fechada | C59: Remada curva encosto fechada | D59: https://youtube.com/shorts/Pt6-1kTAfE0?feature=share | E59: Dorsal | F59: Trapézio | I59: Ombro posterior | J59: Biceps
A60: Puxar | B60: Remada fechada | C60: Remada deitado banco barra pronado | D60: https://youtu.be/BAEmJXvZd5E | E60: Dorsal | F60: Trapézio | I60: Ombro posterior | J60: Biceps
A61: Puxar | B61: Remada fechada | C61: Remada deitado halteres | D61: https://youtu.be/ykHSVgXU1Yg | E61: Dorsal | F61: Trapézio | I61: Ombro posterior | J61: Biceps
A62: Puxar | B62: Remada fechada | C62: Remada deitado na mesa | D62: https://youtu.be/x99pS7PgAAQ | E62: Dorsal | F62: Trapézio | H62: Lombares | I62: Ombro posterior | J62: Biceps
A63: Puxar | B63: Remada fechada | C63: Remada fechada pé elastico | D63: https://youtu.be/RiHWKt7uK0U | E63: Dorsal | F63: Trapézio | H63: Lombares | I63: Ombro posterior | J63: Biceps
A64: Puxar | B64: Remada fechada | C64: Remada fechada TRX | D64: https://youtu.be/iu2vnAvS8SA | E64: Dorsal | F64: Trapézio | H64: Lombares | I64: Ombro posterior | J64: Biceps
A65: Puxar | B65: Remada fechada | C65: Remada inclinado na maquina com encosto | D65: https://youtube.com/shorts/6Os0Lm8OWAM?feature=share | E65: Dorsal | F65: Trapézio | I65: Ombro posterior | J65: Biceps
A66: Puxar | B66: Remada fechada | C66: Remada maquina encosto neutra | D66: https://youtu.be/NmqklJDizWo | E66: Dorsal | F66: Trapézio | I66: Ombro posterior | J66: Biceps
A67: Puxar | B67: Remada fechada | C67: Remada sentado nos cabos pega neutra | D67: https://youtu.be/pss0QOfpSao | E67: Dorsal | F67: Trapézio | H67: Lombares | I67: Ombro posterior | J67: Biceps
A68: Puxar | B68: Remada fechada | C68: Remada sentado nos cabos supinado | E68: Dorsal | F68: Trapézio | H68: Lombares | I68: Ombro posterior | J68: Biceps
A69: Puxar | B69: Remada fechada | C69: Remada T | D69: https://youtu.be/ktdUTtnfhWI | E69: Dorsal | F69: Trapézio | H69: Lombares | I69: Ombro posterior | J69: Biceps
A70: Puxar | B70: Remada fechada | C70: Remada unilateral cabos | D70: https://youtu.be/I2CQeB4LrAw | E70: Dorsal | F70: Trapézio | H70: Lombares | I70: Ombro posterior | J70: Biceps
A71: Puxar | B71: Remada fechada | C71: Remada unilateral halteres | D71: https://youtu.be/b5Aqknu-1Ng | E71: Dorsal | F71: Trapézio | H71: Lombares | I71: Ombro posterior | J71: Biceps
A72: Puxar | B72: Remada fechada | C72: Remada unilateral mochila | D72: https://youtu.be/WyVuZ5uK8k8 | E72: Dorsal | F72: Trapézio | H72: Lombares | I72: Ombro posterior | J72: Biceps
A73: Puxar | B73: Trapézio | C73: Encolhimentos barra | E73: Trapézio
A74: Puxar | B74: Trapézio | C74: Encolhimentos halteres | E74: Trapézio
A75: Puxar | B75: Trapézio | C75: Encolhimentos smith machine | E75: Trapézio
A76: Puxar | B76: Voos | C76: Y comboio | E76: Trapézio | F76: Ombro posterior | H76: Ombro médio
A77: Puxar | B77: Voos | C77: Voos banco inclinado halteres | D77: https://youtu.be/aG3nDTjm16Y | E77: Ombro posterior | G77: Trapézio | H77: Ombro médio
A78: Puxar | B78: Voos | C78: Voos inclinado com halteres | E78: Ombro posterior | G78: Trapézio | H78: Ombro médio
A79: Puxar | B79: Voos | C79: Voos máquina | D79: https://youtu.be/MKfzpZ4Q0uU | E79: Ombro posterior | G79: Trapézio | H79: Ombro médio
A80: Puxar | B80: Voos | C80: Voos pé cabos | D80: https://youtu.be/4yYz0NCWFRk | E80: Ombro posterior | G80: Trapézio | H80: Ombro médio
A81: Puxar | B81: Voos | C81: Voos sentado halteres | D81: https://youtu.be/Ft7E49Tw3UQ | E81: Ombro posterior | G81: Trapézio | H81: Ombro médio
A82: Puxar | B82: Voos | C82: Voos TRX | D82: https://youtube.com/shorts/uhiztQ8V9Vw?feature=share | E82: Ombro posterior | G82: Trapézio | H82: Ombro médio
A83: Perna | B83: Abdutores | C83: Abdutores deitado | D83: https://youtu.be/FA6jHdFlvg8 | E83: Glúteo
A84: Perna | B84: Abdutores | C84: Abdutores máquina | D84: https://youtu.be/oHjivORRk1Y | E84: Glúteo
A85: Perna | B85: Abdutores | C85: Abdutores pêndulo | E85: Glúteo
A86: Perna | B86: Adutores | C86: Adutores deitado | D86: https://youtu.be/teGAg19KWw0 | E86: Adutores
A87: Perna | B87: Adutores | C87: Adutores máquina | E87: Adutores
A88: Perna | B88: Adutores | C88: Adutores pêndulo | E88: Adutores
A89: Perna | B89: Agachamento | C89: Agachamento TRX | D89: https://www.youtube.com/shorts/GHar7RpOJrg | E89: Quadriceps | F89: Glúteo | H89: Adutores | I89: Posterior de coxa | J89: Gémeos
A90: Perna | B90: Agachamento | C90: Agachamento cadeira | D90: https://www.youtube.com/shorts/a7VXjG3LvR8 | E90: Quadriceps | F90: Glúteo | H90: Adutores | I90: Posterior de coxa | J90: Gémeos
A91: Perna | B91: Agachamento | C91: Agachamento 1 perna cadeira | D91: https://youtu.be/MOmHtKUKbvo | E91: Quadriceps | F91: Glúteo | H91: Adutores | I91: Posterior de coxa | J91: Gémeos
A92: Perna | B92: Agachamento | C92: Agachamento barra | D92: https://youtu.be/x8hljkfvgo4 | E92: Quadriceps | F92: Glúteo | H92: Adutores | I92: Gémeos | J92: Posterior de coxa
A93: Perna | B93: Agachamento | C93: Agachamento normal smith | D93: https://youtube.com/shorts/sNTHP1a9byE?feature=share | E93: Quadriceps | F93: Glúteo | H93: Adutores | I93: Gémeos | J93: Posterior de coxa
A94: Perna | B94: Agachamento | C94: Agachamento curto em baixo | D94: https://youtu.be/9hZT-XcdPqc | E94: Quadriceps | F94: Glúteo | H94: Adutores | I94: Gémeos | J94: Posterior de coxa
A95: Perna | B95: Agachamento | C95: Agachamento mochila | D95: https://youtu.be/u53nsBJnQRM | E95: Quadriceps | F95: Glúteo | H95: Adutores | I95: Gémeos | J95: Posterior de coxa
A96: Perna | B96: Agachamento | C96: Pistol squat | D96: https://youtu.be/RbQZwsGUAzY | E96: Quadriceps | F96: Glúteo | H96: Adutores | I96: Posterior de coxa | J96: Gémeos
A97: Perna | B97: Agachamento | C97: Pistol squat TRX | D97: https://youtu.be/SH5ivwB_LhE | E97: Quadriceps | F97: Glúteo | H97: Adutores | I97: Posterior de coxa | J97: Gémeos
A98: Perna | B98: Gémeos | C98: Gémeos no leg press | E98: Gémeos
A99: Perna | B99: Gémeos | C99: Gemeos pé maquina | D99: https://youtu.be/SYPJv6TPACY | E99: Gémeos
A100: Perna | B100: Gémeos | C100: Gémeos pé peso corpo | D100: https://youtu.be/6ZwbBza7x54 | E100: Gémeos
...

Sheet Dieta 1
A1: Plano Alimentar
J2: \
D3: Proteina | E3: Gordura | F3: Hidratos | G3: Kcal | L3: Proteina | M3: Gordura | N3: Hidratos | O3: Kcal
B4: Objetivo | G4: =D4*4+E4*9+F4*4 -> 0 | J4: Objetivo | L4: =D4 -> 0 | M4: =E4 -> 0 | N4: =F4 -> 0 | O4: =L4*4+M4*9+N4*4 -> 0
B5: Total diário alimentação | D5: =SUM(D15,D23,D31,D39,D47,D55) -> 0 | E5: =SUM(E15,E23,E31,E39,E47,E55) -> 0 | F5: =SUM(F15,F23,F31,F39,F47,F55) -> 0 | G5: =SUM(G15,G23,G31,G39,G47,G55) -> 0 | J5: Total diário alimentação | L5: =SUM(L15,L23,L31,L39,L47,L55) -> 0 | M5: =SUM(M15,M23,M31,M39,M47,M55) -> 0 | N5: =SUM(N15,N23,N31,N39,N47,N55) -> 0 | O5: =SUM(O15,O23,O31,O39,O47,O55) -> 0
B6: Em falta | D6: =D4-D5 -> 0 | E6: =E4-E5 -> 0 | F6: =F4-F5 -> 0 | G6: =G4-G5 -> 0 | J6: Em falta | L6: =L4-L5 -> 0 | M6: =M4-M5 -> 0 | N6: =N4-N5 -> 0 | O6: =O4-O5 -> 0
B8: Alimento | C8: Quantidade | D8: Proteina | E8: Gordura | F8: Hidratos | G8: Kcal | J8: Alimento | K8: Quantidade | L8: Proteina | M8: Gordura | N8: Hidratos | O8: Kcal
A9: Refeição 1 | D9: =IFERROR(VLOOKUP($B9,'Base dados dieta'!$A:$F,MATCH(D$8,$D$8:$F$8,0)+3,FALSE)/VLOOKUP($B9,'Base dados dieta'!$A:$F,2,FALSE)*$C9,"") | E9: =IFERROR(VLOOKUP($B9,'Base dados dieta'!$A:$F,MATCH(E$8,$D$8:$F$8,0)+3,FALSE)/VLOOKUP($B9,'Base dados dieta'!$A:$F,2,FALSE)*$C9,"") | F9: =IFERROR(VLOOKUP($B9,'Base dados dieta'!$A:$F,MATCH(F$8,$D$8:$F$8,0)+3,FALSE)/VLOOKUP($B9,'Base dados dieta'!$A:$F,2,FALSE)*$C9,"") | G9: =IFERROR(D9*4+E9*9+F9*4,"") | I9: Refeição 1 | L9: =IFERROR(VLOOKUP($J9,'Base dados dieta'!$A:$F,MATCH(L$8,$L$8:$N$8,0)+3,FALSE)/VLOOKUP($J9,'Base dados dieta'!$A:$F,2,FALSE)*$K9,"") | M9: =IFERROR(VLOOKUP($J9,'Base dados dieta'!$A:$F,MATCH(M$8,$L$8:$N$8,0)+3,FALSE)/VLOOKUP($J9,'Base dados dieta'!$A:$F,2,FALSE)*$K9,"") | N9: =IFERROR(VLOOKUP($J9,'Base dados dieta'!$A:$F,MATCH(N$8,$L$8:$N$8,0)+3,FALSE)/VLOOKUP($J9,'Base dados dieta'!$A:$F,2,FALSE)*$K9,"") | O9: =IFERROR(L9*4+M9*9+N9*4,"")
D10: =IFERROR(VLOOKUP($B10,'Base dados dieta'!$A:$F,MATCH(D$8,$D$8:$F$8,0)+3,FALSE)/VLOOKUP($B10,'Base dados dieta'!$A:$F,2,FALSE)*$C10,"") | E10: =IFERROR(VLOOKUP($B10,'Base dados dieta'!$A:$F,MATCH(E$8,$D$8:$F$8,0)+3,FALSE)/VLOOKUP($B10,'Base dados dieta'!$A:$F,2,FALSE)*$C10,"") | F10: =IFERROR(VLOOKUP($B10,'Base dados dieta'!$A:$F,MATCH(F$8,$D$8:$F$8,0)+3,FALSE)/VLOOKUP($B10,'Base dados dieta'!$A:$F,2,FALSE)*$C10,"") | G10: =IFERROR(D10*4+E10*9+F10*4,"") | L10: =IFERROR(VLOOKUP($J10,'Base dados dieta'!$A:$F,MATCH(L$8,$L$8:$N$8,0)+3,FALSE)/VLOOKUP($J10,'Base dados dieta'!$A:$F,2,FALSE)*$K10,"") | M10: =IFERROR(VLOOKUP($J10,'Base dados dieta'!$A:$F,MATCH(M$8,$L$8:$N$8,0)+3,FALSE)/VLOOKUP($J10,'Base dados dieta'!$A:$F,2,FALSE)*$K10,"") | N10: =IFERROR(VLOOKUP($J10,'Base dados dieta'!$A:$F,MATCH(N$8,$L$8:$N$8,0)+3,FALSE)/VLOOKUP($J10,'Base dados dieta'!$A:$F,2,FALSE)*$K10,"") | O10: =IFERROR(L10*4+M10*9+N10*4,"")
D11: =IFERROR(VLOOKUP($B11,'Base dados dieta'!$A:$F,MATCH(D$8,$D$8:$F$8,0)+3,FALSE)/VLOOKUP($B11,'Base dados dieta'!$A:$F,2,FALSE)*$C11,"") | E11: =IFERROR(VLOOKUP($B11,'Base dados dieta'!$A:$F,MATCH(E$8,$D$8:$F$8,0)+3,FALSE)/VLOOKUP($B11,'Base dados dieta'!$A:$F,2,FALSE)*$C11,"") | F11: =IFERROR(VLOOKUP($B11,'Base dados dieta'!$A:$F,MATCH(F$8,$D$8:$F$8,0)+3,FALSE)/VLOOKUP($B11,'Base dados dieta'!$A:$F,2,FALSE)*$C11,"") | G11: =IFERROR(D11*4+E11*9+F11*4,"") | L11: =IFERROR(VLOOKUP($J11,'Base dados dieta'!$A:$F,MATCH(L$8,$L$8:$N$8,0)+3,FALSE)/VLOOKUP($J11,'Base dados dieta'!$A:$F,2,FALSE)*$K11,"") | M11: =IFERROR(VLOOKUP($J11,'Base dados dieta'!$A:$F,MATCH(M$8,$L$8:$N$8,0)+3,FALSE)/VLOOKUP($J11,'Base dados dieta'!$A:$F,2,FALSE)*$K11,"") | N11: =IFERROR(VLOOKUP($J11,'Base dados dieta'!$A:$F,MATCH(N$8,$L$8:$N$8,0)+3,FALSE)/VLOOKUP($J11,'Base dados dieta'!$A:$F,2,FALSE)*$K11,"") | O11: =IFERROR(L11*4+M11*9+N11*4,"")
D12: =IFERROR(VLOOKUP($B12,'Base dados dieta'!$A:$F,MATCH(D$8,$D$8:$F$8,0)+3,FALSE)/VLOOKUP($B12,'Base dados dieta'!$A:$F,2,FALSE)*$C12,"") | E12: =IFERROR(VLOOKUP($B12,'Base dados dieta'!$A:$F,MATCH(E$8,$D$8:$F$8,0)+3,FALSE)/VLOOKUP($B12,'Base dados dieta'!$A:$F,2,FALSE)*$C12,"") | F12: =IFERROR(VLOOKUP($B12,'Base dados dieta'!$A:$F,MATCH(F$8,$D$8:$F$8,0)+3,FALSE)/VLOOKUP($B12,'Base dados dieta'!$A:$F,2,FALSE)*$C12,"") | G12: =IFERROR(D12*4+E12*9+F12*4,"") | L12: =IFERROR(VLOOKUP($J12,'Base dados dieta'!$A:$F,MATCH(L$8,$L$8:$N$8,0)+3,FALSE)/VLOOKUP($J12,'Base dados dieta'!$A:$F,2,FALSE)*$K12,"") | M12: =IFERROR(VLOOKUP($J12,'Base dados dieta'!$A:$F,MATCH(M$8,$L$8:$N$8,0)+3,FALSE)/VLOOKUP($J12,'Base dados dieta'!$A:$F,2,FALSE)*$K12,"") | N12: =IFERROR(VLOOKUP($J12,'Base dados dieta'!$A:$F,MATCH(N$8,$L$8:$N$8,0)+3,FALSE)/VLOOKUP($J12,'Base dados dieta'!$A:$F,2,FALSE)*$K12,"") | O12: =IFERROR(L12*4+M12*9+N12*4,"")
D13: =IFERROR(VLOOKUP($B13,'Base dados dieta'!$A:$F,MATCH(D$8,$D$8:$F$8,0)+3,FALSE)/VLOOKUP($B13,'Base dados dieta'!$A:$F,2,FALSE)*$C13,"") | E13: =IFERROR(VLOOKUP($B13,'Base dados dieta'!$A:$F,MATCH(E$8,$D$8:$F$8,0)+3,FALSE)/VLOOKUP($B13,'Base dados dieta'!$A:$F,2,FALSE)*$C13,"") | F13: =IFERROR(VLOOKUP($B13,'Base dados dieta'!$A:$F,MATCH(F$8,$D$8:$F$8,0)+3,FALSE)/VLOOKUP($B13,'Base dados dieta'!$A:$F,2,FALSE)*$C13,"") | G13: =IFERROR(D13*4+E13*9+F13*4,"") | L13: =IFERROR(VLOOKUP($J13,'Base dados dieta'!$A:$F,MATCH(L$8,$L$8:$N$8,0)+3,FALSE)/VLOOKUP($J13,'Base dados dieta'!$A:$F,2,FALSE)*$K13,"") | M13: =IFERROR(VLOOKUP($J13,'Base dados dieta'!$A:$F,MATCH(M$8,$L$8:$N$8,0)+3,FALSE)/VLOOKUP($J13,'Base dados dieta'!$A:$F,2,FALSE)*$K13,"") | N13: =IFERROR(VLOOKUP($J13,'Base dados dieta'!$A:$F,MATCH(N$8,$L$8:$N$8,0)+3,FALSE)/VLOOKUP($J13,'Base dados dieta'!$A:$F,2,FALSE)*$K13,"") | O13: =IFERROR(L13*4+M13*9+N13*4,"")
D14: =IFERROR(VLOOKUP($B14,'Base dados dieta'!$A:$F,MATCH(D$8,$D$8:$F$8,0)+3,FALSE)/VLOOKUP($B14,'Base dados dieta'!$A:$F,2,FALSE)*$C14,"") | E14: =IFERROR(VLOOKUP($B14,'Base dados dieta'!$A:$F,MATCH(E$8,$D$8:$F$8,0)+3,FALSE)/VLOOKUP($B14,'Base dados dieta'!$A:$F,2,FALSE)*$C14,"") | F14: =IFERROR(VLOOKUP($B14,'Base dados dieta'!$A:$F,MATCH(F$8,$D$8:$F$8,0)+3,FALSE)/VLOOKUP($B14,'Base dados dieta'!$A:$F,2,FALSE)*$C14,"") | G14: =IFERROR(D14*4+E14*9+F14*4,"") | O14: =IFERROR(L14*4+M14*9+N14*4,"") -> 0
C15: Total | D15: =SUM(D9:D14) -> 0 | E15: =SUM(E9:E14) -> 0 | F15: =SUM(F9:F14) -> 0 | G15: =SUM(G9:G14) -> 0 | K15: Total | L15: =SUM(L9:L14) -> 0 | M15: =SUM(M9:M14) -> 0 | N15: =SUM(N9:N14) -> 0 | O15: =SUM(O9:O14) -> 0
A17: Refeição 2 | D17: =IFERROR(VLOOKUP($B17,'Base dados dieta'!$A:$F,MATCH(D$8,$D$8:$F$8,0)+3,FALSE)/VLOOKUP($B17,'Base dados dieta'!$A:$F,2,FALSE)*$C17,"") | E17: =IFERROR(VLOOKUP($B17,'Base dados dieta'!$A:$F,MATCH(E$8,$D$8:$F$8,0)+3,FALSE)/VLOOKUP($B17,'Base dados dieta'!$A:$F,2,FALSE)*$C17,"") | F17: =IFERROR(VLOOKUP($B17,'Base dados dieta'!$A:$F,MATCH(F$8,$D$8:$F$8,0)+3,FALSE)/VLOOKUP($B17,'Base dados dieta'!$A:$F,2,FALSE)*$C17,"") | G17: =IFERROR(D17*4+E17*9+F17*4,"") | I17: Refeição 2 | L17: =IFERROR(VLOOKUP($J17,'Base dados dieta'!$A:$F,MATCH(L$8,$L$8:$N$8,0)+3,FALSE)/VLOOKUP($J17,'Base dados dieta'!$A:$F,2,FALSE)*$K17,"") | M17: =IFERROR(VLOOKUP($J17,'Base dados dieta'!$A:$F,MATCH(M$8,$L$8:$N$8,0)+3,FALSE)/VLOOKUP($J17,'Base dados dieta'!$A:$F,2,FALSE)*$K17,"") | N17: =IFERROR(VLOOKUP($J17,'Base dados dieta'!$A:$F,MATCH(N$8,$L$8:$N$8,0)+3,FALSE)/VLOOKUP($J17,'Base dados dieta'!$A:$F,2,FALSE)*$K17,"") | O17: =IFERROR(L17*4+M17*9+N17*4,"")
D18: =IFERROR(VLOOKUP($B18,'Base dados dieta'!$A:$F,MATCH(D$8,$D$8:$F$8,0)+3,FALSE)/VLOOKUP($B18,'Base dados dieta'!$A:$F,2,FALSE)*$C18,"") | E18: =IFERROR(VLOOKUP($B18,'Base dados dieta'!$A:$F,MATCH(E$8,$D$8:$F$8,0)+3,FALSE)/VLOOKUP($B18,'Base dados dieta'!$A:$F,2,FALSE)*$C18,"") | F18: =IFERROR(VLOOKUP($B18,'Base dados dieta'!$A:$F,MATCH(F$8,$D$8:$F$8,0)+3,FALSE)/VLOOKUP($B18,'Base dados dieta'!$A:$F,2,FALSE)*$C18,"") | G18: =IFERROR(D18*4+E18*9+F18*4,"") | L18: =IFERROR(VLOOKUP($J18,'Base dados dieta'!$A:$F,MATCH(L$8,$L$8:$N$8,0)+3,FALSE)/VLOOKUP($J18,'Base dados dieta'!$A:$F,2,FALSE)*$K18,"") | M18: =IFERROR(VLOOKUP($J18,'Base dados dieta'!$A:$F,MATCH(M$8,$L$8:$N$8,0)+3,FALSE)/VLOOKUP($J18,'Base dados dieta'!$A:$F,2,FALSE)*$K18,"") | N18: =IFERROR(VLOOKUP($J18,'Base dados dieta'!$A:$F,MATCH(N$8,$L$8:$N$8,0)+3,FALSE)/VLOOKUP($J18,'Base dados dieta'!$A:$F,2,FALSE)*$K18,"") | O18: =IFERROR(L18*4+M18*9+N18*4,"")
D19: =IFERROR(VLOOKUP($B19,'Base dados dieta'!$A:$F,MATCH(D$8,$D$8:$F$8,0)+3,FALSE)/VLOOKUP($B19,'Base dados dieta'!$A:$F,2,FALSE)*$C19,"") | E19: =IFERROR(VLOOKUP($B19,'Base dados dieta'!$A:$F,MATCH(E$8,$D$8:$F$8,0)+3,FALSE)/VLOOKUP($B19,'Base dados dieta'!$A:$F,2,FALSE)*$C19,"") | F19: =IFERROR(VLOOKUP($B19,'Base dados dieta'!$A:$F,MATCH(F$8,$D$8:$F$8,0)+3,FALSE)/VLOOKUP($B19,'Base dados dieta'!$A:$F,2,FALSE)*$C19,"") | G19: =IFERROR(D19*4+E19*9+F19*4,"") | L19: =IFERROR(VLOOKUP($J19,'Base dados dieta'!$A:$F,MATCH(L$8,$L$8:$N$8,0)+3,FALSE)/VLOOKUP($J19,'Base dados dieta'!$A:$F,2,FALSE)*$K19,"") | M19: =IFERROR(VLOOKUP($J19,'Base dados dieta'!$A:$F,MATCH(M$8,$L$8:$N$8,0)+3,FALSE)/VLOOKUP($J19,'Base dados dieta'!$A:$F,2,FALSE)*$K19,"") | N19: =IFERROR(VLOOKUP($J19,'Base dados dieta'!$A:$F,MATCH(N$8,$L$8:$N$8,0)+3,FALSE)/VLOOKUP($J19,'Base dados dieta'!$A:$F,2,FALSE)*$K19,"") | O19: =IFERROR(L19*4+M19*9+N19*4,"")
D20: =IFERROR(VLOOKUP($B20,'Base dados dieta'!$A:$F,MATCH(D$8,$D$8:$F$8,0)+3,FALSE)/VLOOKUP($B20,'Base dados dieta'!$A:$F,2,FALSE)*$C20,"") | E20: =IFERROR(VLOOKUP($B20,'Base dados dieta'!$A:$F,MATCH(E$8,$D$8:$F$8,0)+3,FALSE)/VLOOKUP($B20,'Base dados dieta'!$A:$F,2,FALSE)*$C20,"") | F20: =IFERROR(VLOOKUP($B20,'Base dados dieta'!$A:$F,MATCH(F$8,$D$8:$F$8,0)+3,FALSE)/VLOOKUP($B20,'Base dados dieta'!$A:$F,2,FALSE)*$C20,"") | G20: =IFERROR(D20*4+E20*9+F20*4,"") | L20: =IFERROR(VLOOKUP($J20,'Base dados dieta'!$A:$F,MATCH(L$8,$L$8:$N$8,0)+3,FALSE)/VLOOKUP($J20,'Base dados dieta'!$A:$F,2,FALSE)*$K20,"") | M20: =IFERROR(VLOOKUP($J20,'Base dados dieta'!$A:$F,MATCH(M$8,$L$8:$N$8,0)+3,FALSE)/VLOOKUP($J20,'Base dados dieta'!$A:$F,2,FALSE)*$K20,"") | N20: =IFERROR(VLOOKUP($J20,'Base dados dieta'!$A:$F,MATCH(N$8,$L$8:$N$8,0)+3,FALSE)/VLOOKUP($J20,'Base dados dieta'!$A:$F,2,FALSE)*$K20,"") | O20: =IFERROR(L20*4+M20*9+N20*4,"")
D21: =IFERROR(VLOOKUP($B21,'Base dados dieta'!$A:$F,MATCH(D$8,$D$8:$F$8,0)+3,FALSE)/VLOOKUP($B21,'Base dados dieta'!$A:$F,2,FALSE)*$C21,"") | E21: =IFERROR(VLOOKUP($B21,'Base dados dieta'!$A:$F,MATCH(E$8,$D$8:$F$8,0)+3,FALSE)/VLOOKUP($B21,'Base dados dieta'!$A:$F,2,FALSE)*$C21,"") | F21: =IFERROR(VLOOKUP($B21,'Base dados dieta'!$A:$F,MATCH(F$8,$D$8:$F$8,0)+3,FALSE)/VLOOKUP($B21,'Base dados dieta'!$A:$F,2,FALSE)*$C21,"") | G21: =IFERROR(D21*4+E21*9+F21*4,"") | L21: =IFERROR(VLOOKUP($J21,'Base dados dieta'!$A:$F,MATCH(L$8,$L$8:$N$8,0)+3,FALSE)/VLOOKUP($J21,'Base dados dieta'!$A:$F,2,FALSE)*$K21,"") | M21: =IFERROR(VLOOKUP($J21,'Base dados dieta'!$A:$F,MATCH(M$8,$L$8:$N$8,0)+3,FALSE)/VLOOKUP($J21,'Base dados dieta'!$A:$F,2,FALSE)*$K21,"") | N21: =IFERROR(VLOOKUP($J21,'Base dados dieta'!$A:$F,MATCH(N$8,$L$8:$N$8,0)+3,FALSE)/VLOOKUP($J21,'Base dados dieta'!$A:$F,2,FALSE)*$K21,"") | O21: =IFERROR(L21*4+M21*9+N21*4,"")
D22: =IFERROR(VLOOKUP($B22,'Base dados dieta'!$A:$F,MATCH(D$8,$D$8:$F$8,0)+3,FALSE)/VLOOKUP($B22,'Base dados dieta'!$A:$F,2,FALSE)*$C22,"") | E22: =IFERROR(VLOOKUP($B22,'Base dados dieta'!$A:$F,MATCH(E$8,$D$8:$F$8,0)+3,FALSE)/VLOOKUP($B22,'Base dados dieta'!$A:$F,2,FALSE)*$C22,"") | F22: =IFERROR(VLOOKUP($B22,'Base dados dieta'!$A:$F,MATCH(F$8,$D$8:$F$8,0)+3,FALSE)/VLOOKUP($B22,'Base dados dieta'!$A:$F,2,FALSE)*$C22,"") | G22: =IFERROR(D22*4+E22*9+F22*4,"") | O22: =IFERROR(L22*4+M22*9+N22*4,"") -> 0
C23: Total | D23: =SUM(D17:D22) -> 0 | E23: =SUM(E17:E22) -> 0 | F23: =SUM(F17:F22) -> 0 | G23: =SUM(G17:G22) -> 0 | K23: Total | L23: =SUM(L17:L22) -> 0 | M23: =SUM(M17:M22) -> 0 | N23: =SUM(N17:N22) -> 0 | O23: =SUM(O17:O22) -> 0
A25: Refeição 3 | D25: =IFERROR(VLOOKUP($B25,'Base dados dieta'!$A:$F,MATCH(D$8,$D$8:$F$8,0)+3,FALSE)/VLOOKUP($B25,'Base dados dieta'!$A:$F,2,FALSE)*$C25,"") | E25: =IFERROR(VLOOKUP($B25,'Base dados dieta'!$A:$F,MATCH(E$8,$D$8:$F$8,0)+3,FALSE)/VLOOKUP($B25,'Base dados dieta'!$A:$F,2,FALSE)*$C25,"") | F25: =IFERROR(VLOOKUP($B25,'Base dados dieta'!$A:$F,MATCH(F$8,$D$8:$F$8,0)+3,FALSE)/VLOOKUP($B25,'Base dados dieta'!$A:$F,2,FALSE)*$C25,"") | G25: =IFERROR(D25*4+E25*9+F25*4,"") | I25: Refeição 3 | L25: =IFERROR(VLOOKUP($J25,'Base dados dieta'!$A:$F,MATCH(L$8,$L$8:$N$8,0)+3,FALSE)/VLOOKUP($J25,'Base dados dieta'!$A:$F,2,FALSE)*$K25,"") | M25: =IFERROR(VLOOKUP($J25,'Base dados dieta'!$A:$F,MATCH(M$8,$L$8:$N$8,0)+3,FALSE)/VLOOKUP($J25,'Base dados dieta'!$A:$F,2,FALSE)*$K25,"") | N25: =IFERROR(VLOOKUP($J25,'Base dados dieta'!$A:$F,MATCH(N$8,$L$8:$N$8,0)+3,FALSE)/VLOOKUP($J25,'Base dados dieta'!$A:$F,2,FALSE)*$K25,"") | O25: =IFERROR(L25*4+M25*9+N25*4,"")
D26: =IFERROR(VLOOKUP($B26,'Base dados dieta'!$A:$F,MATCH(D$8,$D$8:$F$8,0)+3,FALSE)/VLOOKUP($B26,'Base dados dieta'!$A:$F,2,FALSE)*$C26,"") | E26: =IFERROR(VLOOKUP($B26,'Base dados dieta'!$A:$F,MATCH(E$8,$D$8:$F$8,0)+3,FALSE)/VLOOKUP($B26,'Base dados dieta'!$A:$F,2,FALSE)*$C26,"") | F26: =IFERROR(VLOOKUP($B26,'Base dados dieta'!$A:$F,MATCH(F$8,$D$8:$F$8,0)+3,FALSE)/VLOOKUP($B26,'Base dados dieta'!$A:$F,2,FALSE)*$C26,"") | G26: =IFERROR(D26*4+E26*9+F26*4,"") | L26: =IFERROR(VLOOKUP($J26,'Base dados dieta'!$A:$F,MATCH(L$8,$L$8:$N$8,0)+3,FALSE)/VLOOKUP($J26,'Base dados dieta'!$A:$F,2,FALSE)*$K26,"") | M26: =IFERROR(VLOOKUP($J26,'Base dados dieta'!$A:$F,MATCH(M$8,$L$8:$N$8,0)+3,FALSE)/VLOOKUP($J26,'Base dados dieta'!$A:$F,2,FALSE)*$K26,"") | N26: =IFERROR(VLOOKUP($J26,'Base dados dieta'!$A:$F,MATCH(N$8,$L$8:$N$8,0)+3,FALSE)/VLOOKUP($J26,'Base dados dieta'!$A:$F,2,FALSE)*$K26,"") | O26: =IFERROR(L26*4+M26*9+N26*4,"")
D27: =IFERROR(VLOOKUP($B27,'Base dados dieta'!$A:$F,MATCH(D$8,$D$8:$F$8,0)+3,FALSE)/VLOOKUP($B27,'Base dados dieta'!$A:$F,2,FALSE)*$C27,"") | E27: =IFERROR(VLOOKUP($B27,'Base dados dieta'!$A:$F,MATCH(E$8,$D$8:$F$8,0)+3,FALSE)/VLOOKUP($B27,'Base dados dieta'!$A:$F,2,FALSE)*$C27,"") | F27: =IFERROR(VLOOKUP($B27,'Base dados dieta'!$A:$F,MATCH(F$8,$D$8:$F$8,0)+3,FALSE)/VLOOKUP($B27,'Base dados dieta'!$A:$F,2,FALSE)*$C27,"") | G27: =IFERROR(D27*4+E27*9+F27*4,"") | L27: =IFERROR(VLOOKUP($J27,'Base dados dieta'!$A:$F,MATCH(L$8,$L$8:$N$8,0)+3,FALSE)/VLOOKUP($J27,'Base dados dieta'!$A:$F,2,FALSE)*$K27,"") | M27: =IFERROR(VLOOKUP($J27,'Base dados dieta'!$A:$F,MATCH(M$8,$L$8:$N$8,0)+3,FALSE)/VLOOKUP($J27,'Base dados dieta'!$A:$F,2,FALSE)*$K27,"") | N27: =IFERROR(VLOOKUP($J27,'Base dados dieta'!$A:$F,MATCH(N$8,$L$8:$N$8,0)+3,FALSE)/VLOOKUP($J27,'Base dados dieta'!$A:$F,2,FALSE)*$K27,"") | O27: =IFERROR(L27*4+M27*9+N27*4,"")
D28: =IFERROR(VLOOKUP($B28,'Base dados dieta'!$A:$F,MATCH(D$8,$D$8:$F$8,0)+3,FALSE)/VLOOKUP($B28,'Base dados dieta'!$A:$F,2,FALSE)*$C28,"") | E28: =IFERROR(VLOOKUP($B28,'Base dados dieta'!$A:$F,MATCH(E$8,$D$8:$F$8,0)+3,FALSE)/VLOOKUP($B28,'Base dados dieta'!$A:$F,2,FALSE)*$C28,"") | F28: =IFERROR(VLOOKUP($B28,'Base dados dieta'!$A:$F,MATCH(F$8,$D$8:$F$8,0)+3,FALSE)/VLOOKUP($B28,'Base dados dieta'!$A:$F,2,FALSE)*$C28,"") | G28: =IFERROR(D28*4+E28*9+F28*4,"") | L28: =IFERROR(VLOOKUP($J28,'Base dados dieta'!$A:$F,MATCH(L$8,$L$8:$N$8,0)+3,FALSE)/VLOOKUP($J28,'Base dados dieta'!$A:$F,2,FALSE)*$K28,"") | M28: =IFERROR(VLOOKUP($J28,'Base dados dieta'!$A:$F,MATCH(M$8,$L$8:$N$8,0)+3,FALSE)/VLOOKUP($J28,'Base dados dieta'!$A:$F,2,FALSE)*$K28,"") | N28: =IFERROR(VLOOKUP($J28,'Base dados dieta'!$A:$F,MATCH(N$8,$L$8:$N$8,0)+3,FALSE)/VLOOKUP($J28,'Base dados dieta'!$A:$F,2,FALSE)*$K28,"") | O28: =IFERROR(L28*4+M28*9+N28*4,"")
D29: =IFERROR(VLOOKUP($B29,'Base dados dieta'!$A:$F,MATCH(D$8,$D$8:$F$8,0)+3,FALSE)/VLOOKUP($B29,'Base dados dieta'!$A:$F,2,FALSE)*$C29,"") | E29: =IFERROR(VLOOKUP($B29,'Base dados dieta'!$A:$F,MATCH(E$8,$D$8:$F$8,0)+3,FALSE)/VLOOKUP($B29,'Base dados dieta'!$A:$F,2,FALSE)*$C29,"") | F29: =IFERROR(VLOOKUP($B29,'Base dados dieta'!$A:$F,MATCH(F$8,$D$8:$F$8,0)+3,FALSE)/VLOOKUP($B29,'Base dados dieta'!$A:$F,2,FALSE)*$C29,"") | G29: =IFERROR(D29*4+E29*9+F29*4,"") | L29: =IFERROR(VLOOKUP($J29,'Base dados dieta'!$A:$F,MATCH(L$8,$L$8:$N$8,0)+3,FALSE)/VLOOKUP($J29,'Base dados dieta'!$A:$F,2,FALSE)*$K29,"") | M29: =IFERROR(VLOOKUP($J29,'Base dados dieta'!$A:$F,MATCH(M$8,$L$8:$N$8,0)+3,FALSE)/VLOOKUP($J29,'Base dados dieta'!$A:$F,2,FALSE)*$K29,"") | N29: =IFERROR(VLOOKUP($J29,'Base dados dieta'!$A:$F,MATCH(N$8,$L$8:$N$8,0)+3,FALSE)/VLOOKUP($J29,'Base dados dieta'!$A:$F,2,FALSE)*$K29,"") | O29: =IFERROR(L29*4+M29*9+N29*4,"")
D30: =IFERROR(VLOOKUP($B30,'Base dados dieta'!$A:$F,MATCH(D$8,$D$8:$F$8,0)+3,FALSE)/VLOOKUP($B30,'Base dados dieta'!$A:$F,2,FALSE)*$C30,"") | E30: =IFERROR(VLOOKUP($B30,'Base dados dieta'!$A:$F,MATCH(E$8,$D$8:$F$8,0)+3,FALSE)/VLOOKUP($B30,'Base dados dieta'!$A:$F,2,FALSE)*$C30,"") | F30: =IFERROR(VLOOKUP($B30,'Base dados dieta'!$A:$F,MATCH(F$8,$D$8:$F$8,0)+3,FALSE)/VLOOKUP($B30,'Base dados dieta'!$A:$F,2,FALSE)*$C30,"") | G30: =IFERROR(D30*4+E30*9+F30*4,"") | O30: =IFERROR(L30*4+M30*9+N30*4,"") -> 0
C31: Total | D31: =SUM(D25:D30) -> 0 | E31: =SUM(E25:E30) -> 0 | F31: =SUM(F25:F30) -> 0 | G31: =SUM(G25:G30) -> 0 | K31: Total | L31: =SUM(L25:L30) -> 0 | M31: =SUM(M25:M30) -> 0 | N31: =SUM(N25:N30) -> 0 | O31: =SUM(O25:O30) -> 0
A33: Refeição 4 | D33: =IFERROR(VLOOKUP($B33,'Base dados dieta'!$A:$F,MATCH(D$8,$D$8:$F$8,0)+3,FALSE)/VLOOKUP($B33,'Base dados dieta'!$A:$F,2,FALSE)*$C33,"") | E33: =IFERROR(VLOOKUP($B33,'Base dados dieta'!$A:$F,MATCH(E$8,$D$8:$F$8,0)+3,FALSE)/VLOOKUP($B33,'Base dados dieta'!$A:$F,2,FALSE)*$C33,"") | F33: =IFERROR(VLOOKUP($B33,'Base dados dieta'!$A:$F,MATCH(F$8,$D$8:$F$8,0)+3,FALSE)/VLOOKUP($B33,'Base dados dieta'!$A:$F,2,FALSE)*$C33,"") | G33: =IFERROR(D33*4+E33*9+F33*4,"") | I33: Refeição 4 | L33: =IFERROR(VLOOKUP($J33,'Base dados dieta'!$A:$F,MATCH(L$8,$L$8:$N$8,0)+3,FALSE)/VLOOKUP($J33,'Base dados dieta'!$A:$F,2,FALSE)*$K33,"") | M33: =IFERROR(VLOOKUP($J33,'Base dados dieta'!$A:$F,MATCH(M$8,$L$8:$N$8,0)+3,FALSE)/VLOOKUP($J33,'Base dados dieta'!$A:$F,2,FALSE)*$K33,"") | N33: =IFERROR(VLOOKUP($J33,'Base dados dieta'!$A:$F,MATCH(N$8,$L$8:$N$8,0)+3,FALSE)/VLOOKUP($J33,'Base dados dieta'!$A:$F,2,FALSE)*$K33,"") | O33: =IFERROR(L33*4+M33*9+N33*4,"")
D34: =IFERROR(VLOOKUP($B34,'Base dados dieta'!$A:$F,MATCH(D$8,$D$8:$F$8,0)+3,FALSE)/VLOOKUP($B34,'Base dados dieta'!$A:$F,2,FALSE)*$C34,"") | E34: =IFERROR(VLOOKUP($B34,'Base dados dieta'!$A:$F,MATCH(E$8,$D$8:$F$8,0)+3,FALSE)/VLOOKUP($B34,'Base dados dieta'!$A:$F,2,FALSE)*$C34,"") | F34: =IFERROR(VLOOKUP($B34,'Base dados dieta'!$A:$F,MATCH(F$8,$D$8:$F$8,0)+3,FALSE)/VLOOKUP($B34,'Base dados dieta'!$A:$F,2,FALSE)*$C34,"") | G34: =IFERROR(D34*4+E34*9+F34*4,"") | L34: =IFERROR(VLOOKUP($J34,'Base dados dieta'!$A:$F,MATCH(L$8,$L$8:$N$8,0)+3,FALSE)/VLOOKUP($J34,'Base dados dieta'!$A:$F,2,FALSE)*$K34,"") | M34: =IFERROR(VLOOKUP($J34,'Base dados dieta'!$A:$F,MATCH(M$8,$L$8:$N$8,0)+3,FALSE)/VLOOKUP($J34,'Base dados dieta'!$A:$F,2,FALSE)*$K34,"") | N34: =IFERROR(VLOOKUP($J34,'Base dados dieta'!$A:$F,MATCH(N$8,$L$8:$N$8,0)+3,FALSE)/VLOOKUP($J34,'Base dados dieta'!$A:$F,2,FALSE)*$K34,"") | O34: =IFERROR(L34*4+M34*9+N34*4,"")
D35: =IFERROR(VLOOKUP($B35,'Base dados dieta'!$A:$F,MATCH(D$8,$D$8:$F$8,0)+3,FALSE)/VLOOKUP($B35,'Base dados dieta'!$A:$F,2,FALSE)*$C35,"") | E35: =IFERROR(VLOOKUP($B35,'Base dados dieta'!$A:$F,MATCH(E$8,$D$8:$F$8,0)+3,FALSE)/VLOOKUP($B35,'Base dados dieta'!$A:$F,2,FALSE)*$C35,"") | F35: =IFERROR(VLOOKUP($B35,'Base dados dieta'!$A:$F,MATCH(F$8,$D$8:$F$8,0)+3,FALSE)/VLOOKUP($B35,'Base dados dieta'!$A:$F,2,FALSE)*$C35,"") | G35: =IFERROR(D35*4+E35*9+F35*4,"") | L35: =IFERROR(VLOOKUP($J35,'Base dados dieta'!$A:$F,MATCH(L$8,$L$8:$N$8,0)+3,FALSE)/VLOOKUP($J35,'Base dados dieta'!$A:$F,2,FALSE)*$K35,"") | M35: =IFERROR(VLOOKUP($J35,'Base dados dieta'!$A:$F,MATCH(M$8,$L$8:$N$8,0)+3,FALSE)/VLOOKUP($J35,'Base dados dieta'!$A:$F,2,FALSE)*$K35,"") | N35: =IFERROR(VLOOKUP($J35,'Base dados dieta'!$A:$F,MATCH(N$8,$L$8:$N$8,0)+3,FALSE)/VLOOKUP($J35,'Base dados dieta'!$A:$F,2,FALSE)*$K35,"") | O35: =IFERROR(L35*4+M35*9+N35*4,"")
D36: =IFERROR(VLOOKUP($B36,'Base dados dieta'!$A:$F,MATCH(D$8,$D$8:$F$8,0)+3,FALSE)/VLOOKUP($B36,'Base dados dieta'!$A:$F,2,FALSE)*$C36,"") | E36: =IFERROR(VLOOKUP($B36,'Base dados dieta'!$A:$F,MATCH(E$8,$D$8:$F$8,0)+3,FALSE)/VLOOKUP($B36,'Base dados dieta'!$A:$F,2,FALSE)*$C36,"") | F36: =IFERROR(VLOOKUP($B36,'Base dados dieta'!$A:$F,MATCH(F$8,$D$8:$F$8,0)+3,FALSE)/VLOOKUP($B36,'Base dados dieta'!$A:$F,2,FALSE)*$C36,"") | G36: =IFERROR(D36*4+E36*9+F36*4,"") | L36: =IFERROR(VLOOKUP($J36,'Base dados dieta'!$A:$F,MATCH(L$8,$L$8:$N$8,0)+3,FALSE)/VLOOKUP($J36,'Base dados dieta'!$A:$F,2,FALSE)*$K36,"") | M36: =IFERROR(VLOOKUP($J36,'Base dados dieta'!$A:$F,MATCH(M$8,$L$8:$N$8,0)+3,FALSE)/VLOOKUP($J36,'Base dados dieta'!$A:$F,2,FALSE)*$K36,"") | N36: =IFERROR(VLOOKUP($J36,'Base dados dieta'!$A:$F,MATCH(N$8,$L$8:$N$8,0)+3,FALSE)/VLOOKUP($J36,'Base dados dieta'!$A:$F,2,FALSE)*$K36,"") | O36: =IFERROR(L36*4+M36*9+N36*4,"")
D37: =IFERROR(VLOOKUP($B37,'Base dados dieta'!$A:$F,MATCH(D$8,$D$8:$F$8,0)+3,FALSE)/VLOOKUP($B37,'Base dados dieta'!$A:$F,2,FALSE)*$C37,"") | E37: =IFERROR(VLOOKUP($B37,'Base dados dieta'!$A:$F,MATCH(E$8,$D$8:$F$8,0)+3,FALSE)/VLOOKUP($B37,'Base dados dieta'!$A:$F,2,FALSE)*$C37,"") | F37: =IFERROR(VLOOKUP($B37,'Base dados dieta'!$A:$F,MATCH(F$8,$D$8:$F$8,0)+3,FALSE)/VLOOKUP($B37,'Base dados dieta'!$A:$F,2,FALSE)*$C37,"") | G37: =IFERROR(D37*4+E37*9+F37*4,"") | L37: =IFERROR(VLOOKUP($J37,'Base dados dieta'!$A:$F,MATCH(L$8,$L$8:$N$8,0)+3,FALSE)/VLOOKUP($J37,'Base dados dieta'!$A:$F,2,FALSE)*$K37,"") | M37: =IFERROR(VLOOKUP($J37,'Base dados dieta'!$A:$F,MATCH(M$8,$L$8:$N$8,0)+3,FALSE)/VLOOKUP($J37,'Base dados dieta'!$A:$F,2,FALSE)*$K37,"") | N37: =IFERROR(VLOOKUP($J37,'Base dados dieta'!$A:$F,MATCH(N$8,$L$8:$N$8,0)+3,FALSE)/VLOOKUP($J37,'Base dados dieta'!$A:$F,2,FALSE)*$K37,"") | O37: =IFERROR(L37*4+M37*9+N37*4,"")
D38: =IFERROR(VLOOKUP($B38,'Base dados dieta'!$A:$F,MATCH(D$8,$D$8:$F$8,0)+3,FALSE)/VLOOKUP($B38,'Base dados dieta'!$A:$F,2,FALSE)*$C38,"") | E38: =IFERROR(VLOOKUP($B38,'Base dados dieta'!$A:$F,MATCH(E$8,$D$8:$F$8,0)+3,FALSE)/VLOOKUP($B38,'Base dados dieta'!$A:$F,2,FALSE)*$C38,"") | F38: =IFERROR(VLOOKUP($B38,'Base dados dieta'!$A:$F,MATCH(F$8,$D$8:$F$8,0)+3,FALSE)/VLOOKUP($B38,'Base dados dieta'!$A:$F,2,FALSE)*$C38,"") | G38: =IFERROR(D38*4+E38*9+F38*4,"") | O38: =IFERROR(L38*4+M38*9+N38*4,"") -> 0
C39: Total | D39: =SUM(D33:D38) -> 0 | E39: =SUM(E33:E38) -> 0 | F39: =SUM(F33:F38) -> 0 | G39: =SUM(G33:G38) -> 0 | K39: Total | L39: =SUM(L33:L38) -> 0 | M39: =SUM(M33:M38) -> 0 | N39: =SUM(N33:N38) -> 0 | O39: =SUM(O33:O38) -> 0
A41: Refeição 5 | D41: =IFERROR(VLOOKUP($B41,'Base dados dieta'!$A:$F,MATCH(D$8,$D$8:$F$8,0)+3,FALSE)/VLOOKUP($B41,'Base dados dieta'!$A:$F,2,FALSE)*$C41,"") | E41: =IFERROR(VLOOKUP($B41,'Base dados dieta'!$A:$F,MATCH(E$8,$D$8:$F$8,0)+3,FALSE)/VLOOKUP($B41,'Base dados dieta'!$A:$F,2,FALSE)*$C41,"") | F41: =IFERROR(VLOOKUP($B41,'Base dados dieta'!$A:$F,MATCH(F$8,$D$8:$F$8,0)+3,FALSE)/VLOOKUP($B41,'Base dados dieta'!$A:$F,2,FALSE)*$C41,"") | G41: =IFERROR(D41*4+E41*9+F41*4,"") | I41: Refeição 5 | L41: =IFERROR(VLOOKUP($J41,'Base dados dieta'!$A:$F,MATCH(L$8,$L$8:$N$8,0)+3,FALSE)/VLOOKUP($J41,'Base dados dieta'!$A:$F,2,FALSE)*$K41,"") | M41: =IFERROR(VLOOKUP($J41,'Base dados dieta'!$A:$F,MATCH(M$8,$L$8:$N$8,0)+3,FALSE)/VLOOKUP($J41,'Base dados dieta'!$A:$F,2,FALSE)*$K41,"") | N41: =IFERROR(VLOOKUP($J41,'Base dados dieta'!$A:$F,MATCH(N$8,$L$8:$N$8,0)+3,FALSE)/VLOOKUP($J41,'Base dados dieta'!$A:$F,2,FALSE)*$K41,"") | O41: =IFERROR(L41*4+M41*9+N41*4,"")
D42: =IFERROR(VLOOKUP($B42,'Base dados dieta'!$A:$F,MATCH(D$8,$D$8:$F$8,0)+3,FALSE)/VLOOKUP($B42,'Base dados dieta'!$A:$F,2,FALSE)*$C42,"") | E42: =IFERROR(VLOOKUP($B42,'Base dados dieta'!$A:$F,MATCH(E$8,$D$8:$F$8,0)+3,FALSE)/VLOOKUP($B42,'Base dados dieta'!$A:$F,2,FALSE)*$C42,"") | F42: =IFERROR(VLOOKUP($B42,'Base dados dieta'!$A:$F,MATCH(F$8,$D$8:$F$8,0)+3,FALSE)/VLOOKUP($B42,'Base dados dieta'!$A:$F,2,FALSE)*$C42,"") | G42: =IFERROR(D42*4+E42*9+F42*4,"") | L42: =IFERROR(VLOOKUP($J42,'Base dados dieta'!$A:$F,MATCH(L$8,$L$8:$N$8,0)+3,FALSE)/VLOOKUP($J42,'Base dados dieta'!$A:$F,2,FALSE)*$K42,"") | M42: =IFERROR(VLOOKUP($J42,'Base dados dieta'!$A:$F,MATCH(M$8,$L$8:$N$8,0)+3,FALSE)/VLOOKUP($J42,'Base dados dieta'!$A:$F,2,FALSE)*$K42,"") | N42: =IFERROR(VLOOKUP($J42,'Base dados dieta'!$A:$F,MATCH(N$8,$L$8:$N$8,0)+3,FALSE)/VLOOKUP($J42,'Base dados dieta'!$A:$F,2,FALSE)*$K42,"") | O42: =IFERROR(L42*4+M42*9+N42*4,"")
D43: =IFERROR(VLOOKUP($B43,'Base dados dieta'!$A:$F,MATCH(D$8,$D$8:$F$8,0)+3,FALSE)/VLOOKUP($B43,'Base dados dieta'!$A:$F,2,FALSE)*$C43,"") | E43: =IFERROR(VLOOKUP($B43,'Base dados dieta'!$A:$F,MATCH(E$8,$D$8:$F$8,0)+3,FALSE)/VLOOKUP($B43,'Base dados dieta'!$A:$F,2,FALSE)*$C43,"") | F43: =IFERROR(VLOOKUP($B43,'Base dados dieta'!$A:$F,MATCH(F$8,$D$8:$F$8,0)+3,FALSE)/VLOOKUP($B43,'Base dados dieta'!$A:$F,2,FALSE)*$C43,"") | G43: =IFERROR(D43*4+E43*9+F43*4,"") | L43: =IFERROR(VLOOKUP($J43,'Base dados dieta'!$A:$F,MATCH(L$8,$L$8:$N$8,0)+3,FALSE)/VLOOKUP($J43,'Base dados dieta'!$A:$F,2,FALSE)*$K43,"") | M43: =IFERROR(VLOOKUP($J43,'Base dados dieta'!$A:$F,MATCH(M$8,$L$8:$N$8,0)+3,FALSE)/VLOOKUP($J43,'Base dados dieta'!$A:$F,2,FALSE)*$K43,"") | N43: =IFERROR(VLOOKUP($J43,'Base dados dieta'!$A:$F,MATCH(N$8,$L$8:$N$8,0)+3,FALSE)/VLOOKUP($J43,'Base dados dieta'!$A:$F,2,FALSE)*$K43,"") | O43: =IFERROR(L43*4+M43*9+N43*4,"")
D44: =IFERROR(VLOOKUP($B44,'Base dados dieta'!$A:$F,MATCH(D$8,$D$8:$F$8,0)+3,FALSE)/VLOOKUP($B44,'Base dados dieta'!$A:$F,2,FALSE)*$C44,"") | E44: =IFERROR(VLOOKUP($B44,'Base dados dieta'!$A:$F,MATCH(E$8,$D$8:$F$8,0)+3,FALSE)/VLOOKUP($B44,'Base dados dieta'!$A:$F,2,FALSE)*$C44,"") | F44: =IFERROR(VLOOKUP($B44,'Base dados dieta'!$A:$F,MATCH(F$8,$D$8:$F$8,0)+3,FALSE)/VLOOKUP($B44,'Base dados dieta'!$A:$F,2,FALSE)*$C44,"") | G44: =IFERROR(D44*4+E44*9+F44*4,"") | L44: =IFERROR(VLOOKUP($J44,'Base dados dieta'!$A:$F,MATCH(L$8,$L$8:$N$8,0)+3,FALSE)/VLOOKUP($J44,'Base dados dieta'!$A:$F,2,FALSE)*$K44,"") | M44: =IFERROR(VLOOKUP($J44,'Base dados dieta'!$A:$F,MATCH(M$8,$L$8:$N$8,0)+3,FALSE)/VLOOKUP($J44,'Base dados dieta'!$A:$F,2,FALSE)*$K44,"") | N44: =IFERROR(VLOOKUP($J44,'Base dados dieta'!$A:$F,MATCH(N$8,$L$8:$N$8,0)+3,FALSE)/VLOOKUP($J44,'Base dados dieta'!$A:$F,2,FALSE)*$K44,"") | O44: =IFERROR(L44*4+M44*9+N44*4,"")
D45: =IFERROR(VLOOKUP($B45,'Base dados dieta'!$A:$F,MATCH(D$8,$D$8:$F$8,0)+3,FALSE)/VLOOKUP($B45,'Base dados dieta'!$A:$F,2,FALSE)*$C45,"") | E45: =IFERROR(VLOOKUP($B45,'Base dados dieta'!$A:$F,MATCH(E$8,$D$8:$F$8,0)+3,FALSE)/VLOOKUP($B45,'Base dados dieta'!$A:$F,2,FALSE)*$C45,"") | F45: =IFERROR(VLOOKUP($B45,'Base dados dieta'!$A:$F,MATCH(F$8,$D$8:$F$8,0)+3,FALSE)/VLOOKUP($B45,'Base dados dieta'!$A:$F,2,FALSE)*$C45,"") | G45: =IFERROR(D45*4+E45*9+F45*4,"") | L45: =IFERROR(VLOOKUP($J45,'Base dados dieta'!$A:$F,MATCH(L$8,$L$8:$N$8,0)+3,FALSE)/VLOOKUP($J45,'Base dados dieta'!$A:$F,2,FALSE)*$K45,"") | M45: =IFERROR(VLOOKUP($J45,'Base dados dieta'!$A:$F,MATCH(M$8,$L$8:$N$8,0)+3,FALSE)/VLOOKUP($J45,'Base dados dieta'!$A:$F,2,FALSE)*$K45,"") | N45: =IFERROR(VLOOKUP($J45,'Base dados dieta'!$A:$F,MATCH(N$8,$L$8:$N$8,0)+3,FALSE)/VLOOKUP($J45,'Base dados dieta'!$A:$F,2,FALSE)*$K45,"") | O45: =IFERROR(L45*4+M45*9+N45*4,"")
D46: =IFERROR(VLOOKUP($B46,'Base dados dieta'!$A:$F,MATCH(D$8,$D$8:$F$8,0)+3,FALSE)/VLOOKUP($B46,'Base dados dieta'!$A:$F,2,FALSE)*$C46,"") | E46: =IFERROR(VLOOKUP($B46,'Base dados dieta'!$A:$F,MATCH(E$8,$D$8:$F$8,0)+3,FALSE)/VLOOKUP($B46,'Base dados dieta'!$A:$F,2,FALSE)*$C46,"") | F46: =IFERROR(VLOOKUP($B46,'Base dados dieta'!$A:$F,MATCH(F$8,$D$8:$F$8,0)+3,FALSE)/VLOOKUP($B46,'Base dados dieta'!$A:$F,2,FALSE)*$C46,"") | G46: =IFERROR(D46*4+E46*9+F46*4,"") | O46: =IFERROR(L46*4+M46*9+N46*4,"") -> 0
C47: Total | D47: =SUM(D41:D46) -> 0 | E47: =SUM(E41:E46) -> 0 | F47: =SUM(F41:F46) -> 0 | G47: =SUM(G41:G46) -> 0 | K47: Total | L47: =SUM(L41:L46) -> 0 | M47: =SUM(M41:M46) -> 0 | N47: =SUM(N41:N46) -> 0 | O47: =SUM(O41:O46) -> 0
A49: Refeição 6 | D49: =IFERROR(VLOOKUP($B49,'Base dados dieta'!$A:$F,MATCH(D$8,$D$8:$F$8,0)+3,FALSE)/VLOOKUP($B49,'Base dados dieta'!$A:$F,2,FALSE)*$C49,"") | E49: =IFERROR(VLOOKUP($B49,'Base dados dieta'!$A:$F,MATCH(E$8,$D$8:$F$8,0)+3,FALSE)/VLOOKUP($B49,'Base dados dieta'!$A:$F,2,FALSE)*$C49,"") | F49: =IFERROR(VLOOKUP($B49,'Base dados dieta'!$A:$F,MATCH(F$8,$D$8:$F$8,0)+3,FALSE)/VLOOKUP($B49,'Base dados dieta'!$A:$F,2,FALSE)*$C49,"") | G49: =IFERROR(D49*4+E49*9+F49*4,"") | I49: Refeição 6 | L49: =IFERROR(VLOOKUP($J49,'Base dados dieta'!$A:$F,MATCH(L$8,$L$8:$N$8,0)+3,FALSE)/VLOOKUP($J49,'Base dados dieta'!$A:$F,2,FALSE)*$K49,"") | M49: =IFERROR(VLOOKUP($J49,'Base dados dieta'!$A:$F,MATCH(M$8,$L$8:$N$8,0)+3,FALSE)/VLOOKUP($J49,'Base dados dieta'!$A:$F,2,FALSE)*$K49,"") | N49: =IFERROR(VLOOKUP($J49,'Base dados dieta'!$A:$F,MATCH(N$8,$L$8:$N$8,0)+3,FALSE)/VLOOKUP($J49,'Base dados dieta'!$A:$F,2,FALSE)*$K49,"") | O49: =IFERROR(L49*4+M49*9+N49*4,"")
D50: =IFERROR(VLOOKUP($B50,'Base dados dieta'!$A:$F,MATCH(D$8,$D$8:$F$8,0)+3,FALSE)/VLOOKUP($B50,'Base dados dieta'!$A:$F,2,FALSE)*$C50,"") | E50: =IFERROR(VLOOKUP($B50,'Base dados dieta'!$A:$F,MATCH(E$8,$D$8:$F$8,0)+3,FALSE)/VLOOKUP($B50,'Base dados dieta'!$A:$F,2,FALSE)*$C50,"") | F50: =IFERROR(VLOOKUP($B50,'Base dados dieta'!$A:$F,MATCH(F$8,$D$8:$F$8,0)+3,FALSE)/VLOOKUP($B50,'Base dados dieta'!$A:$F,2,FALSE)*$C50,"") | G50: =IFERROR(D50*4+E50*9+F50*4,"") | L50: =IFERROR(VLOOKUP($J50,'Base dados dieta'!$A:$F,MATCH(L$8,$L$8:$N$8,0)+3,FALSE)/VLOOKUP($J50,'Base dados dieta'!$A:$F,2,FALSE)*$K50,"") | M50: =IFERROR(VLOOKUP($J50,'Base dados dieta'!$A:$F,MATCH(M$8,$L$8:$N$8,0)+3,FALSE)/VLOOKUP($J50,'Base dados dieta'!$A:$F,2,FALSE)*$K50,"") | N50: =IFERROR(VLOOKUP($J50,'Base dados dieta'!$A:$F,MATCH(N$8,$L$8:$N$8,0)+3,FALSE)/VLOOKUP($J50,'Base dados dieta'!$A:$F,2,FALSE)*$K50,"") | O50: =IFERROR(L50*4+M50*9+N50*4,"")
D51: =IFERROR(VLOOKUP($B51,'Base dados dieta'!$A:$F,MATCH(D$8,$D$8:$F$8,0)+3,FALSE)/VLOOKUP($B51,'Base dados dieta'!$A:$F,2,FALSE)*$C51,"") | E51: =IFERROR(VLOOKUP($B51,'Base dados dieta'!$A:$F,MATCH(E$8,$D$8:$F$8,0)+3,FALSE)/VLOOKUP($B51,'Base dados dieta'!$A:$F,2,FALSE)*$C51,"") | F51: =IFERROR(VLOOKUP($B51,'Base dados dieta'!$A:$F,MATCH(F$8,$D$8:$F$8,0)+3,FALSE)/VLOOKUP($B51,'Base dados dieta'!$A:$F,2,FALSE)*$C51,"") | G51: =IFERROR(D51*4+E51*9+F51*4,"") | L51: =IFERROR(VLOOKUP($J51,'Base dados dieta'!$A:$F,MATCH(L$8,$L$8:$N$8,0)+3,FALSE)/VLOOKUP($J51,'Base dados dieta'!$A:$F,2,FALSE)*$K51,"") | M51: =IFERROR(VLOOKUP($J51,'Base dados dieta'!$A:$F,MATCH(M$8,$L$8:$N$8,0)+3,FALSE)/VLOOKUP($J51,'Base dados dieta'!$A:$F,2,FALSE)*$K51,"") | N51: =IFERROR(VLOOKUP($J51,'Base dados dieta'!$A:$F,MATCH(N$8,$L$8:$N$8,0)+3,FALSE)/VLOOKUP($J51,'Base dados dieta'!$A:$F,2,FALSE)*$K51,"") | O51: =IFERROR(L51*4+M51*9+N51*4,"")
D52: =IFERROR(VLOOKUP($B52,'Base dados dieta'!$A:$F,MATCH(D$8,$D$8:$F$8,0)+3,FALSE)/VLOOKUP($B52,'Base dados dieta'!$A:$F,2,FALSE)*$C52,"") | E52: =IFERROR(VLOOKUP($B52,'Base dados dieta'!$A:$F,MATCH(E$8,$D$8:$F$8,0)+3,FALSE)/VLOOKUP($B52,'Base dados dieta'!$A:$F,2,FALSE)*$C52,"") | F52: =IFERROR(VLOOKUP($B52,'Base dados dieta'!$A:$F,MATCH(F$8,$D$8:$F$8,0)+3,FALSE)/VLOOKUP($B52,'Base dados dieta'!$A:$F,2,FALSE)*$C52,"") | G52: =IFERROR(D52*4+E52*9+F52*4,"") | L52: =IFERROR(VLOOKUP($J52,'Base dados dieta'!$A:$F,MATCH(L$8,$L$8:$N$8,0)+3,FALSE)/VLOOKUP($J52,'Base dados dieta'!$A:$F,2,FALSE)*$K52,"") | M52: =IFERROR(VLOOKUP($J52,'Base dados dieta'!$A:$F,MATCH(M$8,$L$8:$N$8,0)+3,FALSE)/VLOOKUP($J52,'Base dados dieta'!$A:$F,2,FALSE)*$K52,"") | N52: =IFERROR(VLOOKUP($J52,'Base dados dieta'!$A:$F,MATCH(N$8,$L$8:$N$8,0)+3,FALSE)/VLOOKUP($J52,'Base dados dieta'!$A:$F,2,FALSE)*$K52,"") | O52: =IFERROR(L52*4+M52*9+N52*4,"")
D53: =IFERROR(VLOOKUP($B53,'Base dados dieta'!$A:$F,MATCH(D$8,$D$8:$F$8,0)+3,FALSE)/VLOOKUP($B53,'Base dados dieta'!$A:$F,2,FALSE)*$C53,"") | E53: =IFERROR(VLOOKUP($B53,'Base dados dieta'!$A:$F,MATCH(E$8,$D$8:$F$8,0)+3,FALSE)/VLOOKUP($B53,'Base dados dieta'!$A:$F,2,FALSE)*$C53,"") | F53: =IFERROR(VLOOKUP($B53,'Base dados dieta'!$A:$F,MATCH(F$8,$D$8:$F$8,0)+3,FALSE)/VLOOKUP($B53,'Base dados dieta'!$A:$F,2,FALSE)*$C53,"") | G53: =IFERROR(D53*4+E53*9+F53*4,"") | L53: =IFERROR(VLOOKUP($J53,'Base dados dieta'!$A:$F,MATCH(L$8,$L$8:$N$8,0)+3,FALSE)/VLOOKUP($J53,'Base dados dieta'!$A:$F,2,FALSE)*$K53,"") | M53: =IFERROR(VLOOKUP($J53,'Base dados dieta'!$A:$F,MATCH(M$8,$L$8:$N$8,0)+3,FALSE)/VLOOKUP($J53,'Base dados dieta'!$A:$F,2,FALSE)*$K53,"") | N53: =IFERROR(VLOOKUP($J53,'Base dados dieta'!$A:$F,MATCH(N$8,$L$8:$N$8,0)+3,FALSE)/VLOOKUP($J53,'Base dados dieta'!$A:$F,2,FALSE)*$K53,"") | O53: =IFERROR(L53*4+M53*9+N53*4,"")
D54: =IFERROR(VLOOKUP($B54,'Base dados dieta'!$A:$F,MATCH(D$8,$D$8:$F$8,0)+3,FALSE)/VLOOKUP($B54,'Base dados dieta'!$A:$F,2,FALSE)*$C54,"") | E54: =IFERROR(VLOOKUP($B54,'Base dados dieta'!$A:$F,MATCH(E$8,$D$8:$F$8,0)+3,FALSE)/VLOOKUP($B54,'Base dados dieta'!$A:$F,2,FALSE)*$C54,"") | F54: =IFERROR(VLOOKUP($B54,'Base dados dieta'!$A:$F,MATCH(F$8,$D$8:$F$8,0)+3,FALSE)/VLOOKUP($B54,'Base dados dieta'!$A:$F,2,FALSE)*$C54,"") | G54: =IFERROR(D54*4+E54*9+F54*4,"") | O54: =IFERROR(L54*4+M54*9+N54*4,"") -> 0
C55: Total | D55: =SUM(D49:D54) -> 0 | E55: =SUM(E49:E54) -> 0 | F55: =SUM(F49:F54) -> 0 | G55: =SUM(G49:G54) -> 0 | K55: Total | L55: =SUM(L49:L54) -> 0 | M55: =SUM(M49:M54) -> 0 | N55: =SUM(N49:N54) -> 0 | O55: =SUM(O49:O54) -> 0

Sheet Base dados dieta
A1: Alimento | B1: Quant. | C1: Unid. | D1: Proteina | E1: Gordura | F1: Hidratos
A2: Frango grelhado | B2: 100 | C2: g | D2: 32 | E2: 2.5 | F2: 0
A3: Frango cozido | B3: 100 | C3: g | D3: 24 | E3: 2 | F3: 0
A4: lula cozida | B4: 100 | C4: g | D4: 15.6 | E4: 0.9 | F4: 0
A5: lula grelhada | B5: 100 | C5: g | D5: 32.5 | E5: 1.6 | F5: 0
A6: Atum ao natural | B6: 100 | C6: g | D6: 19 | E6: 0.5 | F6: 0.5
A7: Peixe magro cozido | B7: 100 | C7: g | D7: 20.1 | E7: 0.9 | F7: 0
A8: whey | B8: 100 | C8: g | D8: 75 | E8: 6.5 | F8: 6.5
A9: camaroes cozidos | B9: 100 | C9: g | D9: 22.4 | E9: 1 | F9: 0.4
A10: claras de ovo | B10: 100 | C10: g | D10: 10 | E10: 0 | F10: 0.7
A11: seitan | B11: 100 | C11: g | D11: 22.1 | E11: 1.6 | F11: 3.5
A12: nacos soja cru | B12: 100 | C12: g | D12: 47 | E12: 1.3 | F12: 17.9
A13: skyr | B13: 100 | C13: g | D13: 11 | E13: 0.2 | F13: 4
... A1374: Vinho verde tinto | B1374: 100 | C1374: g | D1374: 4.8 | E1374: 0.6 | F1374: 15.8
A1375: Wasabi, raiz crua | B1375: 100 | C1375: g
